Workbook
Name \a: #REF!
Name \b: #REF!
Name \g: #REF!
Name \p: #REF!
Name __123Graph_A: '[2]#REF'!$E$11:$L$11
Name __123Graph_A: '[3]#REF'!$E$11:$L$11
Name __123Graph_B: '[2]#REF'!$E$12:$L$12
Name __123Graph_B: '[3]#REF'!$E$12:$L$12
Name __123Graph_C: '[2]#REF'!$E$10:$L$10
Name __123Graph_C: '[3]#REF'!$E$10:$L$10
Name __123Graph_X: '[2]#REF'!$E$8:$L$8
Name __123Graph_X: '[3]#REF'!$E$8:$L$8
Name _123: #REF!
Name _123: #REF!
Name _123: #REF!
Name _2IMPORT_RANGE: '[5]#REF'!$A$2:$K$34
Name _5IMPORT_RANGE: '[2]#REF'!$A$2:$K$34
Name _6IMPORT_RANGE: '[3]#REF'!$A$2:$K$34
Name _PS1: '[5]#REF'!$A$1:$X$45
Name _PS1: '[2]#REF'!$A$1:$X$45
Name _PS1: '[3]#REF'!$A$1:$X$45
Name _PS10: '[5]#REF'!$A$1:$Q$63
Name _PS10: '[2]#REF'!$A$1:$Q$63
Name _PS10: '[3]#REF'!$A$1:$Q$63
Name _PS11: '[5]#REF'!$A$1:$X$64
Name _PS11: '[2]#REF'!$A$1:$X$64
Name _PS11: '[3]#REF'!$A$1:$X$64
Name _PS12: '[5]#REF'!$A$1:$P$58
Name _PS12: '[2]#REF'!$A$1:$P$58
Name _PS12: '[3]#REF'!$A$1:$P$58
Name _PS13: '[5]#REF'!$A$1:$U$60
Name _PS13: '[2]#REF'!$A$1:$U$60
Name _PS13: '[3]#REF'!$A$1:$U$60
Name _PS14: '[5]#REF'!#REF!
Name _PS14: '[2]#REF'!#REF!
Name _PS14: '[3]#REF'!#REF!
Name _PS15: '[5]#REF'!$A$1:$Z$44
Name _PS15: '[2]#REF'!$A$1:$Z$44
Name _PS15: '[3]#REF'!$A$1:$Z$44
Name _PS16: '[5]#REF'!$A$1:$M$60
Name _PS16: '[2]#REF'!$A$1:$M$60
Name _PS16: '[3]#REF'!$A$1:$M$60
Name _PS17: '[5]#REF'!$B$1:$T$50
Name _PS17: '[2]#REF'!$B$1:$T$50
Name _PS17: '[3]#REF'!$B$1:$T$50
Name _PS18: '[5]#REF'!$A$1:$U$63
Name _PS18: '[2]#REF'!$A$1:$U$63
Name _PS18: '[3]#REF'!$A$1:$U$63
Name _PS19: '[5]#REF'!$A$1:$S$48
Name _PS19: '[2]#REF'!$A$1:$S$48
Name _PS19: '[3]#REF'!$A$1:$S$48
Name _PS2: '[5]#REF'!$A$1:$W$65
Name _PS2: '[2]#REF'!$A$1:$W$65
Name _PS2: '[3]#REF'!$A$1:$W$65
Name _PS3: '[5]#REF'!$A$1:$W$82
Name _PS3: '[2]#REF'!$A$1:$W$82
Name _PS3: '[3]#REF'!$A$1:$W$82
Name _PS4: '[5]#REF'!$A$1:$V$63
Name _PS4: '[2]#REF'!$A$1:$V$63
Name _PS4: '[3]#REF'!$A$1:$V$63

Sheet Considerações
B7: Principais Premissas | C7: Crescimento | D7: Margem Ebitda | E7: Investimento (Capex) | F7: Capital de giro
B8: Cenários
B9: =Output!B3 -> Base Case
B10: =Output!B4 -> Cliente Case
B11: =Output!B5 & " (Ainda a definir)" -> Stress Case (Ainda a definir)

Sheet Capa
C4: Unimed Rio
C6: Projeções Financeiras

Sheet Output
B2: SCENARIO | G2: 1 | I2: Check Scenario
B3: Base Case | G3: 1 | I3: Revenues, COGS & SG&A | L3: ='Revenues, COGS & SG&A'!C3 -> 1
B4: Cliente Case | G4: 2 | I4: Fixed Assets & CAPEX | L4: ='Fixed Assets & CAPEX'!C3 -> 1
B5: Stress Case | G5: 3 | I5: Working Capital | L5: ='Working Capital'!C3 -> 1
B8: SUMMARY
B9: R$ million - nominal | G9: 2010 | H9: =G9+1 -> 2011 | I9: =H9+1 -> 2012 | J9: =I9+1 -> 2013 | K9: =J9+1 -> 2014 | L9: =K9+1 -> 2015 | M9: =L9+1 -> 2016 | N9: =M9+1 -> 2017 | O9: =N9+1 -> 2018 | ... AB9: =AA9+1 -> 2031
B10: Net Revenues | G10: ='Income Statement'!H24 -> 2434971 | H10: ='Income Statement'!I24 -> 2853511 | I10: ='Income Statement'!J24 -> 3068721.7 | J10: ='Income Statement'!K24 -> 3352129.3 | K10: ='Income Statement'!L24 -> 3604529.7 | L10: ='Income Statement'!M24 -> 3881886.1 | M10: ='Income Statement'!N24 -> 4190073.4 | N10: ='Income Statement'!O24 -> 4520937.5 | ... AB10: ='Income Statement'!AC24 -> 12878274
B11: % Growth | G11: =(G10-F10)/F10 -> #DIV/0! | H11: =(H10-G10)/G10 -> 0.17188706 | I11: =(I10-H10)/H10 -> 0.075419627 | J11: =(J10-I10)/I10 -> 0.092353609 | K11: =(K10-J10)/J10 -> 0.075295561 | L11: =(L10-K10)/K10 -> 0.076946626 | M11: =(M10-L10)/L10 -> 0.07939113 | N11: =(N10-M10)/M10 -> 0.078963777 | ... AB11: =(AB10-AA10)/AA10 -> 0 | AE11: 2009 | AF11: 2010 | AG11: 2011 | AH11: 2012 | AI11: 2013 | AJ11: 2014 | AK11: 2015 | AO11: Cenário | AP11: Índice | AQ11: 2009 | AR11: 2010 | AS11: 2013 | AT11: =AS11+1 -> 2014 | AU11: =AT11+1 -> 2015 | AV11: =AU11+1 -> 2016 | AW11: =AV11+1 -> 2017 | AX11: =AW11+1 -> 2018 | AY11: =AX11+1 -> 2019 | AZ11: =AY11+1 -> 2020 | BA11: 2019 | BB11: 2020
B12: EBITDA | G12: ='Income Statement'!H42 -> 82461 | H12: ='Income Statement'!I42 -> 115501 | I12: ='Income Statement'!J42 -> 95584.45 | J12: ='Income Statement'!K42 -> 118167.81 | K12: ='Income Statement'!L42 -> 165665.86 | L12: ='Income Statement'!M42 -> 164205.03 | M12: ='Income Statement'!N42 -> 130003.15 | N12: ='Income Statement'!O42 -> 138513.19 | ... AB12: ='Income Statement'!AC42 -> 516528.38 | AD12: Ebitda | AE12: =G12 -> 82461 | AF12: =H12 -> 115501 | AG12: =I12 -> 95584.45 | AH12: =J12 -> 118167.81 | AI12: =K12 -> 165665.86 | AJ12: =L12 -> 164205.03 | AK12: =M12 -> 130003.15 | AO12: Base Case | AP12: Base Case | AS12: 0.040205585 | AT12: 0.04465238 | AU12: 0.045140839 | AV12: 0.046529054 | AW12: 0.047550553 | AX12: 0.048846226
B13: % Growth | G13: =(G12-F12)/F12 -> #DIV/0! | H13: =(H12-G12)/G12 -> 0.40067426 | I13: =(I12-H12)/H12 -> -0.17243617 | J13: =(J12-I12)/I12 -> 0.23626602 | K13: =(K12-J12)/J12 -> 0.40195422 | L13: =(L12-K12)/K12 -> -0.0088178805 | M13: =(M12-L12)/L12 -> -0.20828764 | N13: =(N12-M12)/M12 -> 0.065460259 | ... AB13: =(AB12-AA12)/AA12 -> -0.0067930673 | AD13: 2*Ebitda | AE13: =2*AE12 -> 164922 | AF13: =2*AF12 -> 231002 | AG13: =2*AG12 -> 191168.9 | AH13: =2*AH12 -> 236335.61 | AI13: =2*AI12 -> 331331.71 | AJ13: =2*AJ12 -> 328410.07 | AK13: =2*AK12 -> 260006.31 | AO13: Client Case | AP13: =B$25&" "&AO13 -> Variação NCG Client Case | AS13: -1130.3121 | AT13: -10886.227 | AU13: -12264.204 | AV13: -15929.103 | AW13: -14631.611 | AX13: -11863.965 | AY13: 2.3029296
B14: % EBITDA Margin | G14: =G12/G10 -> 0.03386529 | H14: =H12/H10 -> 0.040476802 | I14: =I12/I10 -> 0.031147969 | J14: =J12/J10 -> 0.035251566 | K14: =K12/K10 -> 0.045960463 | L14: =L12/L10 -> 0.042300322 | M14: =M12/M10 -> 0.031026462 | N14: =N12/N10 -> 0.030638158 | ... AB14: =AB12/AB10 -> 0.040108509 | AD14: Caixa | AE14: =G32 -> 119958 | AF14: =H32 -> 228486 | AG14: =I32 -> 149443.51 | AH14: =J32 -> 165864.86 | AI14: =K32 -> 120594.37 | AJ14: =L32 -> 70000 | AK14: =M32 -> 70000 | AO14: Stress Case | AP14: Stress Case | AS14: 0.03307451 | AT14: 0.032433557 | AU14: 0.031969457 | AV14: 0.031026462 | AW14: 0.030638158 | AX14: 0.030498388 | AY14: =O14 -> 0.030498388 | AZ14: =P14 -> 0.050102562
B15: Amortization Bancos | G15: n.a. | H15: n.a. | I15: ='ST Inv. & Debt'!H126 -> 0 | J15: ='ST Inv. & Debt'!I126 -> 0 | K15: ='ST Inv. & Debt'!J126 -> 0 | L15: ='ST Inv. & Debt'!K126 -> 0 | M15: ='ST Inv. & Debt'!L126 -> 0.33333333 | N15: ='ST Inv. & Debt'!M126 -> 0.33333333 | O15: ='ST Inv. & Debt'!N126 -> 0.33333333 | P15: ='ST Inv. & Debt'!O126 -> 0 | ... AB15: ='ST Inv. & Debt'!AA126 -> 0 | AD15: Dívida total permitida | AE15: =AE13+AE14 -> 284880 | AF15: =AF13+AF14 -> 459488 | AG15: =AG13+AG14 -> 340612.41 | AH15: =AH13+AH14 -> 402200.47 | AI15: =AI13+AI14 -> 451926.08 | AJ15: =AJ13+AJ14 -> 398410.07 | AK15: =AK13+AK14 -> 330006.31 | AP15: Corte Sugerido | AQ15: =$AX15 -> 0 | AR15: =$AX15 -> 0 | AY15: 0.8
B16: Net Profit | G16: ='Income Statement'!H81 -> 32615 | H16: ='Income Statement'!I81 -> 51805 | I16: ='Income Statement'!J81 -> 19970.898 | J16: ='Income Statement'!K81 -> 23388.519 | K16: ='Income Statement'!L81 -> 40022.884 | L16: ='Income Statement'!M81 -> 34441.552 | M16: ='Income Statement'!N81 -> 5830.7836 | N16: ='Income Statement'!O81 -> -24.583116 | ... AB16: ='Income Statement'!AC81 -> #VALUE!
B17: Capex | G17: nd | H17: nd | I17: ='Fixed Assets & CAPEX'!H37 -> 139000 | J17: ='Fixed Assets & CAPEX'!I37 -> 107863.74 | K17: ='Fixed Assets & CAPEX'!J37 -> 63272.849 | L17: ='Fixed Assets & CAPEX'!K37 -> 72311.827 | M17: ='Fixed Assets & CAPEX'!L37 -> 82642.088 | N17: ='Fixed Assets & CAPEX'!M37 -> 94448.101 | O17: ='Fixed Assets & CAPEX'!N37 -> 107940.69 | P17: ='Fixed Assets & CAPEX'!O104 -> 123360.79 | Q17: ='Fixed Assets & CAPEX'!P104 -> 121126.61 | R17: ='Fixed Assets & CAPEX'!Q104 -> 123021.31 | S17: ='Fixed Assets & CAPEX'!R104 -> 131556.8 | T17: ='Fixed Assets & CAPEX'!S104 -> 140020.37 | U17: ='Fixed Assets & CAPEX'!T104 -> 120210.67 | V17: ='Fixed Assets & CAPEX'!U104 -> 123891.03 | W17: ='Fixed Assets & CAPEX'!V104 -> 126169.65 | ... AB17: ='Fixed Assets & CAPEX'!AA104 -> 125658.84 | AO17: Base Case | AP17: Base Case | AQ17: n.a. | AR17: n.a. | AS17: 2.3505268 | AT17: 1.8981458 | AU17: 1.664438 | AV17: 1.3339471 | AW17: 1.0312661 | AX17: 0.73791208 | AY17: 8.3252499 | AZ17: 12.85502 | BA17: 43.347551 | BB17: #DIV/0!
B18: Current Portion of LT Debt | G18: ='Balance Sheet'!H50 -> 75294 | H18: ='Balance Sheet'!I50 -> 49121 | I18: ='Balance Sheet'!J50 -> 44928 | J18: ='Balance Sheet'!K50 -> 84248.825 | K18: ='Balance Sheet'!L50 -> 137426.11 | L18: ='Balance Sheet'!M50 -> 120481.63 | M18: ='Balance Sheet'!N50 -> 124575.83 | N18: ='Balance Sheet'!O50 -> 126614.73 | ... AB18: ='Balance Sheet'!AC50 -> 57171.388 | AD18: Total Debt permitido a 2x | AE18: =AE11 -> 2009 | AF18: =AF11 -> 2010 | AG18: =AG11 -> 2011 | AH18: =AH11 -> 2012 | AI18: =AI11 -> 2013 | AJ18: =AJ11 -> 2014 | AK18: =AK11 -> 2015 | AO18: Client Case | AP18: Covenant Sugerido | AQ18: n.a. | AR18: n.a. | AS18: 3 | AT18: 3 | AU18: 3 | AV18: 3 | AW18: 3 | AX18: 3 | AY18: 8.8590739 | AZ18: 14.847081 | BA18: 89.271082 | BB18: #DIV/0!
B19: Long Term Debt | G19: ='Balance Sheet'!H64 -> 135784 | H19: ='Balance Sheet'!I64 -> 344986 | I19: ='Balance Sheet'!J64 -> 391248 | J19: ='Balance Sheet'!K64 -> 436122.39 | K19: ='Balance Sheet'!L64 -> 327169.06 | L19: ='Balance Sheet'!M64 -> 239227.76 | M19: ='Balance Sheet'!N64 -> 151840.86 | N19: ='Balance Sheet'!O64 -> 67727.774 | ... AB19: ='Balance Sheet'!AC64 -> 41700 | AD19: =B3 -> Base Case | AE19: 164570 | AF19: 183465.55 | AG19: 170148.82 | AH19: 159491.35 | AI19: 162862.31 | AJ19: 186936.78 | AK19: 218723.07 | AO19: Stress Case | AP19: ="Interest Coverage "&AO19 -> Interest Coverage Stress Case | AQ19: n.a. | AR19: n.a. | AS19: 1.3667285 | AT19: 0.91197166 | AU19: 1.0356277 | AV19: 1.3761137 | AW19: 1.7752233 | AX19: 2.1959344 | AY19: 2.5172534 | AZ19: 2.9262704 | BA19: 3.6853073 | BB19: 4.7964766
B20: Revolving Leverage | G20: ='Balance Sheet'!H55 -> 0 | H20: ='Balance Sheet'!I55 -> 0 | I20: ='Balance Sheet'!J55 -> 0 | J20: ='Balance Sheet'!K55 -> 0 | K20: ='Balance Sheet'!L55 -> 0 | L20: ='Balance Sheet'!M55 -> 51880.553 | M20: ='Balance Sheet'!N55 -> 154768.37 | N20: ='Balance Sheet'!O55 -> 262913.99 | ... AB20: ='Balance Sheet'!AC55 -> #VALUE! | AD20: =B4 -> Cliente Case | AE20: 164570 | AF20: 204717.1 | AG20: 239998.33 | AH20: 259196.63 | AI20: 293350.95 | AJ20: 354049.09 | AK20: 428186.86 | AP20: Corte Sugerido | AQ20: =$AX20 -> 0 | AR20: =$AX20 -> 0
B21: Net Debt | G21: =G18+G19+G20-'Balance Sheet'!H13 -> 91120 | H21: =H18+H19+H20-'Balance Sheet'!I13 -> 165621 | I21: =I18+I19+I20-'Balance Sheet'!J13 -> 286732.49 | J21: =J18+J19+J20-'Balance Sheet'!K13 -> 354506.35 | K21: =K18+K19+K20-'Balance Sheet'!L13 -> 344000.8 | L21: =L18+L19+L20-'Balance Sheet'!M13 -> 341589.93 | M21: =M18+M19+M20-'Balance Sheet'!N13 -> 361185.06 | N21: =N18+N19+N20-'Balance Sheet'!O13 -> 387256.5 | ... AB21: =AB18+AB19+AB20-'Balance Sheet'!AC13 -> #VALUE! | AD21: =B5 -> Stress Case | AE21: 164570 | AF21: 167819.94 | AG21: 153977.52 | AH21: 144302.16 | AI21: 173477.33 | AJ21: 207217.01 | AK21: 231712.47
B22: Total Debt | H22: =H18+H19+H20 -> 394107 | I22: =I18+I19+I20 -> 436176 | J22: =J18+J19+J20 -> 520371.21 | K22: =K18+K19+K20 -> 464595.17 | L22: =L18+L19+L20 -> 411589.93 | M22: =M18+M19+M20 -> 431185.06 | N22: =N18+N19+N20 -> 457256.5 | O22: =O18+O19+O20 -> 488659.26 | ... AB22: =AB18+AB19+AB20 -> #VALUE!
B23: Net Debt / EBITDA (com revolving) | G23: =G21/G12 -> 1.1050072 | H23: =H21/H12 -> 1.4339356 | I23: =I21/I12 -> 2.9997818 | J23: =J21/J12 -> 3.0000248 | K23: =K21/K12 -> 2.0764738 | L23: =L21/L12 -> 2.0802647 | M23: =M21/M12 -> 2.7782792 | N23: =N21/N12 -> 2.7958095 | ... AB23: =AB21/AB12 -> #VALUE! | AO23: Base Case | AP23: ="Liquidez Seca "&AO23 -> Liquidez Seca Base Case | AQ23: 1.654467 | AR23: 3.0990813 | AS23: 2.792803 | AT23: 2.4669518 | AU23: 2.1859556 | AV23: 2.0513889 | AW23: 2.0297355 | AX23: 2.5673358 | AY23: 2.9183024 | AZ23: 3.6622641 | BA23: 4.0558025 | BB23: 4.4704877
B24: Total Debt / EBITDA (com revolving) | H24: =H22/H12 -> 3.4121523 | I24: =I22/I12 -> 4.5632527 | J24: =J22/J12 -> 4.4036631 | K24: =K22/K12 -> 2.8044111 | L24: =L22/L12 -> 2.506561 | M24: =M22/M12 -> 3.3167277 | N24: =N22/N12 -> 3.3011765 | O24: =O22/O12 -> 3.2825067 | ... AB24: =AB22/AB12 -> #VALUE!
B25: Variação NCG | G25: n.a. | H25: n.a. | I25: ='Cash Flow'!H19 -> -5892.988 | J25: ='Cash Flow'!I19 -> -7760.3803 | K25: ='Cash Flow'!J19 -> -6911.332 | L25: ='Cash Flow'!K19 -> -7594.6858 | M25: ='Cash Flow'!L19 -> -8438.9109 | N25: ='Cash Flow'!M19 -> -9059.8534 | O25: ='Cash Flow'!N19 -> -9863.94 | P25: ='Cash Flow'!P19 -> -11417.577 | Q25: ='Cash Flow'!Q19 -> -12255.468 | R25: ='Cash Flow'!R19 -> -13268.547 | S25: ='Cash Flow'!S19 -> -15723.948 | T25: ='Cash Flow'!T19 -> -17088 | U25: ='Cash Flow'!U19 -> -18570.384 | V25: ='Cash Flow'!V19 -> -20181.365 | W25: ='Cash Flow'!W19 -> -21932.098 | ... AB25: ='Cash Flow'!AB19 -> 0 | AO25: Client Case | AP25: ="Liquidez Seca "&AO25 -> Liquidez Seca Client Case | AQ25: 1.654467 | AR25: 2.9792809 | AS25: 2.6285731 | AT25: 2.1509618 | AU25: 1.9089283 | AV25: 1.9053959 | AW25: 2.1092385 | AX25: 2.9633391 | AY25: 2.8972543 | AZ25: 3.6083441 | BA25: 4.2549437 | BB25: 4.6023975
B26: Liquidez | G26: =G31/G49 -> 0.92612612 | H26: =H31/H49 -> 1.1874826 | I26: =I31/I49 -> 1.0511633 | J26: =J31/J49 -> 1.0210521 | K26: =K31/K49 -> 0.87970776 | L26: =L31/L49 -> 0.79225626 | M26: =M31/M49 -> 0.71191665 | N26: =N31/N49 -> 0.65308721 | ... AB26: =AB31/AB49 -> #VALUE! | AD26: =AD19 -> Base Case | AE26: 143212.5 | AF26: 164380.75 | AG26: 146656.67 | AH26: 131809.04 | AI26: 130925.44 | AJ26: 150685.12 | AK26: 177508.85 | AP26: Corte Sugerido | AQ26: =$AX26 -> 1.5 | AR26: =$AX26 -> 1.5 | AS26: 2 | AT26: 2 | AU26: 1.8 | AV26: 1.8 | AW26: 1.5 | AX26: 1.5
B27: (EBITDA)/(Juros + Amortização) | G27: =(G12)/(-G88-G120) -> #DIV/0! | H27: =(H12)/(-H88-H120) -> 2.819711 | I27: =(I12)/(-I88-I120) -> 0.90426485 | J27: =(J12)/(-J88-J120) -> 1.2753077 | K27: =(K12)/(-K88-K120) -> 1.2291494 | L27: =(L12)/(-L88-L120) -> 0.88350187 | M27: =(M12)/(-M88-M120) -> 0.59890068 | N27: =(N12)/(-N88-N120) -> 0.42207892 | ... AB27: =(AB12)/(-AB88-AB120) -> #VALUE! | AD27: =AD20 -> Cliente Case | AE27: 143212.5 | AF27: 180104.96 | AG27: 202039.08 | AH27: 211724.11 | AI27: 237908.05 | AJ27: 290148.92 | AK27: 354983.95
AD28: =AD21 -> Stress Case | AE28: 143212.5 | AF28: 147040.51 | AG28: 126752.77 | AH28: 110726.62 | AI28: 132607.99 | AJ28: 157912.76 | AK28: 176284.35 | AO28: Base Case | AP28: ="Net Debt / EBITDA "&AO28 -> Net Debt / EBITDA Base Case | AQ28: -0.92508577 | AR28: -0.31715496 | AS28: 2.3963706 | AT28: 2.3280127 | AU28: 1.87158 | AV28: 1.5310027 | AW28: 1.1431096 | AX28: 0.72027186 | AY28: 0.51839832 | AZ28: 0.086923138 | BA28: -0.34032976 | BB28: -0.75107533
B29: BALANCE SHEET | AO29: Client Case | AP29: ="Net Debt / EBITDA "&AO29 -> Net Debt / EBITDA Client Case | AQ29: -0.92508577 | AR29: -0.31715496 | AS29: 1.9214067 | AT29: 1.8837126 | AU29: 1.5973005 | AV29: 1.2760107 | AW29: 0.87276614 | AX29: 0.42758281 | AY29: 0.46919547 | AZ29: 0.021558984 | BA29: -0.45303542 | BB29: -1.0091994
B30: R$ million - nominal | G30: =+G$9 -> 2010 | H30: =+H$9 -> 2011 | I30: =+I$9 -> 2012 | J30: =+J$9 -> 2013 | K30: =+K$9 -> 2014 | L30: =+L$9 -> 2015 | M30: =+M$9 -> 2016 | N30: =+N$9 -> 2017 | ... AB30: =+AB$9 -> 2031 | AO30: Stress Case | AP30: ="Net Debt / EBITDA "&AO30 -> Net Debt / EBITDA Stress Case | AQ30: -0.92508577 | AR30: -0.31715496 | AS30: 4.9345766 | AT30: 4.7783112 | AU30: 4.4518329 | AV30: 4.0396359 | AW30: 3.5567187 | AX30: 3.0343066 | AY30: 2.6072214 | AZ30: 2.1268193 | BA30: 1.6246444 | BB30: 1.1614132
B31: Current Assets | G31: ='Balance Sheet'!H12 -> 375922 | H31: ='Balance Sheet'!I12 -> 601454 | I31: ='Balance Sheet'!J12 -> 550540.62 | J31: ='Balance Sheet'!K12 -> 604004.73 | K31: ='Balance Sheet'!L12 -> 591724.23 | L31: ='Balance Sheet'!M12 -> 577381.71 | M31: ='Balance Sheet'!N12 -> 617663.32 | N31: ='Balance Sheet'!O12 -> 660908.89 | ... AB31: ='Balance Sheet'!AC12 -> #VALUE! | AD31: =2800*(1-34%) -> 1848 | AP31: Corte Sugerido | AQ31: 0 | AR31: 0 | AS31: 2.6 | AT31: 2.6 | AU31: 2.2 | AV31: 2 | AW31: 1.5 | AX31: 1.5 | AY31: 1 | AZ31: 1 | BA31: 1 | BB31: 1
B32: ='Balance Sheet'!C13 -> Cash & Short Term Inv. | G32: ='Balance Sheet'!H13 -> 119958 | H32: ='Balance Sheet'!I13 -> 228486 | I32: ='Balance Sheet'!J13 -> 149443.51 | J32: ='Balance Sheet'!K13 -> 165864.86 | K32: ='Balance Sheet'!L13 -> 120594.37 | L32: ='Balance Sheet'!M13 -> 70000 | M32: ='Balance Sheet'!N13 -> 70000 | N32: ='Balance Sheet'!O13 -> 70000 | ... AB32: ='Balance Sheet'!AC13 -> #VALUE!
B33: ='Balance Sheet'!C15 -> Reserva Técnica | G33: ='Balance Sheet'!H15 -> 102022 | H33: ='Balance Sheet'!I15 -> 172303 | I33: ='Balance Sheet'!J15 -> 185298.03 | J33: ='Balance Sheet'!K15 -> 202410.97 | K33: ='Balance Sheet'!L15 -> 217651.62 | L33: ='Balance Sheet'!M15 -> 234399.17 | M33: ='Balance Sheet'!N15 -> 253008.39 | N33: ='Balance Sheet'!O15 -> 272986.89 | ... AB33: ='Balance Sheet'!AC15 -> 777626.33 | AO33: Base Case | AP33: ="EBITDA / INTEREST EXPENSE "&AO33 -> EBITDA / INTEREST EXPENSE Base Case | AQ33: n.a. | AR33: 3.9420497
B34: ='Balance Sheet'!C16 -> Créd. operações pl. de assist. à saúde | G34: ='Balance Sheet'!H16 -> 86898 | H34: ='Balance Sheet'!I16 -> 106236 | I34: ='Balance Sheet'!J16 -> 114248.28 | J34: ='Balance Sheet'!K16 -> 124799.52 | K34: ='Balance Sheet'!L16 -> 134196.37 | L34: ='Balance Sheet'!M16 -> 144522.33 | M34: ='Balance Sheet'!N16 -> 155996.12 | N34: ='Balance Sheet'!O16 -> 168314.16 | O34: ='Balance Sheet'!P16 -> 181725.46 | P34: ='Balance Sheet'!Q15 -> 318237.24 | Q34: ='Balance Sheet'!R15 -> 343414.91 | R34: ='Balance Sheet'!S15 -> 370440.27 | S34: ='Balance Sheet'!T15 -> 399699.65 | T34: ='Balance Sheet'!U15 -> 434373.59 | U34: ='Balance Sheet'!V15 -> 472055.5 | V34: ='Balance Sheet'!W15 -> 513006.32 | W34: ='Balance Sheet'!X15 -> 557509.62 | ... AB34: ='Balance Sheet'!AC15 -> 777626.33 | AO34: Client Case | AP34: ="EBITDA / INTEREST EXPENSE "&AO34 -> EBITDA / INTEREST EXPENSE Client Case | AQ34: n.a. | AR34: 5.0837439
B35: ='Balance Sheet'!C17 -> Despesas de comercialização diferidas | G35: ='Balance Sheet'!H17 -> 9839 | H35: ='Balance Sheet'!I17 -> 9480 | I35: ='Balance Sheet'!J17 -> 10194.978 | J35: ='Balance Sheet'!K17 -> 11136.521 | K35: ='Balance Sheet'!L17 -> 11975.052 | L35: ='Balance Sheet'!M17 -> 12896.492 | M35: ='Balance Sheet'!N17 -> 13920.359 | N35: ='Balance Sheet'!O17 -> 15019.563 | O35: ='Balance Sheet'!P17 -> 16216.324 | P35: ='Balance Sheet'!Q16 -> 196213.94 | Q35: ='Balance Sheet'!R16 -> 211737.62 | R35: ='Balance Sheet'!S16 -> 228400.51 | S35: ='Balance Sheet'!T16 -> 246440.82 | T35: ='Balance Sheet'!U16 -> 267819.56 | U35: ='Balance Sheet'!V16 -> 291052.9 | V35: ='Balance Sheet'!W16 -> 316301.74 | W35: ='Balance Sheet'!X16 -> 343740.92 | ... AB35: ='Balance Sheet'!AC16 -> 479457.18 | AO35: Stress Case | AP35: ="EBITDA / INTEREST EXPENSE "&AO35 -> EBITDA / INTEREST EXPENSE Stress Case | AQ35: n.a. | AR35: 4.2920817
B36: ='Balance Sheet'!C18 -> Títulos e créditos a receber | G36: ='Balance Sheet'!H18 -> 45149 | H36: ='Balance Sheet'!I18 -> 52275 | I36: ='Balance Sheet'!J18 -> 56217.561 | J36: ='Balance Sheet'!K18 -> 61409.456 | K36: ='Balance Sheet'!L18 -> 66033.315 | L36: ='Balance Sheet'!M18 -> 71114.356 | M36: ='Balance Sheet'!N18 -> 76760.205 | N36: ='Balance Sheet'!O18 -> 82821.481 | O36: ='Balance Sheet'!P18 -> 89420.711 | P36: ='Balance Sheet'!Q20 -> 0 | Q36: ='Balance Sheet'!R20 -> 0 | R36: ='Balance Sheet'!S20 -> 0 | S36: ='Balance Sheet'!T20 -> 0 | T36: ='Balance Sheet'!U20 -> 0 | U36: ='Balance Sheet'!V20 -> 0 | V36: ='Balance Sheet'!W20 -> 0 | W36: ='Balance Sheet'!X20 -> 0 | ... AB36: ='Balance Sheet'!AC20 -> 0 | AP36: Corte Sugerido | AQ36: =$AX36 -> 0 | AR36: =$AX36 -> 0 | AS36: =$AX36 -> 0 | AT36: =$AX36 -> 0 | AU36: =$AX36 -> 0 | AV36: =$AX36 -> 0 | AW36: =$AX36 -> 0
B37: ='Balance Sheet'!C19 -> Outros valores e bens | G37: ='Balance Sheet'!H19 -> 12056 | H37: ='Balance Sheet'!I19 -> 32674 | I37: ='Balance Sheet'!J19 -> 35138.261 | J37: ='Balance Sheet'!K19 -> 38383.406 | K37: ='Balance Sheet'!L19 -> 41273.506 | L37: ='Balance Sheet'!M19 -> 44449.363 | M37: ='Balance Sheet'!N19 -> 47978.248 | N37: ='Balance Sheet'!O19 -> 51766.792 | O37: ='Balance Sheet'!P19 -> 55891.579
B38: Long-Term Assets | G38: ='Balance Sheet'!H27 -> 741463 | H38: ='Balance Sheet'!I27 -> 708901 | I38: ='Balance Sheet'!J27 -> 708901 | J38: ='Balance Sheet'!K27 -> 708901 | K38: ='Balance Sheet'!L27 -> 708901 | L38: ='Balance Sheet'!M27 -> 708901 | M38: ='Balance Sheet'!N27 -> 708901 | N38: ='Balance Sheet'!O27 -> 708901 | ... AB38: ='Balance Sheet'!AC27 -> 708901
B39: ='Balance Sheet'!C28 -> Ativo Fiscal Diferido | G39: ='Balance Sheet'!H28 -> 6460 | H39: ='Balance Sheet'!I28 -> 8368 | I39: ='Balance Sheet'!J28 -> 8368 | J39: ='Balance Sheet'!K28 -> 8368 | K39: ='Balance Sheet'!L28 -> 8368 | L39: ='Balance Sheet'!M28 -> 8368 | M39: ='Balance Sheet'!N28 -> 8368 | N39: ='Balance Sheet'!O28 -> 8368 | ... AB39: ='Balance Sheet'!AC28 -> 8368 | AO39: Base Case | AP39: ="Total Debt / (EBITDA+WCC) "&AO39 -> Total Debt / (EBITDA+WCC) Base Case | AQ39: n.a. | AR39: 0.17376374 | AS39: 3.4901979 | AT39: 2.6701663 | AU39: 2.011435 | AV39: 1.592421 | AW39: 1.1369846 | AX39: 0.44815481 | AY39: 0.56705325 | AZ39: 0.19455969 | BA39: 0.028855506 | BB39: 0.025983266
B40: ='Balance Sheet'!C29 -> Valores e bens | G40: ='Balance Sheet'!H29 -> 45783 | H40: ='Balance Sheet'!I29 -> 65262 | I40: ='Balance Sheet'!J29 -> 65262 | J40: ='Balance Sheet'!K29 -> 65262 | K40: ='Balance Sheet'!L29 -> 65262 | L40: ='Balance Sheet'!M29 -> 65262 | M40: ='Balance Sheet'!N29 -> 65262 | N40: ='Balance Sheet'!O29 -> 65262 | O40: ='Balance Sheet'!P29 -> 65262
B41: ='Balance Sheet'!C30 -> Conta-corrente com cooperados | G41: ='Balance Sheet'!H30 -> 689220 | H41: ='Balance Sheet'!I30 -> 635271 | I41: ='Balance Sheet'!J30 -> 635271 | J41: ='Balance Sheet'!K30 -> 635271 | K41: ='Balance Sheet'!L30 -> 635271 | L41: ='Balance Sheet'!M30 -> 635271 | M41: ='Balance Sheet'!N30 -> 635271 | N41: ='Balance Sheet'!O30 -> 635271 | O41: ='Balance Sheet'!P30 -> 635271
B42: ='Balance Sheet'!C31 -> Bens destinados a venda | G42: ='Balance Sheet'!H31 -> 0 | H42: ='Balance Sheet'!I31 -> 0 | I42: ='Balance Sheet'!J31 -> 0 | J42: ='Balance Sheet'!K31 -> 0 | K42: ='Balance Sheet'!L31 -> 0 | L42: ='Balance Sheet'!M31 -> 0 | M42: ='Balance Sheet'!N31 -> 0 | N42: ='Balance Sheet'!O31 -> 0 | O42: ='Balance Sheet'!P31 -> 0 | P42: ='Balance Sheet'!Q29 -> 65262 | Q42: ='Balance Sheet'!R29 -> 65262 | R42: ='Balance Sheet'!S29 -> 65262 | S42: ='Balance Sheet'!T29 -> 65262 | T42: ='Balance Sheet'!U29 -> 65262 | U42: ='Balance Sheet'!V29 -> 65262 | V42: ='Balance Sheet'!W29 -> 65262 | W42: ='Balance Sheet'!X29 -> 65262 | ... AB42: ='Balance Sheet'!AC29 -> 65262 | AO42: Client Case | AP42: ="Total Debt / (EBITDA+WCC) "&AO42 -> Total Debt / (EBITDA+WCC) Client Case | AQ42: n.a. | AR42: 0.26220802 | AS42: 3.7083104 | AT42: 3.3811167 | AU42: 3.2020542 | AV42: 2.2690903 | AW42: 1.4673449 | AX42: 0.57972032 | AY42: 0.48128469 | AZ42: 0.099238699 | BA42: 0.021320086 | BB42: 0.017762639
B43: Permanent | G43: ='Balance Sheet'!H34 -> 297589 | H43: ='Balance Sheet'!I34 -> 407811 | I43: ='Balance Sheet'!J34 -> 518804.4 | J43: ='Balance Sheet'!K34 -> 578804.4 | K43: ='Balance Sheet'!L34 -> 578804.4 | L43: ='Balance Sheet'!M34 -> 578804.4 | M43: ='Balance Sheet'!N34 -> 578804.4 | N43: ='Balance Sheet'!O34 -> 578804.4 | ... AB43: ='Balance Sheet'!AC34 -> 578804.4 | AO43: Stress Case | AP43: ="Total Debt / (EBITDA+WCC) "&AO43 -> Total Debt / (EBITDA+WCC) Stress Case | AQ43: n.a. | AR43: 0.18284319 | AS43: 7.5960487 | AT43: 6.5554055 | AU43: 6.1424919 | AV43: 5.4313143 | AW43: 4.7642196 | AX43: 2.1867103 | AY43: 2.2437947 | AZ43: 1.8542284 | BA43: 1.4466947 | BB43: 1.0648172
B44: ='Balance Sheet'!C37 -> PP&E | G44: ='Balance Sheet'!H37 -> 197195 | H44: ='Balance Sheet'!I37 -> 280066 | I44: ='Balance Sheet'!J37 -> 419066 | J44: ='Balance Sheet'!K37 -> 526929.74 | K44: ='Balance Sheet'!L37 -> 590202.59 | L44: ='Balance Sheet'!M37 -> 662514.42 | M44: ='Balance Sheet'!N37 -> 745156.51 | N44: ='Balance Sheet'!O37 -> 839604.61 | O44: ='Balance Sheet'!P37 -> 947545.3 | P44: ='Balance Sheet'!Q35+'Balance Sheet'!Q17 -> 17509.208 | Q44: ='Balance Sheet'!R35+'Balance Sheet'!R17 -> 18894.467 | R44: ='Balance Sheet'!S35+'Balance Sheet'!S17 -> 20381.385 | S44: ='Balance Sheet'!T35+'Balance Sheet'!T17 -> 21991.217 | T44: ='Balance Sheet'!U35+'Balance Sheet'!U17 -> 23898.955 | U44: ='Balance Sheet'!V35+'Balance Sheet'!V17 -> 25972.19 | V44: ='Balance Sheet'!W35+'Balance Sheet'!W17 -> 28225.277 | W44: ='Balance Sheet'!X35+'Balance Sheet'!X17 -> 30673.82 | ... AB44: ='Balance Sheet'!AC35+'Balance Sheet'!AC17 -> 42784.5 | AP44: Corte Sugerido | AQ44: =$AX44 -> 0 | AR44: =$AX44 -> 0
B45: ='Balance Sheet'!C39 -> Amortizacao | G45: ='Balance Sheet'!H39 -> 0 | H45: ='Balance Sheet'!I39 -> 0 | I45: ='Balance Sheet'!J39 -> -28006.6 | J45: ='Balance Sheet'!K39 -> -75870.343 | K45: ='Balance Sheet'!L39 -> -139143.19 | L45: ='Balance Sheet'!M39 -> -211455.02 | M45: ='Balance Sheet'!N39 -> -294097.11 | N45: ='Balance Sheet'!O39 -> -388545.21 | O45: ='Balance Sheet'!P39 -> -496485.9 | P45: ='Balance Sheet'!Q38+'Balance Sheet'!Q40 -> 31238 | Q45: ='Balance Sheet'!R38+'Balance Sheet'!R40 -> 31238 | R45: ='Balance Sheet'!S38+'Balance Sheet'!S40 -> 31238 | S45: ='Balance Sheet'!T38+'Balance Sheet'!T40 -> 31238 | T45: ='Balance Sheet'!U38+'Balance Sheet'!U40 -> 31238 | U45: ='Balance Sheet'!V38+'Balance Sheet'!V40 -> 31238 | V45: ='Balance Sheet'!W38+'Balance Sheet'!W40 -> 31238 | W45: ='Balance Sheet'!X38+'Balance Sheet'!X40 -> 31238 | ... AB45: ='Balance Sheet'!AC38+'Balance Sheet'!AC40 -> 31238
B46: ='Balance Sheet'!C40 -> Intangible Amortization | G46: ='Balance Sheet'!H40 -> 12791 | H46: ='Balance Sheet'!I40 -> 31238 | I46: ='Balance Sheet'!J40 -> 31238 | J46: ='Balance Sheet'!K40 -> 31238 | K46: ='Balance Sheet'!L40 -> 31238 | L46: ='Balance Sheet'!M40 -> 31238 | M46: ='Balance Sheet'!N40 -> 31238 | N46: ='Balance Sheet'!O40 -> 31238 | O46: ='Balance Sheet'!P40 -> 31238 | P46: ='Balance Sheet'!Q37+'Balance Sheet'!Q39 -> 451059.4 | Q46: ='Balance Sheet'!R37+'Balance Sheet'!R39 -> 451059.4 | R46: ='Balance Sheet'!S37+'Balance Sheet'!S39 -> 451059.4 | S46: ='Balance Sheet'!T37+'Balance Sheet'!T39 -> 451059.4 | T46: ='Balance Sheet'!U37+'Balance Sheet'!U39 -> 451059.4 | U46: ='Balance Sheet'!V37+'Balance Sheet'!V39 -> 451059.4 | V46: ='Balance Sheet'!W37+'Balance Sheet'!W39 -> 451059.4 | W46: ='Balance Sheet'!X37+'Balance Sheet'!X39 -> 451059.4 | ... AB46: ='Balance Sheet'!AC37+'Balance Sheet'!AC39 -> 451059.4
B47: Investimentos | G47: ='Balance Sheet'!H41 -> 87603 | H47: ='Balance Sheet'!I41 -> 96507 | I47: ='Balance Sheet'!J41 -> 96507 | J47: ='Balance Sheet'!K41 -> 96507 | K47: ='Balance Sheet'!L41 -> 96507 | L47: ='Balance Sheet'!M41 -> 96507 | M47: ='Balance Sheet'!N41 -> 96507 | N47: ='Balance Sheet'!O41 -> 96507 | ... AB47: ='Balance Sheet'!AC41 -> 96507
B48: ASSETS | G48: ='Balance Sheet'!H10 -> 1414974 | H48: ='Balance Sheet'!I10 -> 1718166 | I48: ='Balance Sheet'!J10 -> 1778246 | J48: ='Balance Sheet'!K10 -> 1891710.1 | K48: ='Balance Sheet'!L10 -> 1879429.6 | L48: ='Balance Sheet'!M10 -> 1865087.1 | M48: ='Balance Sheet'!N10 -> 1905368.7 | N48: ='Balance Sheet'!O10 -> 1948614.3 | ... AB48: ='Balance Sheet'!AC10 -> #VALUE!
B49: Current Liabilities | G49: ='Balance Sheet'!H46 -> 405908 | H49: ='Balance Sheet'!I46 -> 506495 | I49: ='Balance Sheet'!J46 -> 523744.12 | J49: ='Balance Sheet'!K46 -> 591551.33 | K49: ='Balance Sheet'!L46 -> 672637.27 | L49: ='Balance Sheet'!M46 -> 728781.51 | M49: ='Balance Sheet'!N46 -> 867606.23 | N49: ='Balance Sheet'!O46 -> 1011976.5 | ... AB49: ='Balance Sheet'!AC46 -> #VALUE!
B50: ='Balance Sheet'!C47 -> Débitos de operações de assit. à saúde | G50: ='Balance Sheet'!H47 -> 4653 | H50: ='Balance Sheet'!I47 -> 4911 | I50: ='Balance Sheet'!J47 -> 5281.3858 | J50: ='Balance Sheet'!K47 -> 5769.1408 | K50: ='Balance Sheet'!L47 -> 6203.5315 | L50: ='Balance Sheet'!M47 -> 6680.8723 | M50: ='Balance Sheet'!N47 -> 7211.2743 | N50: ='Balance Sheet'!O47 -> 7780.7038 | ... AB50: ='Balance Sheet'!AC47 -> 22163.996
B51: ='Balance Sheet'!C48 -> Débitos de oper. assist. à saúde não rel. c/plano de saúde da op. | G51: ='Balance Sheet'!H48 -> 29653 | H51: ='Balance Sheet'!I48 -> 39339 | I51: ='Balance Sheet'!J48 -> 42305.933 | J51: ='Balance Sheet'!K48 -> 46213.038 | K51: ='Balance Sheet'!L48 -> 49692.675 | L51: ='Balance Sheet'!M48 -> 53516.359 | M51: ='Balance Sheet'!N48 -> 57765.083 | N51: ='Balance Sheet'!O48 -> 62326.432 | ... AB51: ='Balance Sheet'!AC48 -> 177542.13
B52: ='Balance Sheet'!C49 -> Taxes | G52: ='Balance Sheet'!H49 -> 25896 | H52: ='Balance Sheet'!I49 -> 32706 | I52: ='Balance Sheet'!J49 -> 35172.674 | J52: ='Balance Sheet'!K49 -> 38420.998 | K52: ='Balance Sheet'!L49 -> 41313.928 | L52: ='Balance Sheet'!M49 -> 44492.896 | M52: ='Balance Sheet'!N49 -> 48025.237 | N52: ='Balance Sheet'!O49 -> 51817.491 | ... AB52: ='Balance Sheet'!AC49 -> 89604.054
B53: ='Balance Sheet'!C50 -> Bank Short Term | G53: ='Balance Sheet'!H50 -> 75294 | H53: ='Balance Sheet'!I50 -> 49121 | I53: ='Balance Sheet'!J50 -> 44928 | J53: ='Balance Sheet'!K50 -> 84248.825 | K53: ='Balance Sheet'!L50 -> 137426.11 | L53: ='Balance Sheet'!M50 -> 120481.63 | M53: ='Balance Sheet'!N50 -> 124575.83 | N53: ='Balance Sheet'!O50 -> 126614.73 | ... AB53: ='Balance Sheet'!AC50 -> 57171.388
B54: ='Balance Sheet'!C51 -> Tributos e contribuições a recolher - parcelamento | G54: ='Balance Sheet'!H51 -> 6767 | H54: ='Balance Sheet'!I51 -> 24196 | I54: ='Balance Sheet'!J51 -> 23402 | J54: ='Balance Sheet'!K51 -> 22606 | K54: ='Balance Sheet'!L51 -> 24436 | L54: ='Balance Sheet'!M51 -> 16987 | M54: ='Balance Sheet'!N51 -> 16987 | N54: ='Balance Sheet'!O51 -> 16987 | ... AB54: ='Balance Sheet'!AC51 -> 0
B55: ='Balance Sheet'!C52 -> Provisões técnicas de operações de assist. à saúde | G55: ='Balance Sheet'!H52 -> 171826 | H55: ='Balance Sheet'!I52 -> 217876 | I55: ='Balance Sheet'!J52 -> 234308.13 | J55: ='Balance Sheet'!K52 -> 255947.33 | K55: ='Balance Sheet'!L52 -> 275219.03 | L55: ='Balance Sheet'!M52 -> 296396.2 | M55: ='Balance Sheet'!N52 -> 319927.43 | N55: ='Balance Sheet'!O52 -> 345190.11 | ... AB55: ='Balance Sheet'!AC52 -> 983303.34
B56: ='Balance Sheet'!C55 -> Revolving Leverage | G56: ='Balance Sheet'!H55 -> 0 | H56: ='Balance Sheet'!I55 -> 0 | I56: ='Balance Sheet'!J55 -> 0 | J56: ='Balance Sheet'!K55 -> 0 | K56: ='Balance Sheet'!L55 -> 0 | L56: ='Balance Sheet'!M55 -> 51880.553 | M56: ='Balance Sheet'!N55 -> 154768.37 | N56: ='Balance Sheet'!O55 -> 262913.99 | O56: ='Balance Sheet'!P55 -> 372358.18 | P56: =P49-SUM(P50:P55) -> 464327.38 | Q56: =Q49-SUM(Q50:Q55) -> 448032.22 | R56: =R49-SUM(R50:R55) -> 410904.32 | S56: =S49-SUM(S50:S55) -> 356810.44 | T56: =T49-SUM(T50:T55) -> #VALUE! | U56: =U49-SUM(U50:U55) -> #VALUE! | V56: =V49-SUM(V50:V55) -> #VALUE! | W56: =W49-SUM(W50:W55) -> #VALUE! | ... AB56: =AB49-SUM(AB50:AB55) -> #VALUE!
B57: ='Balance Sheet'!C56 -> Other Non-Op. Cur. Liabilities | G57: ='Balance Sheet'!H56 -> 91819 | H57: ='Balance Sheet'!I56 -> 138346 | I57: ='Balance Sheet'!J56 -> 138346 | J57: ='Balance Sheet'!K56 -> 138346 | K57: ='Balance Sheet'!L56 -> 138346 | L57: ='Balance Sheet'!M56 -> 138346 | M57: ='Balance Sheet'!N56 -> 138346 | N57: ='Balance Sheet'!O56 -> 138346 | O57: ='Balance Sheet'!P56 -> 138346
B58: Long-Term Liabilities | G58: ='Balance Sheet'!H63 -> 845134 | H58: ='Balance Sheet'!I63 -> 1004560 | I58: ='Balance Sheet'!J63 -> 1027420 | J58: ='Balance Sheet'!K63 -> 1049688.4 | K58: ='Balance Sheet'!L63 -> 916299.06 | L58: ='Balance Sheet'!M63 -> 811370.76 | M58: ='Balance Sheet'!N63 -> 706996.86 | N58: ='Balance Sheet'!O63 -> 605896.77 | ... AB58: ='Balance Sheet'!AC63 -> 494934
B59: ='Balance Sheet'!C64 -> LT Bank Debt | G59: ='Balance Sheet'!H64 -> 135784 | H59: ='Balance Sheet'!I64 -> 344986 | I59: ='Balance Sheet'!J64 -> 391248 | J59: ='Balance Sheet'!K64 -> 436122.39 | K59: ='Balance Sheet'!L64 -> 327169.06 | L59: ='Balance Sheet'!M64 -> 239227.76 | M59: ='Balance Sheet'!N64 -> 151840.86 | N59: ='Balance Sheet'!O64 -> 67727.774 | ... AB59: ='Balance Sheet'!AC64 -> 41700
B60: ='Balance Sheet'!C66 -> Other Long-Term Liabilities | G60: ='Balance Sheet'!H66 -> 709350 | H60: ='Balance Sheet'!I66 -> 659574 | I60: ='Balance Sheet'!J66 -> 636172 | J60: ='Balance Sheet'!K66 -> 613566 | K60: ='Balance Sheet'!L66 -> 589130 | L60: ='Balance Sheet'!M66 -> 572143 | M60: ='Balance Sheet'!N66 -> 555156 | N60: ='Balance Sheet'!O66 -> 538169 | ... AB60: ='Balance Sheet'!AC66 -> 453234
P61: ='Balance Sheet'!Q73 -> 0 | Q61: ='Balance Sheet'!R73 -> 0 | R61: ='Balance Sheet'!S73 -> 0 | S61: ='Balance Sheet'!T73 -> 0 | T61: ='Balance Sheet'!U73 -> 0 | U61: ='Balance Sheet'!V73 -> 0 | V61: ='Balance Sheet'!W73 -> 0 | W61: ='Balance Sheet'!X73 -> 0 | ... AB61: ='Balance Sheet'!AC73 -> 0
B62: Shareholder's Equity | G62: ='Balance Sheet'!H77 -> 163932 | H62: ='Balance Sheet'!I77 -> 207111 | I62: ='Balance Sheet'!J77 -> 227081.9 | J62: ='Balance Sheet'!K77 -> 250470.42 | K62: ='Balance Sheet'!L77 -> 290493.3 | L62: ='Balance Sheet'!M77 -> 324934.85 | M62: ='Balance Sheet'!N77 -> 330765.64 | N62: ='Balance Sheet'!O77 -> 330741.05 | O62: ='Balance Sheet'!P77 -> 326189.23 | P62: ='Balance Sheet'!Q77+P61 -> 383594.79 | Q62: ='Balance Sheet'!R77+Q61 -> 418242.3 | R62: ='Balance Sheet'!S77+R61 -> 478072.8 | S62: ='Balance Sheet'!T77+S61 -> 538502.02 | T62: ='Balance Sheet'!U77+T61 -> #VALUE! | U62: ='Balance Sheet'!V77+U61 -> #VALUE! | V62: ='Balance Sheet'!W77+V61 -> #VALUE! | W62: ='Balance Sheet'!X77+W61 -> #VALUE! | ... AB62: ='Balance Sheet'!AC77+AB61 -> #VALUE!
B63: ='Balance Sheet'!C78 -> Capital | G63: ='Balance Sheet'!H78 -> 100818 | H63: ='Balance Sheet'!I78 -> 108963 | I63: ='Balance Sheet'!J78 -> 108963 | J63: ='Balance Sheet'!K78 -> 108963 | K63: ='Balance Sheet'!L78 -> 108963 | L63: ='Balance Sheet'!M78 -> 108963 | M63: ='Balance Sheet'!N78 -> 108963 | N63: ='Balance Sheet'!O78 -> 108963 | ... AB63: ='Balance Sheet'!AC78 -> 108963
B64: ='Balance Sheet'!C79 -> Reserves | G64: ='Balance Sheet'!H79 -> 37118 | H64: ='Balance Sheet'!I79 -> 61606 | I64: ='Balance Sheet'!J79 -> 61606 | J64: ='Balance Sheet'!K79 -> 61606 | K64: ='Balance Sheet'!L79 -> 61606 | L64: ='Balance Sheet'!M79 -> 61606 | M64: ='Balance Sheet'!N79 -> 61606 | N64: ='Balance Sheet'!O79 -> 61606 | O64: ='Balance Sheet'!P79 -> 61606
B65: ='Balance Sheet'!C80 -> Retained earnings | G65: ='Balance Sheet'!H80 -> 25996 | H65: ='Balance Sheet'!I80 -> 36542 | I65: ='Balance Sheet'!J80 -> 56512.898 | J65: ='Balance Sheet'!K80 -> 79901.416 | K65: ='Balance Sheet'!L80 -> 119924.3 | L65: ='Balance Sheet'!M80 -> 154365.85 | M65: ='Balance Sheet'!N80 -> 160196.64 | N65: ='Balance Sheet'!O80 -> 160172.05 | O65: ='Balance Sheet'!P80 -> 155620.23
B66: LIABILITIES & EQUITY | G66: =G62+G58+G49 -> 1414974 | H66: =H62+H58+H49 -> 1718166 | I66: =I62+I58+I49 -> 1778246 | J66: =J62+J58+J49 -> 1891710.1 | K66: =K62+K58+K49 -> 1879429.6 | L66: =L62+L58+L49 -> 1865087.1 | M66: =M62+M58+M49 -> 1905368.7 | N66: =N62+N58+N49 -> 1948614.3 | ... AB66: =AB62+AB58+AB49 -> #VALUE!
G67: =G48-G66 -> 0 | H67: =H48-H66 -> 0 | I67: =I48-I66 -> 0 | J67: =J48-J66 -> 0 | K67: =K48-K66 -> 0 | L67: =L48-L66 -> 0 | M67: =M48-M66 -> 0 | N67: =N48-N66 -> 0 | ... AB67: =AB48-AB66 -> #VALUE!
B69: INCOME STATEMENT
B70: R$ million - nominal | G70: =G30 -> 2010 | H70: =H30 -> 2011 | I70: =I30 -> 2012 | J70: =J30 -> 2013 | K70: =K30 -> 2014 | L70: =L30 -> 2015 | M70: =M30 -> 2016 | N70: =N30 -> 2017 | ... AB70: =AB30 -> 2031
B71: Gross Revenues | G71: ='Income Statement'!H10 -> 2434971 | H71: ='Income Statement'!I10 -> 2853511 | I71: ='Income Statement'!J10 -> 3068721.7 | J71: ='Income Statement'!K10 -> 3352129.3 | K71: ='Income Statement'!L10 -> 3604529.7 | L71: ='Income Statement'!M10 -> 3881886.1 | M71: ='Income Statement'!N10 -> 4190073.4 | N71: ='Income Statement'!O10 -> 4520937.5 | ... AB71: ='Income Statement'!AC10 -> 12878274
B72: Deductions | G72: ='Income Statement'!H17 -> 0 | H72: ='Income Statement'!I17 -> 0 | I72: ='Income Statement'!J17 -> 0 | J72: ='Income Statement'!K17 -> 0 | K72: ='Income Statement'!L17 -> 0 | L72: ='Income Statement'!M17 -> 0 | M72: ='Income Statement'!N17 -> 0 | N72: ='Income Statement'!O17 -> 0 | ... AB72: ='Income Statement'!AC17 -> 0
B73: Net Revenues | G73: ='Income Statement'!H24 -> 2434971 | H73: ='Income Statement'!I24 -> 2853511 | I73: ='Income Statement'!J24 -> 3068721.7 | J73: ='Income Statement'!K24 -> 3352129.3 | K73: ='Income Statement'!L24 -> 3604529.7 | L73: ='Income Statement'!M24 -> 3881886.1 | M73: ='Income Statement'!N24 -> 4190073.4 | N73: ='Income Statement'!O24 -> 4520937.5 | ... AB73: ='Income Statement'!AC24 -> 12878274
B74: COGS | G74: ='Income Statement'!H26 -> 1897818 | H74: ='Income Statement'!I26 -> 2250776 | I74: ='Income Statement'!J26 -> 2425322.3 | J74: ='Income Statement'!K26 -> 2652824.4 | K74: ='Income Statement'!L26 -> 2825774.9 | L74: ='Income Statement'!M26 -> 3061587.4 | M74: ='Income Statement'!N26 -> 3356477.9 | N74: ='Income Statement'!O26 -> 3628553.9 | ... AB74: ='Income Statement'!AC26 -> 10196556
B75: % Custos | G75: =G74/G73 -> 0.77940066 | H75: =H74/H73 -> 0.78877425 | I75: =I74/I73 -> 0.79033633 | J75: =J74/J73 -> 0.79138487 | K75: =K74/K73 -> 0.78395107 | L75: =L74/L73 -> 0.78868552 | M75: =M74/M73 -> 0.80105467 | N75: =N74/N73 -> 0.80261094 | ... AB75: =AB74/AB73 -> 0.79176418
B76: Gross Profit | G76: ='Income Statement'!H33 -> 537153 | H76: ='Income Statement'!I33 -> 602735 | I76: ='Income Statement'!J33 -> 643399.46 | J76: ='Income Statement'!K33 -> 699304.88 | K76: ='Income Statement'!L33 -> 778754.79 | L76: ='Income Statement'!M33 -> 820298.75 | M76: ='Income Statement'!N33 -> 833595.54 | N76: ='Income Statement'!O33 -> 892383.62 | ... AB76: ='Income Statement'!AC33 -> 2681718.1
B77: Gross Profit Margin (%) | G77: =G76/G73 -> 0.22059934 | H77: =H76/H73 -> 0.21122575 | I77: =I76/I73 -> 0.20966367 | J77: =J76/J73 -> 0.20861513 | K77: =K76/K73 -> 0.21604893 | L77: =L76/L73 -> 0.21131448 | M77: =M76/M73 -> 0.19894533 | N77: =N76/N73 -> 0.19738906 | ... AB77: =AB76/AB73 -> 0.20823582
B78: SG&A | G78: ='Income Statement'!H35 -> 492128 | H78: ='Income Statement'!I35 -> 535439 | I78: ='Income Statement'!J35 -> 575821.61 | J78: ='Income Statement'!K35 -> 629000.81 | K78: ='Income Statement'!L35 -> 676361.78 | L78: ='Income Statement'!M35 -> 728405.54 | M78: ='Income Statement'!N35 -> 786234.48 | N78: ='Income Statement'!O35 -> 848318.52 | ... AB78: ='Income Statement'!AC35 -> 2290848.5
B79: % SG&A | G79: =G78/G73 -> 0.20210836 | H79: =H78/H73 -> 0.18764217 | I79: =I78/I73 -> 0.18764217 | J79: =J78/J73 -> 0.18764217 | K79: =K78/K73 -> 0.18764217 | L79: =L78/L73 -> 0.18764217 | M79: =M78/M73 -> 0.18764217 | N79: =N78/N73 -> 0.18764217 | ... AB79: =AB78/AB73 -> 0.17788474
B80: EBITDA | G80: ='Income Statement'!H42 -> 82461 | H80: ='Income Statement'!I42 -> 115501 | I80: ='Income Statement'!J42 -> 95584.45 | J80: ='Income Statement'!K42 -> 118167.81 | K80: ='Income Statement'!L42 -> 165665.86 | L80: ='Income Statement'!M42 -> 164205.03 | M80: ='Income Statement'!N42 -> 130003.15 | N80: ='Income Statement'!O42 -> 138513.19 | ... AB80: ='Income Statement'!AC42 -> 516528.38
B81: EBITDA Margin (%) | G81: =G80/G73 -> 0.03386529 | H81: =H80/H73 -> 0.040476802 | I81: =I80/I73 -> 0.031147969 | J81: =J80/J73 -> 0.035251566 | K81: =K80/K73 -> 0.045960463 | L81: =L80/L73 -> 0.042300322 | M81: =M80/M73 -> 0.031026462 | N81: =N80/N73 -> 0.030638158 | ... AB81: =AB80/AB73 -> 0.040108509
B82: Depreciation and Amortization | G82: ='Income Statement'!H44 -> 37436 | H82: ='Income Statement'!I44 -> 48205 | I82: ='Income Statement'!J44 -> 28006.6 | J82: ='Income Statement'!K44 -> 47863.743 | K82: ='Income Statement'!L44 -> 63272.849 | L82: ='Income Statement'!M44 -> 72311.827 | M82: ='Income Statement'!N44 -> 82642.088 | N82: ='Income Statement'!O44 -> 94448.101 | ... AB82: ='Income Statement'!AC44 -> 125658.84
B83: Goodwill Amortization | G83: ='Income Statement'!I46 -> 0 | H83: ='Income Statement'!J46 -> 0 | I83: ='Income Statement'!K46 -> 0 | J83: ='Income Statement'!L46 -> 0 | K83: ='Income Statement'!M46 -> 0 | L83: ='Income Statement'!N46 -> 0 | M83: ='Income Statement'!O46 -> 0 | N83: ='Income Statement'!P46 -> 0 | ... AB83: ='Income Statement'!AD46 -> 0
B84: Other Expenses | G84: ='Income Statement'!I48+'Income Statement'!I53 -> 0 | H84: ='Income Statement'!J48+'Income Statement'!J53 -> 0 | I84: ='Income Statement'!K48+'Income Statement'!K53 -> 0 | J84: ='Income Statement'!L48+'Income Statement'!L53 -> 0 | K84: ='Income Statement'!M48+'Income Statement'!M53 -> 0 | L84: ='Income Statement'!N48+'Income Statement'!N53 -> 0 | M84: ='Income Statement'!O48+'Income Statement'!O53 -> 0 | N84: ='Income Statement'!P48+'Income Statement'!P53 -> 0 | ... AB84: ='Income Statement'!AD48+'Income Statement'!AD53 -> 0
B85: Resultado não operacional | G85: ='Income Statement'!H55+'Income Statement'!H58 -> 0 | H85: ='Income Statement'!I55+'Income Statement'!I58 -> 0 | I85: ='Income Statement'!J55+'Income Statement'!J58 -> 0 | J85: ='Income Statement'!K55+'Income Statement'!K58 -> 0 | K85: ='Income Statement'!L55+'Income Statement'!L58 -> 0 | L85: ='Income Statement'!M55+'Income Statement'!M58 -> 0 | M85: ='Income Statement'!N55+'Income Statement'!N58 -> 0 | N85: ='Income Statement'!O55+'Income Statement'!O58 -> 0 | ... AB85: ='Income Statement'!AC55+'Income Statement'!AC58 -> 0
B86: EBIT | G86: ='Income Statement'!H61 -> 45025 | H86: ='Income Statement'!I61 -> 67296 | I86: ='Income Statement'!J61 -> 67577.85 | J86: ='Income Statement'!K61 -> 70304.064 | K86: ='Income Statement'!L61 -> 102393.01 | L86: ='Income Statement'!M61 -> 91893.206 | M86: ='Income Statement'!N61 -> 47361.066 | N86: ='Income Statement'!O61 -> 44065.093 | ... AB86: ='Income Statement'!AC61 -> 390869.55
B87: EBIT Margin (%) | G87: =G86/G73 -> 0.01849098 | H87: =H86/H73 -> 0.023583578 | I87: =I86/I73 -> 0.022021498 | J87: =J86/J73 -> 0.020972957 | K87: =K86/K73 -> 0.028406759 | L87: =L86/L73 -> 0.023672309 | M87: =M86/M73 -> 0.011303159 | N87: =N86/N73 -> 0.0097468929 | ... AB87: =AB86/AB73 -> 0.030351081
B88: Financial Expenses | G88: ='ST Inv. & Debt'!F20 -> 0 | H88: ='Income Statement'!I64 -> -40962 | I88: ='Income Statement'!J64 -> -52413.042 | J88: ='Income Statement'!K64 -> -44494.359 | K88: ='Income Statement'!L64 -> -47368.432 | L88: ='Income Statement'!M64 -> -44815.328 | M88: ='Income Statement'!N64 -> -40575.356 | N88: ='Income Statement'!O64 -> -44102.34 | O88: ='Income Statement'!P64 -> -47823.728 | ... AB88: ='Income Statement'!AC64 -> #VALUE!
B89: Financial Income | G89: ='Income Statement'!H66 -> 26443 | H89: ='Income Statement'!I66 -> 36484 | I89: ='Income Statement'!J66 -> 15094.128 | J89: ='Income Statement'!K66 -> 9627.4446 | K89: ='Income Statement'!L66 -> 5616.1586 | L89: ='Income Statement'!M66 -> 5106.2911 | M89: ='Income Statement'!N66 -> 2048.8105 | N89: ='Income Statement'!O66 -> 0 | ... AB89: ='Income Statement'!AC66 -> #VALUE!
B90: EBT | G90: ='Income Statement'!H70 -> 36321 | H90: ='Income Statement'!I70 -> 62818 | I90: ='Income Statement'!J70 -> 30258.936 | J90: ='Income Statement'!K70 -> 35437.15 | K90: ='Income Statement'!L70 -> 60640.733 | L90: ='Income Statement'!M70 -> 52184.169 | M90: ='Income Statement'!N70 -> 8834.5206 | N90: ='Income Statement'!O70 -> -37.247146 | ... AB90: ='Income Statement'!AC70 -> #VALUE!
B91: Current Taxes | G91: ='Income Statement'!H73 -> 4362 | H91: ='Income Statement'!I73 -> -4228 | I91: ='Income Statement'!J73 -> -10288.038 | J91: ='Income Statement'!K73 -> -12048.631 | K91: ='Income Statement'!L73 -> -20617.849 | L91: ='Income Statement'!M73 -> -17742.617 | M91: ='Income Statement'!N73 -> -3003.737 | N91: ='Income Statement'!O73 -> 12.66403 | ... AB91: ='Income Statement'!AC73 -> #VALUE!
B92: Deferred Taxes | G92: ='Income Statement'!I74 -> -9141 | H92: ='Income Statement'!J74 -> 0 | I92: ='Income Statement'!K74 -> 0 | J92: ='Income Statement'!L74 -> 0 | K92: ='Income Statement'!M74 -> 0 | L92: ='Income Statement'!N74 -> 0 | M92: ='Income Statement'!O74 -> 0 | N92: ='Income Statement'!P74 -> 0 | ... AB92: ='Income Statement'!AD74 -> 0
B93: Extraordinary Items | G93: ='Income Statement'!I76 -> 2356 | H93: ='Income Statement'!J76 -> 0 | I93: ='Income Statement'!K76 -> 0 | J93: ='Income Statement'!L76 -> 0 | K93: ='Income Statement'!M76 -> 0 | L93: ='Income Statement'!N76 -> 0 | M93: ='Income Statement'!O76 -> 0 | N93: ='Income Statement'!P76 -> 0 | ... AB93: ='Income Statement'!AD76 -> 0
B94: Net Profit | G94: ='Income Statement'!H81 -> 32615 | H94: ='Income Statement'!I81 -> 51805 | I94: ='Income Statement'!J81 -> 19970.898 | J94: ='Income Statement'!K81 -> 23388.519 | K94: ='Income Statement'!L81 -> 40022.884 | L94: ='Income Statement'!M81 -> 34441.552 | M94: ='Income Statement'!N81 -> 5830.7836 | N94: ='Income Statement'!O81 -> -24.583116 | ... AB94: ='Income Statement'!AC81 -> #VALUE!
B95: Net Profit Margin (%) | G95: =G94/G73 -> 0.01339441 | H95: =H94/H73 -> 0.018154828 | I95: =I94/I73 -> 0.0065078881 | J95: =J94/J73 -> 0.0069772127 | K95: =K94/K73 -> 0.011103497 | L95: =L94/L73 -> 0.0088723756 | M95: =M94/M73 -> 0.0013915707 | N95: =N94/N73 -> -5.4376147e-06 | ... AB95: =AB94/AB73 -> #VALUE!
B98: CASH FLOW
B99: R$ million - nominal | G99: =G70 -> 2010 | H99: =H70 -> 2011 | I99: =I70 -> 2012 | J99: =J70 -> 2013 | K99: =K70 -> 2014 | L99: =L70 -> 2015 | M99: =M70 -> 2016 | N99: =N70 -> 2017 | ... AB99: =AB70 -> 2031
B100: Net Income | G100: ='Cash Flow'!G12 -> 0 | H100: ='Cash Flow'!G12 -> 0 | I100: ='Cash Flow'!H12 -> 19970.898 | J100: ='Cash Flow'!I12 -> 23388.519 | K100: ='Cash Flow'!J12 -> 40022.884 | L100: ='Cash Flow'!K12 -> 34441.552 | M100: ='Cash Flow'!L12 -> 5830.7836 | N100: ='Cash Flow'!M12 -> -24.583116 | O100: ='Cash Flow'!N12 -> -4551.8246 | ... AB100: ='Cash Flow'!AA12 -> #VALUE!
B101: Deferred Taxes | G101: ='Cash Flow'!G13 -> 0 | H101: ='Cash Flow'!G13 -> 0 | I101: ='Cash Flow'!H13 -> 0 | J101: ='Cash Flow'!I13 -> 0 | K101: ='Cash Flow'!J13 -> 0 | L101: ='Cash Flow'!K13 -> 0 | M101: ='Cash Flow'!L13 -> 0 | N101: ='Cash Flow'!M13 -> 0 | O101: ='Cash Flow'!N13 -> 0 | ... AB101: ='Cash Flow'!AA13 -> 0
B102: Depreciation | G102: ='Cash Flow'!G14 -> 0 | H102: ='Cash Flow'!G14 -> 0 | I102: ='Cash Flow'!H14 -> 28006.6 | J102: ='Cash Flow'!I14 -> 47863.743 | K102: ='Cash Flow'!J14 -> 63272.849 | L102: ='Cash Flow'!K14 -> 72311.827 | M102: ='Cash Flow'!L14 -> 82642.088 | N102: ='Cash Flow'!M14 -> 94448.101 | O102: ='Cash Flow'!N14 -> 107940.69 | ... AB102: ='Cash Flow'!AA14 -> 125658.84
B103: Amort. of Acquisition Goodwill | G103: ='Cash Flow'!G15 -> 0 | H103: ='Cash Flow'!G15 -> 0 | I103: ='Cash Flow'!H15 -> 0 | J103: ='Cash Flow'!I15 -> 0 | K103: ='Cash Flow'!J15 -> 0 | L103: ='Cash Flow'!K15 -> 0 | M103: ='Cash Flow'!L15 -> 0 | N103: ='Cash Flow'!M15 -> 0 | O103: ='Cash Flow'!N15 -> 0 | ... AB103: ='Cash Flow'!AA15 -> 0
B104: FX (Gain) / Loss | G104: ='Cash Flow'!G16 -> 0 | H104: ='Cash Flow'!G16 -> 0 | I104: ='Cash Flow'!H16 -> 0 | J104: ='Cash Flow'!I16 -> 0 | K104: ='Cash Flow'!J16 -> 0 | L104: ='Cash Flow'!K16 -> 0 | M104: ='Cash Flow'!L16 -> 0 | N104: ='Cash Flow'!M16 -> 0 | O104: ='Cash Flow'!N16 -> 0 | ... AB104: ='Cash Flow'!AA16 -> 0
B105: Equity Income & Others | G105: ='Cash Flow'!G17 -> 0 | H105: ='Cash Flow'!G17 -> 0 | I105: ='Cash Flow'!H17 -> 0 | J105: ='Cash Flow'!I17 -> 0 | K105: ='Cash Flow'!J17 -> 0 | L105: ='Cash Flow'!K17 -> 0 | M105: ='Cash Flow'!L17 -> 0 | N105: ='Cash Flow'!M17 -> 0 | O105: ='Cash Flow'!N17 -> 0 | ... AB105: ='Cash Flow'!AA17 -> 0
B106: Dividends Received | G106: ='Cash Flow'!G18 -> 0 | H106: ='Cash Flow'!H18 -> 0 | I106: ='Cash Flow'!I18 -> 0 | J106: ='Cash Flow'!J18 -> 0 | K106: ='Cash Flow'!K18 -> 0 | L106: ='Cash Flow'!L18 -> 0 | M106: ='Cash Flow'!M18 -> 0 | N106: ='Cash Flow'!N18 -> 0 | ... AB106: ='Cash Flow'!AB18 -> 0
...

Sheet Revenues, COGS & SG&A
A2: 1 | B2: Base Case | C2: Scenario
A3: 2 | B3: Client Case | C3: =Output!G2 -> 1
A4: 3 | B4: Stress Case
B5: Last Completed Period | C5: 40908
B7: REVENUES | D7: =+EOMONTH(E7,-12) -> 39447 | E7: =+EOMONTH(F7,-12) -> 39813 | F7: =+EOMONTH(G7,-12) -> 40178 | G7: =+EOMONTH(H7,-12) -> 40543 | H7: =C5 -> 40908 | I7: =+EOMONTH(H7,12) -> 41274 | J7: =+EOMONTH(I7,12) -> 41639 | K7: =+EOMONTH(J7,12) -> 42004 | L7: =+EOMONTH(K7,12) -> 42369 | M7: =+EOMONTH(L7,12) -> 42735 | N7: =+EOMONTH(M7,12) -> 43100 | O7: =+EOMONTH(N7,12) -> 43465 | P7: =+EOMONTH(O7,12) -> 43830 | ... AC7: =+EOMONTH(AB7,12) -> 48579
B8: R$ thousand
B10: GROSS REVENUES | C10: HISTORICO | G10: =Premissas!B9 -> 2434971 | H10: =Premissas!C9 -> 2853511 | I10: =H10*(1+CHOOSE($C$3,I11,I12,I13)) -> 3068721.7 | J10: =I10*(1+CHOOSE($C$3,J11,J12,J13)) -> 3352129.3 | K10: =J10*(1+CHOOSE($C$3,K11,K12,K13)) -> 3604529.7 | L10: =K10*(1+CHOOSE($C$3,L11,L12,L13)) -> 3881886.1 | M10: =L10*(1+CHOOSE($C$3,M11,M12,M13)) -> 4190073.4 | N10: =M10*(1+CHOOSE($C$3,N11,N12,N13)) -> 4520937.5 | O10: =N10*(1+CHOOSE($C$3,O11,O12,O13)) -> 4881166.6 | P10: =O10*(1+CHOOSE($C$3,P11,P12,P13)) -> 5270328.7 | ... AC10: =AB10*(1+CHOOSE($C$3,AC11,AC12,AC13)) -> 12878274
B11: Receita | I11: =Anual!T20/100 -> 0.075419627 | J11: =Anual!U20/100 -> 0.092353609 | K11: =Anual!V20/100 -> 0.075295561 | L11: =Anual!W20/100 -> 0.076946626 | M11: =Anual!X20/100 -> 0.07939113 | N11: =Anual!Y20/100 -> 0.078963777 | O11: =Anual!Z20/100 -> 0.079680178 | P11: =Anual!AA20/100 -> 0.079727286 | ... AC11: =Anual!AN20/100 -> 0
G12: crec | I12: =I11 -> 0.075419627 | J12: =J11 -> 0.092353609 | K12: =K11 -> 0.075295561 | L12: =L11 -> 0.076946626 | M12: =M11 -> 0.07939113 | N12: =N11 -> 0.078963777 | O12: =O11 -> 0.079680178 | P12: =P11 -> 0.079727286 | ... AD12: =AD11 -> 0
I13: 0.07 | J13: 0.07 | K13: 0.07 | L13: 0.07 | M13: 0.07 | N13: 0.07 | O13: 0.07 | P13: 0.07 | Q13: 0.07 | R13: =R12 -> 0.078695954 | S13: =S12 -> 0.078985405 | T13: =T12 -> 0.08675 | U13: =U12 -> 0.08675 | V13: =V12 -> 0.08675 | W13: =W12 -> 0.08675 | X13: =X12 -> 0.08675 | Y13: =Y12 -> 0.08675 | ... AC13: =AC12 -> 0
B23: DEVOLUÇÔES | I23: =I24*I10 -> 0 | J23: =J24*J10 -> 0 | K23: =K24*K10 -> 0 | L23: =L24*L10 -> 0 | M23: =M24*M10 -> 0 | N23: =N24*N10 -> 0 | O23: =O24*O10 -> 0 | P23: =P24*P10 -> 0 | ... AC23: =AC24*AC10 -> 0
B24: % Gross | D24: =IF(D10>0,D23/D10,0) -> 0 | E24: =IF(E10>0,E23/E10,0) -> 0 | F24: =IF(F10>0,F23/F10,0) -> 0 | G24: =IF(G10>0,G23/G10,0) -> 0 | H24: =IF(H10>0,H23/H10,0) -> 0 | I24: =AVERAGE(G24:H24) -> 0 | J24: =I24 -> 0 | K24: =J24 -> 0 | L24: =K24 -> 0 | M24: =L24 -> 0 | N24: =M24 -> 0 | O24: =N24 -> 0 | P24: =O24 -> 0 | Q24: =P24 -> 0 | ... AC24: =AB24 -> 0
B27: IMPOSTOS
B28: % Gross | D28: =IF(D13>0,D27/D13,0) -> 0 | E28: =IF(E13>0,E27/E13,0) -> 0 | F28: =IF(F13>0,F27/F13,0) -> 0 | G28: =IF(G10>0,G27/(G10-G23),0) -> 0 | H28: =IF(H10>0,H27/(H10-H23),0) -> 0 | I28: =CHOOSE($C$3,I30,I31,I32) -> 0 | J28: =CHOOSE($C$3,J30,J31,J32) -> 0 | K28: =CHOOSE($C$3,K30,K31,K32) -> 0 | L28: =CHOOSE($C$3,L30,L31,L32) -> 0 | M28: =CHOOSE($C$3,M30,M31,M32) -> 0 | N28: =CHOOSE($C$3,N30,N31,N32) -> 0 | O28: =CHOOSE($C$3,O30,O31,O32) -> 0 | P28: =CHOOSE($C$3,P30,P31,P32) -> 0 | ... AC28: =CHOOSE($C$3,AC30,AC31,AC32) -> 0
I30: 0 | J30: 0 | K30: 0 | L30: 0 | M30: 0 | N30: 0 | O30: 0 | P30: 0 | Q30: 0 | R30: 0 | S30: 0 | T30: 0 | U30: 0 | V30: 0 | W30: 0 | X30: 0 | Y30: 0 | Z30: 0 | AA30: 0 | AB30: 0 | AC30: 0
I31: 0 | J31: 0 | K31: 0 | L31: 0 | M31: 0 | N31: 0 | O31: 0 | P31: 0 | Q31: 0 | R31: 0 | S31: 0 | T31: 0 | U31: 0 | V31: 0 | W31: 0 | X31: 0 | Y31: 0 | Z31: 0 | AA31: 0 | AB31: 0 | AC31: 0
I32: 0 | J32: 0 | K32: 0 | L32: 0 | M32: 0 | N32: 0 | O32: 0 | P32: 0 | Q32: 0 | R32: 0 | S32: 0 | T32: 0 | U32: 0 | V32: 0 | W32: 0 | X32: 0 | Y32: 0 | Z32: 0 | AA32: 0 | AB32: 0 | AC32: 0
B34: RECEITA LÍQUIDA | D34: =D10-D23 -> 0 | E34: =E10-E23 -> 0 | F34: =F10-F23 -> 0 | G34: =G10-G23-G27 -> 2434971 | H34: =H10-H23-H27 -> 2853511 | I34: =I10-I23-I27 -> 3068721.7 | J34: =J10-J23-J27 -> 3352129.3 | K34: =K10-K23-K27 -> 3604529.7 | L34: =L10-L23-L27 -> 3881886.1 | M34: =M10-M23-M27 -> 4190073.4 | N34: =N10-N23-N27 -> 4520937.5 | ... AC34: =AC10-AC23-AC27 -> 12878274
B35: % Gross | D35: =IF(D10>0,D34/D10,0) -> 0 | E35: =IF(E10>0,E34/E10,0) -> 0 | F35: =IF(F10>0,F34/F10,0) -> 0 | G35: =IF(G10>0,G34/G10,0) -> 1 | H35: =IF(H$10>0,H34/H$10,0) -> 1 | I35: =H35 -> 1 | J35: =IF(J10>0,J34/J10,0) -> 1 | K35: =IF(K10>0,K34/K10,0) -> 1 | L35: =IF(L10>0,L34/L10,0) -> 1 | M35: =IF(M10>0,M34/M10,0) -> 1 | N35: =IF(N10>0,N34/N10,0) -> 1 | O35: =IF(O10>0,O34/O10,0) -> 1 | P35: =IF(P10>0,P34/P10,0) -> 1 | Q35: =IF(Q10>0,Q34/Q10,0) -> 1 | ... AC35: =IF(AC10>0,AC34/AC10,0) -> 1
B37: (Ganho de escala *0,99%)
B38: CUSTOS | G38: =-Premissas!B18 -> 1897818 | H38: =-Premissas!C18 -> 2250776 | I38: =I41+I46 -> 2425322.3 | J38: =J41+J46 -> 2652824.4 | K38: =K41+K46 -> 2825774.9 | L38: =L41+L46 -> 3061587.4 | M38: =M41+M46 -> 3356477.9 | N38: =N41+N46 -> 3628553.9 | O38: =O41+O46 -> 3924326.9 | P38: =P41+P46 -> 4140696.6 | ... AC38: =AC41+AC46 -> 10196585
G39: =G38/G34 -> 0.77940066 | H39: , | I39: =I38/I34 -> 0.79033633 | J39: =J38/J34 -> 0.79138487 | K39: =K38/K34 -> 0.78395107 | L39: =L38/L34 -> 0.78868552 | M39: =M38/M34 -> 0.80105467 | N39: =N38/N34 -> 0.80261094 | O39: =O38/O34 -> 0.80397315 | P39: =P38/P34 -> 0.78566192 | ... AC39: =AC38/AC34 -> 0.79176641
B41: Custo Variável | D41: =IF(D$10>0,D38/D$10,0) -> 0 | E41: =IF(E$34>0,E38/E$34,0) -> 0 | F41: =IF(F$34>0,F38/F$34,0) -> 0 | G41: =G38 -> 1897818 | H41: =H38 -> 2250776 | I41: =CHOOSE($C$3,I42,I43,I44)*(I34) -> 2425322.3 | J41: =CHOOSE($C$3,J42,J43,J44)*(J34) -> 2652824.4 | K41: =CHOOSE($C$3,K42,K43,K44)*(K34) -> 2825774.9 | L41: =CHOOSE($C$3,L42,L43,L44)*(L34) -> 3061587.4 | M41: =CHOOSE($C$3,M42,M43,M44)*(M34) -> 3356477.9 | N41: =CHOOSE($C$3,N42,N43,N44)*(N34) -> 3628553.9 | O41: =CHOOSE($C$3,O42,O43,O44)*(O34) -> 3924326.9 | P41: =CHOOSE($C$3,P42,P43,P44)*(P34) -> 4140696.6 | ... AC41: =CHOOSE($C$3,AC42,AC43,AC44)*(AC34) -> 10196585
G42: =G38/G34 -> 0.77940066 | H42: =H38/H34 -> 0.78877425 | I42: 0.79033633 | J42: 0.79138487 | K42: 0.78395107 | L42: 0.78868552 | M42: 0.80105467 | N42: 0.80261094 | O42: 0.80397315 | P42: 0.78566192 | Q42: =AVERAGE(O42:P42) -> 0.79481754 | R42: =AVERAGE(P42:Q42) -> 0.79023973 | S42: =AVERAGE(Q42:R42) -> 0.79252863 | T42: =AVERAGE(R42:S42) -> 0.79138418 | U42: =AVERAGE(S42:T42) -> 0.79195641 | V42: =AVERAGE(T42:U42) -> 0.79167029 | W42: =AVERAGE(U42:V42) -> 0.79181335 | X42: =AVERAGE(V42:W42) -> 0.79174182 | ... AC42: =AVERAGE(AA42:AB42) -> 0.79176641
I43: =I42 -> 0.79033633 | J43: =J42 -> 0.79138487 | K43: =K42 -> 0.78395107 | L43: =L42 -> 0.78868552 | M43: =M42 -> 0.80105467 | N43: =N42 -> 0.80261094 | O43: =O42 -> 0.80397315 | P43: =P42 -> 0.78566192 | ... AC43: =AC42 -> 0.79176641
I44: =I43 -> 0.79033633 | J44: 0.3527 | K44: 0.3869 | L44: 0.4164 | M44: 0.4528 | N44: 0.5032 | O44: 0.5 | P44: =P43 -> 0.78566192 | Q44: =Q43 -> 0.79481754 | R44: =R43 -> 0.79023973 | S44: =S43 -> 0.79252863 | T44: =T43 -> 0.79138418 | U44: =U43 -> 0.79195641 | V44: =V43 -> 0.79167029 | W44: =W43 -> 0.79181335 | ... AC44: =AC43 -> 0.79176641
B46: Custo Fixo | I46: =H46*(1+Anual!T41/100)*H41 -> 0 | J46: =I46*(1+Anual!U41/100) -> 0 | K46: =J46*(1+Anual!V41/100) -> 0 | L46: =K46*(1+Anual!W41/100) -> 0 | M46: =L46*(1+Anual!X41/100) -> 0 | N46: =M46*(1+Anual!Y41/100) -> 0 | O46: =N46*(1+Anual!Z41/100) -> 0 | P46: =O46*(1+Anual!AA41/100) -> 0 | Q46: =P46*(1+Anual!AB41/100) -> 0 | ... AC46: =AB46*(1+Anual!AN41/100) -> 0
B48: SG&A | G48: =-Premissas!B28 -> 492128 | H48: =-Premissas!C28 -> 535439 | I48: =I52 -> 575821.61 | J48: =J52 -> 629000.81 | K48: =K52 -> 676361.78 | L48: =L52 -> 728405.54 | M48: =M52 -> 786234.48 | N48: =N52 -> 848318.52 | O48: =O52 -> 915912.69 | P48: =P52 -> 988935.93 | ... U48: =U52 -> 1466932.8 | V48: =V52-V57 -> 1470298.2 | W48: =W52-W57 -> 1606315.5 | X48: =X52-X57 -> 1756207.3 | Y48: =Y52-Y57 -> 1918760.6 | Z48: =Z52-Z57 -> 2095642.4 | AA48: =AA52-AA57 -> 2289053.3 | AB48: =AB52-AB57 -> 2290848.5 | AC48: =AC52-AC57 -> 2290070.2
B49: % Gross | D49: =D48/D34 -> #DIV/0! | E49: =E48/E34 -> #DIV/0! | F49: =F48/F34 -> #DIV/0! | G49: =G48/G34 -> 0.20210836 | H49: =H48/H34 -> 0.18764217 | I49: =I48/I34 -> 0.18764217 | J49: =J48/J34 -> 0.18764217 | K49: =K48/K34 -> 0.18764217 | ... AC49: =AC48/AC34 -> 0.17782431
G52: =G48 -> 492128 | H52: =H48 -> 535439 | I52: =CHOOSE($C$3,I53,I54,I55)*(I34) -> 575821.61 | J52: =CHOOSE($C$3,J53,J54,J55)*(J34) -> 629000.81 | K52: =CHOOSE($C$3,K53,K54,K55)*(K34) -> 676361.78 | L52: =CHOOSE($C$3,L53,L54,L55)*(L34) -> 728405.54 | M52: =CHOOSE($C$3,M53,M54,M55)*(M34) -> 786234.48 | N52: =CHOOSE($C$3,N53,N54,N55)*(N34) -> 848318.52 | O52: =CHOOSE($C$3,O53,O54,O55)*(O34) -> 915912.69 | P52: =CHOOSE($C$3,P53,P54,P55)*(P34) -> 988935.93 | ... AC52: =CHOOSE($C$3,AC53,AC54,AC55)*(AC34) -> 2416507.3
G53: =G48/G34 -> 0.20210836 | H53: =H48/H34 -> 0.18764217 | I53: =H53 -> 0.18764217 | J53: =AVERAGE(H53:I53) -> 0.18764217 | K53: =AVERAGE(I53:J53) -> 0.18764217 | L53: =AVERAGE(J53:K53) -> 0.18764217 | M53: =AVERAGE(K53:L53) -> 0.18764217 | N53: =AVERAGE(L53:M53) -> 0.18764217 | O53: =AVERAGE(M53:N53) -> 0.18764217 | P53: =AVERAGE(N53:O53) -> 0.18764217 | Q53: =AVERAGE(O53:P53) -> 0.18764217 | ... AC53: =AVERAGE(AA53:AB53) -> 0.18764217
I54: =I53 -> 0.18764217 | J54: =J53 -> 0.18764217 | K54: =K53 -> 0.18764217 | L54: =L53 -> 0.18764217 | M54: =M53 -> 0.18764217 | N54: =N53 -> 0.18764217 | O54: =O53 -> 0.18764217 | P54: =P53 -> 0.18764217 | ... AC54: =AC53 -> 0.18764217
I55: =I54 -> 0.18764217 | J55: =J54 -> 0.18764217 | K55: =K54 -> 0.18764217 | L55: =L54 -> 0.18764217 | M55: =M54 -> 0.18764217 | N55: =N54 -> 0.18764217 | O55: =O54 -> 0.18764217 | P55: =P54 -> 0.18764217 | ... AC55: =AC54 -> 0.18764217
B57: (+) Depreciação | G57: 37436 | H57: 48205 | I57: ='Fixed Assets & CAPEX'!H77 -> 28006.6 | J57: ='Fixed Assets & CAPEX'!I77 -> 47863.743 | K57: ='Fixed Assets & CAPEX'!J77 -> 63272.849 | L57: ='Fixed Assets & CAPEX'!K77 -> 72311.827 | M57: ='Fixed Assets & CAPEX'!L77 -> 82642.088 | N57: ='Fixed Assets & CAPEX'!M77 -> 94448.101 | O57: ='Fixed Assets & CAPEX'!N77 -> 107940.69 | P57: ='Fixed Assets & CAPEX'!O77 -> 123360.79 | ... AC57: ='Fixed Assets & CAPEX'!AB77 -> 126437.15
B58: % Gross | D58: =D57/D34 -> #DIV/0! | E58: =E57/E34 -> #DIV/0! | F58: =F57/F34 -> #DIV/0! | G58: =G57/G34 -> 0.01537431 | H58: =H57/H34 -> 0.016893224 | I58: =I57/I34 -> 0.009126471 | J58: =J57/J34 -> 0.014278609 | K58: =K57/K34 -> 0.017553704 | ... AC58: =AC57/AC34 -> 0.009817864
B60: (+) Amortização | I60: ='Goodwill, Taxes & Div.'!H31 -> 0 | J60: ='Goodwill, Taxes & Div.'!I31 -> 0 | K60: ='Goodwill, Taxes & Div.'!J31 -> 0 | L60: ='Goodwill, Taxes & Div.'!K31 -> 0 | M60: ='Goodwill, Taxes & Div.'!L31 -> 0 | N60: ='Goodwill, Taxes & Div.'!M31 -> 0 | O60: ='Goodwill, Taxes & Div.'!N31 -> 0 | P60: ='Goodwill, Taxes & Div.'!O31 -> 0 | ... AC60: ='Goodwill, Taxes & Div.'!AB31 -> 0
B61: % Gross | D61: =D60/#REF! -> #REF! | E61: =E60/#REF! -> #REF! | F61: =F60/#REF! -> #REF! | G61: =G60/#REF! -> #REF! | H61: =G61 -> #REF! | I61: =H61 -> #REF! | J61: =I61 -> #REF! | K61: =J61 -> #REF! | L61: =K61 -> #REF! | M61: =L61 -> #REF! | N61: =M61 -> #REF! | O61: =N61 -> #REF! | ... AC61: =AB61 -> #REF!
B64: EBITDA | D64: =D34-D38-D48+D57 -> 0 | E64: =E34-E38-E48+E57 -> 0 | F64: =F34-F38-F48+F57 -> 0 | G64: =G34-G38-G48+G57 -> 82461 | H64: =H34-H38-H48+H57 -> 115501 | I64: =I34-I38-I48+I57 -> 95584.45 | J64: =J34-J38-J48+J57 -> 118167.81 | K64: =K34-K38-K48+K57 -> 165665.86 | ... AC64: =AC34-AC38-AC48+AC57 -> 518056.22
B65: EBITDA Margin | D65: =D64/D34 -> #DIV/0! | E65: =E64/E34 -> #DIV/0! | F65: =F64/F34 -> #DIV/0! | G65: =G64/G34 -> 0.03386529 | H65: =H64/H34 -> 0.040476802 | I65: =I64/I34 -> 0.031147969 | J65: =J64/J34 -> 0.035251566 | K65: =K64/K34 -> 0.045960463 | ... AC65: =AC64/AC34 -> 0.040227146
I67: 0.071168652 | J67: 0.098047706 | K67: 0.1577181 | L67: 0.19428325 | M67: 0.24390214 | N67: 0.31483632
I69: =Output!I23 -> 2.9997818 | J69: =Output!J23 -> 3.0000248 | K69: =Output!K23 -> 2.0764738 | L69: =Output!L23 -> 2.0802647 | M69: =Output!M23 -> 2.7782792 | N69: =Output!N23 -> 2.7958095 | O69: =Output!O23 -> 2.8122906 | P69: =Output!P23 -> 1.4727765

Sheet Premissas
A1: Premissas
A3: Receitas
B4: 2010 | C4: 2011 | D4: =C4+1 -> 2012 | E4: =D4+1 -> 2013 | F4: =E4+1 -> 2014 | G4: =F4+1 -> 2015 | H4: =G4+1 -> 2016 | I4: =H4+1 -> 2017 | J4: =I4+1 -> 2018
A6: Contraprest. efetivas de plano de assist. à saúde | B6: 2109847 | C6: 2461029
A7: Outras receitas oper. de assist. à saúde não relac. com planos de saúde da operadora | B7: 325124 | C7: 392482
A9: Total | B9: =SUM(B6:B7) -> 2434971 | C9: =SUM(C6:C7) -> 2853511
A12: Eventos conhecidos ou avisados | B12: -1573150 | C12: -2046013
A13: Recuperação de eventos conhecidos ou avisados | B13: 8133 | C13: 209233
A14: Outras Recuperações/Ressarcimentos/Deduções de | B14: 7741 | C14: 15434
A15: Variação da provisão de eventos ocorridos e não avisados | B15: -42210 | C15: -56528
A16: Outras despesas oper. de assist. à saúde não relac. com planos de saúde da operadora | B16: -298332 | C16: -372902
A18: Eventos indenizáveis líquidos | B18: =SUM(B12:B16) -> -1897818 | C18: =SUM(C12:C16) -> -2250776
A21: Despesas de comercialização | B21: -142210 | C21: -183324
A22: Despesas administrativas | B22: -300484 | C22: -314590
A23: Outras receitas operacionais | B23: 4774 | C23: 4789
A24: Outras despesas operacionais | B24: =SUM(B25:B27) -> -54208 | C24: =SUM(C25:C27) -> -42314
A25: Provisão para perdas sobre créditos | B25: -42990 | C25: -26184
A26: Provisão para contingências - operacional | B26: -1406 | C26: -7179
A27: Outras | B27: -9812 | C27: -8951
A28: Total | B28: =SUM(B21:B24) -> -492128 | C28: =SUM(C21:C24) -> -535439

Sheet Income Statement
A7: =+A6+1 -> 1 | C7: INCOME STATEMENT | E7: ='Revenues, COGS & SG&A'!D7 -> 39447 | F7: ='Revenues, COGS & SG&A'!E7 -> 39813 | G7: ='Revenues, COGS & SG&A'!F7 -> 40178 | H7: ='Revenues, COGS & SG&A'!G7 -> 40543 | I7: ='Revenues, COGS & SG&A'!H7 -> 40908 | J7: ='Revenues, COGS & SG&A'!I7 -> 41274 | K7: ='Revenues, COGS & SG&A'!J7 -> 41639 | L7: ='Revenues, COGS & SG&A'!K7 -> 42004 | ... AD7: ='Revenues, COGS & SG&A'!AC7 -> 48579
A8: =+A7+1 -> 2 | C8: R$ thousand
A9: =+A8+1 -> 3
A10: =+A9+1 -> 4 | B10: + | C10: GROSS REVENUES | E10: ='Revenues, COGS & SG&A'!D10 -> 0 | F10: ='Revenues, COGS & SG&A'!E10 -> 0 | G10: ='Revenues, COGS & SG&A'!F10 -> 0 | H10: ='Revenues, COGS & SG&A'!G10 -> 2434971 | I10: ='Revenues, COGS & SG&A'!H10 -> 2853511 | J10: ='Revenues, COGS & SG&A'!I10 -> 3068721.7 | K10: ='Revenues, COGS & SG&A'!J10 -> 3352129.3 | L10: ='Revenues, COGS & SG&A'!K10 -> 3604529.7 | ... AD10: ='Revenues, COGS & SG&A'!AC10 -> 12878274
A11: =+A10+1 -> 5 | C11: Gross Revenues
A12: =+A11+1 -> 6 | C12: Item 2
A13: =+A12+1 -> 7 | C13: Item 3
A14: =+A13+1 -> 8 | C14: Item 4
A15: =+A14+1 -> 9 | C15: Item 5
A16: =+A15+1 -> 10
A17: =+A16+1 -> 11 | B17: (-) | C17: Deductions | F17: ='Revenues, COGS & SG&A'!D23+'Revenues, COGS & SG&A'!#REF! -> #REF! | G17: ='Revenues, COGS & SG&A'!E23+'Revenues, COGS & SG&A'!#REF! -> #REF! | H17: =SUM(H18:H22) -> 0 | I17: =SUM(I18:I22) -> 0 | J17: =SUM(J18:J22) -> 0 | K17: =SUM(K18:K22) -> 0 | L17: =SUM(L18:L22) -> 0 | M17: =SUM(M18:M22) -> 0 | N17: =SUM(N18:N22) -> 0 | O17: =SUM(O18:O22) -> 0 | ... AD17: =SUM(AD18:AD22) -> 0
A18: =+A17+1 -> 12 | C18: Vendas Canceladas | H18: ='Revenues, COGS & SG&A'!G23 -> 0 | I18: ='Revenues, COGS & SG&A'!H23 -> 0 | J18: ='Revenues, COGS & SG&A'!I23 -> 0 | K18: ='Revenues, COGS & SG&A'!J23 -> 0 | L18: ='Revenues, COGS & SG&A'!K23 -> 0 | M18: ='Revenues, COGS & SG&A'!L23 -> 0 | N18: ='Revenues, COGS & SG&A'!M23 -> 0 | O18: ='Revenues, COGS & SG&A'!N23 -> 0 | ... AD18: ='Revenues, COGS & SG&A'!AC23 -> 0
A19: =+A18+1 -> 13 | C19: Impostos Diretos | H19: ='Revenues, COGS & SG&A'!G27 -> 0 | I19: ='Revenues, COGS & SG&A'!H27 -> 0 | J19: ='Revenues, COGS & SG&A'!I27 -> 0 | K19: ='Revenues, COGS & SG&A'!J27 -> 0 | L19: ='Revenues, COGS & SG&A'!K27 -> 0 | M19: ='Revenues, COGS & SG&A'!L27 -> 0 | N19: ='Revenues, COGS & SG&A'!M27 -> 0 | O19: ='Revenues, COGS & SG&A'!N27 -> 0 | ... AD19: ='Revenues, COGS & SG&A'!AC27 -> 0
A20: =+A19+1 -> 14 | C20: Item 3
C21: Item 4
C22: Item 5
A23: =+A20+1 -> 15
A24: =+A23+1 -> 16 | B24: = | C24: NET REVENUES | E24: =E10-E17 -> 0 | F24: =F10-F17 -> #REF! | G24: =G10-G17 -> #REF! | H24: =H10-H17 -> 2434971 | I24: =I10-I17 -> 2853511 | J24: =J10-J17 -> 3068721.7 | K24: =K10-K17 -> 3352129.3 | L24: =L10-L17 -> 3604529.7 | ... AD24: =AD10-AD17 -> 12878274
A25: =+A24+1 -> 17
A26: =+A25+1 -> 18 | B26: (-) | C26: COGS | E26: ='Revenues, COGS & SG&A'!D38 -> 0 | F26: ='Revenues, COGS & SG&A'!E38 -> 0 | G26: ='Revenues, COGS & SG&A'!F38 -> 0 | H26: =SUM(H27:H31) -> 1897818 | I26: =SUM(I27:I31) -> 2250776 | J26: =SUM(J27:J31) -> 2425322.3 | K26: =SUM(K27:K31) -> 2652824.4 | L26: =SUM(L27:L31) -> 2825774.9 | M26: =SUM(M27:M31) -> 3061587.4 | N26: =SUM(N27:N31) -> 3356477.9 | O26: =SUM(O27:O31) -> 3628553.9 | ... AD26: =SUM(AD27:AD31) -> 10196585
A27: =+A26+1 -> 19 | C27: Item 1 | H27: ='Revenues, COGS & SG&A'!G38 -> 1897818 | I27: ='Revenues, COGS & SG&A'!H38 -> 2250776 | J27: ='Revenues, COGS & SG&A'!I38 -> 2425322.3 | K27: ='Revenues, COGS & SG&A'!J38 -> 2652824.4 | L27: ='Revenues, COGS & SG&A'!K38 -> 2825774.9 | M27: ='Revenues, COGS & SG&A'!L38 -> 3061587.4 | N27: ='Revenues, COGS & SG&A'!M38 -> 3356477.9 | O27: ='Revenues, COGS & SG&A'!N38 -> 3628553.9 | ... AD27: ='Revenues, COGS & SG&A'!AC38 -> 10196585
A28: =+A27+1 -> 20 | C28: Item 2
A29: =+A28+1 -> 21 | C29: Item 3
A30: =+A29+1 -> 22 | C30: Item 4
A31: =+A30+1 -> 23 | C31: Item 5
A32: =+A31+1 -> 24
A33: =+A32+1 -> 25 | B33: = | C33: GROSS PROFIT | E33: =E24-E26 -> 0 | F33: =F24-F26 -> #REF! | G33: =G24-G26 -> #REF! | H33: =H24-H26 -> 537153 | I33: =I24-I26 -> 602735 | J33: =J24-J26 -> 643399.46 | K33: =K24-K26 -> 699304.88 | L33: =L24-L26 -> 778754.79 | ... AD33: =AD24-AD26 -> 2681689.3
A34: =+A33+1 -> 26
A35: =+A34+1 -> 27 | B35: (-) | C35: SG&A | E35: ='Revenues, COGS & SG&A'!D48 -> 0 | F35: ='Revenues, COGS & SG&A'!E48 -> 0 | G35: ='Revenues, COGS & SG&A'!F48 -> 0 | H35: =SUM(H36:H40) -> 492128 | I35: =SUM(I36:I40) -> 535439 | J35: =SUM(J36:J40) -> 575821.61 | K35: ='Revenues, COGS & SG&A'!J48 -> 629000.81 | L35: ='Revenues, COGS & SG&A'!K48 -> 676361.78 | M35: ='Revenues, COGS & SG&A'!L48 -> 728405.54 | N35: ='Revenues, COGS & SG&A'!M48 -> 786234.48 | O35: ='Revenues, COGS & SG&A'!N48 -> 848318.52 | P35: ='Revenues, COGS & SG&A'!O48 -> 915912.69 | Q35: ='Revenues, COGS & SG&A'!P48 -> 988935.93 | R35: ='Revenues, COGS & SG&A'!Q48 -> 1067176.6 | ... AD35: ='Revenues, COGS & SG&A'!AC48 -> 2290070.2
A36: =+A35+1 -> 28 | C36: Item 1 | H36: ='Revenues, COGS & SG&A'!G48 -> 492128 | I36: ='Revenues, COGS & SG&A'!H48 -> 535439 | J36: ='Revenues, COGS & SG&A'!I48 -> 575821.61 | K36: ='Revenues, COGS & SG&A'!J48 -> 629000.81 | L36: ='Revenues, COGS & SG&A'!K48 -> 676361.78 | M36: ='Revenues, COGS & SG&A'!L48 -> 728405.54 | N36: ='Revenues, COGS & SG&A'!M48 -> 786234.48 | O36: ='Revenues, COGS & SG&A'!N48 -> 848318.52 | ... AD36: ='Revenues, COGS & SG&A'!AC48 -> 2290070.2
A37: =+A36+1 -> 29 | C37: Item 2
A38: =+A37+1 -> 30 | C38: Item 3
A39: =+A38+1 -> 31 | C39: Item 4
A40: =+A39+1 -> 32 | C40: Item 5
A41: =+A40+1 -> 33
A42: =+A41+1 -> 34 | B42: = | C42: EBITDA | E42: =E33-E35 -> 0 | F42: =F33-F35+F44 -> #REF! | G42: =G33-G35+G44 -> #REF! | H42: =H33-H36+H44 -> 82461 | I42: =I33-I36+I44 -> 115501 | J42: =J33-J36+J44 -> 95584.45 | K42: =K33-K36+K44 -> 118167.81 | L42: =L33-L36+L44 -> 165665.86 | M42: =M33-M36+M44 -> 164205.03 | N42: =N33-N36+N44 -> 130003.15 | O42: =O33-O36+O44 -> 138513.19 | ... AD42: =AD33-AD36+AD44 -> 518056.22
A43: =+A42+1 -> 35
A44: =+A43+1 -> 36 | B44: (-) | C44: Depreciation and Amortization | F44: 4900 | G44: 2300 | H44: ='Revenues, COGS & SG&A'!G57 -> 37436 | I44: ='Revenues, COGS & SG&A'!H57 -> 48205 | J44: ='Fixed Assets & CAPEX'!H28 -> 28006.6 | K44: ='Fixed Assets & CAPEX'!I28 -> 47863.743 | L44: ='Fixed Assets & CAPEX'!J28 -> 63272.849 | M44: ='Fixed Assets & CAPEX'!K28 -> 72311.827 | N44: ='Fixed Assets & CAPEX'!L28 -> 82642.088 | O44: ='Fixed Assets & CAPEX'!M28 -> 94448.101 | P44: ='Fixed Assets & CAPEX'!N28 -> 107940.69 | Q44: ='Fixed Assets & CAPEX'!O28 -> 123360.79 | ... AD44: ='Fixed Assets & CAPEX'!AB28 -> 126437.15
A45: =+A44+1 -> 37
A46: =+A45+1 -> 38 | B46: (-) | C46: Goodwill Amortization | J46: ='Goodwill, Taxes & Div.'!H31 -> 0 | K46: ='Goodwill, Taxes & Div.'!I31 -> 0 | L46: ='Goodwill, Taxes & Div.'!J31 -> 0 | M46: ='Goodwill, Taxes & Div.'!K31 -> 0 | N46: ='Goodwill, Taxes & Div.'!L31 -> 0 | O46: ='Goodwill, Taxes & Div.'!M31 -> 0 | P46: ='Goodwill, Taxes & Div.'!N31 -> 0 | Q46: ='Goodwill, Taxes & Div.'!O31 -> 0 | ... AD46: ='Goodwill, Taxes & Div.'!AB31 -> 0
A47: =+A46+1 -> 39
A48: =+A47+1 -> 40 | B48: + | C48: Non-Cash Operating Items | H48: =SUM(H49:H51) -> 0 | I48: =SUM(I49:I51) -> 0 | J48: =SUM(J49:J51) -> 0 | K48: =SUM(K49:K51) -> 0 | L48: =SUM(L49:L51) -> 0 | M48: =SUM(M49:M51) -> 0 | N48: =SUM(N49:N51) -> 0 | O48: =SUM(O49:O51) -> 0 | ... AD48: =SUM(AD49:AD51) -> 0
A49: =+A48+1 -> 41 | C49: Item 1
A50: =+A49+1 -> 42 | C50: Item 2
A51: =+A50+1 -> 43 | C51: Item 3
A52: =+A51+1 -> 44
A53: =+A52+1 -> 45 | B53: + | C53: Non-Operating Result | I53: =I54+I57 -> 0 | J53: =J54+J57 -> 0 | K53: =K54+K57 -> 0 | L53: =L54+L57 -> 0 | M53: =M54+M57 -> 0 | N53: =N54+N57 -> 0 | O53: =O54+O57 -> 0 | P53: =P54+P57 -> 0 | ... AD53: =AD54+AD57 -> 0
A54: =+A53+1 -> 46 | C54: Non-Operating Income | I54: =SUM(I55:I56) -> 0 | J54: =SUM(J55:J56) -> 0 | K54: =SUM(K55:K56) -> 0 | L54: =SUM(L55:L56) -> 0 | M54: =SUM(M55:M56) -> 0 | N54: =SUM(N55:N56) -> 0 | O54: =SUM(O55:O56) -> 0 | P54: =SUM(P55:P56) -> 0 | ... AD54: =SUM(AD55:AD56) -> 0
A55: =+A54+1 -> 47 | C55: Outros | J55: =-'ST Inv. & Debt'!H345 -> 0 | K55: =-'ST Inv. & Debt'!I345 -> 0 | L55: =-'ST Inv. & Debt'!J345 -> 0 | M55: =-'ST Inv. & Debt'!K345 -> 0 | N55: =-'ST Inv. & Debt'!L345 -> 0 | O55: =-'ST Inv. & Debt'!M345 -> 0
A56: =+A55+1 -> 48 | C56: Item 2
A57: =+A56+1 -> 49 | C57: Non-Operating Expense | I57: =SUM(I58:I59) -> 0 | J57: =SUM(J58:J59) -> 0 | K57: =SUM(K58:K59) -> 0 | L57: =SUM(L58:L59) -> 0 | M57: =SUM(M58:M59) -> 0 | N57: =SUM(N58:N59) -> 0 | O57: =SUM(O58:O59) -> 0 | P57: =SUM(P58:P59) -> 0 | ... AD57: =SUM(AD58:AD59) -> 0
A58: =+A57+1 -> 50 | C58: Outros | J58: 0 | K58: 0 | L58: 0 | M58: 0 | N58: 0 | O58: 0 | P58: 0 | Q58: 0 | R58: 0 | S58: 0 | T58: 0 | U58: 0 | V58: 0 | W58: 0 | X58: 0 | Y58: 0 | Z58: 0 | AA58: 0 | AB58: 0 | AC58: 0 | AD58: 0
A59: =+A58+1 -> 51 | C59: Item 2
A60: =+A59+1 -> 52
A61: =+A60+1 -> 53 | B61: = | C61: EBIT | E61: =E33-E35 -> 0 | F61: =F42-F44 -> #REF! | G61: =G42-G44 -> #REF! | H61: =H42-H44+H48 -> 45025 | I61: =I42-I44+I48 -> 67296 | J61: =J42-J44 -> 67577.85 | K61: =K42-K44 -> 70304.064 | L61: =L42-L44 -> 102393.01 | M61: =M42-M44 -> 91893.206 | N61: =N42-N44 -> 47361.066 | O61: =O42-O44 -> 44065.093 | P61: =P42-P44 -> 40927.024 | Q61: =Q42-Q44 -> 140696.19 | ... AD61: =AD42-AD44 -> 391619.07
A62: =+A61+1 -> 54
A63: =+A62+1 -> 55 | B63: + | C63: Financial Result | F63: =SUM(F64:F67) -> -1200 | G63: =SUM(G64:G67) -> -1537 | H63: =SUM(H64:H67) -> -8704 | I63: =SUM(I64:I67) -> -4478 | J63: =SUM(J64:J67) -> -37318.914 | K63: =SUM(K64:K67) -> -34866.915 | L63: =SUM(L64:L67) -> -41752.273 | M63: =SUM(M64:M67) -> -39709.037 | ... AD63: =SUM(AD64:AD67) -> #DIV/0!
A64: =+A63+1 -> 56 | C64: Financial Expenses | F64: -1200 | G64: -1537 | H64: -35147 | I64: -40962 | J64: ='ST Inv. & Debt'!H20 -> -52413.042 | K64: ='ST Inv. & Debt'!I20 -> -44494.359 | L64: ='ST Inv. & Debt'!J20 -> -47368.432 | M64: ='ST Inv. & Debt'!K20 -> -44815.328 | N64: ='ST Inv. & Debt'!L20 -> -40575.356 | O64: ='ST Inv. & Debt'!M20 -> -44102.34 | P64: ='ST Inv. & Debt'!N20 -> -47823.728 | Q64: ='ST Inv. & Debt'!O20 -> -53718.068 | ... AD64: ='ST Inv. & Debt'!AB20 -> #DIV/0!
A65: =+A64+1 -> 57 | C65: FX Gain / (Loss)
A66: =+A65+1 -> 58 | C66: Financial Income | H66: 26443 | I66: 36484 | J66: ='ST Inv. & Debt'!G47 -> 15094.128 | K66: ='ST Inv. & Debt'!H47 -> 9627.4446 | L66: ='ST Inv. & Debt'!I47 -> 5616.1586 | M66: ='ST Inv. & Debt'!J47 -> 5106.2911 | N66: ='ST Inv. & Debt'!K47 -> 2048.8105 | O66: ='ST Inv. & Debt'!L47 -> 0 | P66: ='ST Inv. & Debt'!M47 -> 0 | Q66: ='ST Inv. & Debt'!N47 -> 0 | ... AD66: ='ST Inv. & Debt'!AA47 -> #VALUE!
C67: Participação no Resultado
A69: =+A66+1 -> 59
A70: =+A69+1 -> 60 | B70: = | C70: EBT | E70: =E61+E63 -> 0 | F70: =F61+F63 -> #REF! | G70: =G61+G63 -> #REF! | H70: =H61+H63 -> 36321 | I70: =I61+I63 -> 62818 | J70: =J61+J63 -> 30258.936 | K70: =K61+K63 -> 35437.15 | L70: =L61+L63 -> 60640.733 | ... AD70: =AD61+AD63 -> #DIV/0!
A71: =+A70+1 -> 61
A72: =+A71+1 -> 62 | B72: (-) | C72: Income tax | E72: =SUM(E73:E74) -> 0 | F72: =SUM(F73:F74) -> -1378 | G72: =SUM(G73:G74) -> -3404 | H72: =SUM(H73:H74) -> -1740 | I72: =SUM(I73:I74) -> -13369 | J72: =SUM(J73:J74) -> -10288.038 | K72: =SUM(K73:K74) -> -12048.631 | L72: =SUM(L73:L74) -> -20617.849 | ... AD72: =SUM(AD73:AD74) -> #DIV/0!
A73: =+A72+1 -> 63 | C73: Current Taxes | F73: -1378 | G73: -3404 | H73: =-1535-561+4749+1709 -> 4362 | I73: =-4505-1630+1402+505 -> -4228 | J73: =-$I75*J70 -> -10288.038 | K73: =-$I75*K70 -> -12048.631 | L73: =-$I75*L70 -> -20617.849 | M73: =-$I75*M70 -> -17742.617 | N73: =-$I75*N70 -> -3003.737 | O73: =-$I75*O70 -> 12.66403 | P73: =-$I75*P70 -> 2344.8793 | Q73: =-$I75*Q70 -> -29572.561 | ... AD73: =-$I75*AD70 -> #DIV/0!
A74: =+A73+1 -> 64 | C74: Fundo de reserva e Fundo de assist. de educ. e social | H74: =-4068-2034 -> -6102 | I74: =-6094-3047 -> -9141
A75: =+A74+1 -> 65 | I75: 0.34
A76: =+A75+1 -> 66 | B76: + | C76: Extraordinary Items | H76: =SUM(H77:H78) -> -1966 | I76: =SUM(I77:I78) -> 2356 | J76: =SUM(J77:J78) -> 0 | K76: =SUM(K77:K78) -> 0 | L76: =SUM(L77:L78) -> 0 | M76: =SUM(M77:M78) -> 0 | N76: =SUM(N77:N78) -> 0 | O76: =SUM(O77:O78) -> 0 | ... AD76: =SUM(AD77:AD78) -> 0
A77: =+A76+1 -> 67 | C77: Receitas Patrimoniais | H77: 2203 | I77: 8443
A78: =+A77+1 -> 68 | C78: Despesas Patrimoniais | H78: -4169 | I78: -6087 | N78: =-'ST Inv. & Debt'!L345 -> 0 | O78: =-'ST Inv. & Debt'!M345 -> 0
A79: =+A78+1 -> 69
A80: =+A79+1 -> 70
A81: =+A80+1 -> 71 | B81: = | C81: NET PROFIT | E81: =E70+E72+E76 -> 0 | F81: =F70+F72+F76 -> #REF! | G81: =G70+G72+G76 -> #REF! | H81: =H70+H72+H76 -> 32615 | I81: =I70+I72+I76 -> 51805 | J81: =J70+J72 -> 19970.898 | K81: =K70+K72 -> 23388.519 | L81: =L70+L72 -> 40022.884 | M81: =M70+M72 -> 34441.552 | N81: =N70+N72 -> 5830.7836 | O81: =O70+O72 -> -24.583116 | P81: =P70+P72 -> -4551.8246 | Q81: =Q70+Q72 -> 57405.56 | ... AD81: =AD70+AD72 -> #DIV/0!
A82: =+A81+1 -> 72
A83: =+A82+1 -> 73
A84: =+A83+1 -> 74
A85: =+A84+1 -> 75
A86: =+A85+1 -> 76
A87: =+A86+1 -> 77 | C87: DSCR1
A88: =+A87+1 -> 78 | C88: DSCR2
A89: =+A88+1 -> 79 | C89: DSCR3

Sheet Balance Sheet
C7: BALANCE SHEET | E7: ='Revenues, COGS & SG&A'!D7 -> 39447 | F7: ='Revenues, COGS & SG&A'!E7 -> 39813 | G7: ='Revenues, COGS & SG&A'!F7 -> 40178 | H7: ='Revenues, COGS & SG&A'!G7 -> 40543 | I7: ='Revenues, COGS & SG&A'!H7 -> 40908 | J7: ='Revenues, COGS & SG&A'!I7 -> 41274 | K7: ='Revenues, COGS & SG&A'!J7 -> 41639 | L7: ='Revenues, COGS & SG&A'!K7 -> 42004 | ... AD7: ='Revenues, COGS & SG&A'!AC7 -> 48579
C8: R$ thousand
C10: ASSETS | E10: =E12+E27+E34 -> 0 | F10: =F12+F27+F34 -> 0 | G10: =G12+G27+G34 -> 0 | H10: =H12+H27+H34 -> 1414974 | I10: =I12+I27+I34 -> 1718166 | J10: =J12+J27+J34 -> 1778246 | K10: =K12+K27+K34 -> 1891710.1 | L10: =L12+L27+L34 -> 1879429.6 | ... AD10: =AD12+AD27+AD34 -> #DIV/0!
C12: Current Assets | E12: =SUM(E13:E20) -> 0 | F12: =SUM(F13:F20) -> 0 | G12: =SUM(G13:G20) -> 0 | H12: =SUM(H13:H20) -> 375922 | I12: =SUM(I13:I20) -> 601454 | J12: =SUM(J13:J20) -> 550540.62 | K12: =SUM(K13:K20) -> 604004.73 | L12: =SUM(L13:L20) -> 591724.23 | ... AD12: =SUM(AD13:AD20) -> #DIV/0!
C13: Cash & Short Term Inv. | H13: =5417+112353+104210-102022 -> 119958 | I13: =8864+167574+224351-172303 -> 228486 | J13: ='Cash Flow'!H59 -> 149443.51 | K13: ='Cash Flow'!I59 -> 165864.86 | L13: ='Cash Flow'!J59 -> 120594.37 | M13: ='Cash Flow'!K59 -> 70000 | N13: ='Cash Flow'!L59 -> 70000 | O13: ='Cash Flow'!M59 -> 70000 | P13: ='Cash Flow'!N59 -> 70000 | Q13: ='Cash Flow'!O59 -> 70000 | ... AD13: ='Cash Flow'!AB59 -> #DIV/0!
C14: Aplicações de liquidez imediata e valores em trânsito | J14: ='Working Capital'!I13 -> 0 | K14: ='Working Capital'!J13 -> 0 | L14: ='Working Capital'!K13 -> 0 | M14: ='Working Capital'!L13 -> 0 | N14: ='Working Capital'!M13 -> 0 | O14: ='Working Capital'!N13 -> 0 | P14: ='Working Capital'!O13 -> 0 | Q14: ='Working Capital'!P13 -> 0 | ... AD14: ='Working Capital'!AC13 -> 0
C15: Reserva Técnica | H15: 102022 | I15: 172303 | J15: ='Working Capital'!I14 -> 185298.03 | K15: ='Working Capital'!J14 -> 202410.97 | L15: ='Working Capital'!K14 -> 217651.62 | M15: ='Working Capital'!L14 -> 234399.17 | N15: ='Working Capital'!M14 -> 253008.39 | O15: ='Working Capital'!N14 -> 272986.89 | P15: ='Working Capital'!O14 -> 294738.53 | Q15: ='Working Capital'!P14 -> 318237.24 | ... AD15: ='Working Capital'!AC14 -> 777626.33
C16: Créd. operações pl. de assist. à saúde | H16: =86898 -> 86898 | I16: =106236 -> 106236 | J16: ='Working Capital'!I15 -> 114248.28 | K16: ='Working Capital'!J15 -> 124799.52 | L16: ='Working Capital'!K15 -> 134196.37 | M16: ='Working Capital'!L15 -> 144522.33 | N16: ='Working Capital'!M15 -> 155996.12 | O16: ='Working Capital'!N15 -> 168314.16 | P16: ='Working Capital'!O15 -> 181725.46 | Q16: ='Working Capital'!P15 -> 196213.94 | ... AD16: ='Working Capital'!AC15 -> 479457.18
C17: Despesas de comercialização diferidas | H17: 9839 | I17: 9480 | J17: ='Working Capital'!I16 -> 10194.978 | K17: ='Working Capital'!J16 -> 11136.521 | L17: ='Working Capital'!K16 -> 11975.052 | M17: ='Working Capital'!L16 -> 12896.492 | N17: ='Working Capital'!M16 -> 13920.359 | O17: ='Working Capital'!N16 -> 15019.563 | P17: ='Working Capital'!O16 -> 16216.324 | Q17: ='Working Capital'!P16 -> 17509.208 | ... AD17: ='Working Capital'!AC16 -> 42784.5
C18: Títulos e créditos a receber | H18: 45149 | I18: 52275 | J18: ='Working Capital'!I17 -> 56217.561 | K18: ='Working Capital'!J17 -> 61409.456 | L18: ='Working Capital'!K17 -> 66033.315 | M18: ='Working Capital'!L17 -> 71114.356 | N18: ='Working Capital'!M17 -> 76760.205 | O18: ='Working Capital'!N17 -> 82821.481 | P18: ='Working Capital'!O17 -> 89420.711 | Q18: ='Working Capital'!P17 -> 96549.982 | ... AD18: ='Working Capital'!AC17 -> 235924.02
C19: Outros valores e bens | H19: 12056 | I19: 32674 | J19: ='Working Capital'!I18 -> 35138.261 | K19: ='Working Capital'!J18 -> 38383.406 | L19: ='Working Capital'!K18 -> 41273.506 | M19: ='Working Capital'!L18 -> 44449.363 | N19: ='Working Capital'!M18 -> 47978.248 | O19: ='Working Capital'!N18 -> 51766.792 | P19: ='Working Capital'!O18 -> 55891.579 | Q19: ='Working Capital'!P18 -> 60347.663 | ... AD19: ='Working Capital'!AC18 -> 147462.1
C20: Other Non-Op. Cur. Assets | E20: =SUM(E21:E25) -> 0 | F20: =SUM(F21:F25) -> 0 | G20: =SUM(G21:G25) -> 0 | H20: =SUM(H21:H25) -> 0 | I20: =SUM(I21:I25) -> 0 | J20: =SUM(J21:J25) -> 0 | K20: =SUM(K21:K25) -> 0 | L20: =SUM(L21:L25) -> 0 | ... AD20: =SUM(AD21:AD25) -> 0
C21: Impostos
C22: Partes Relacionadas | J22: =I22 -> 0 | K22: =J22 -> 0 | L22: =K22 -> 0 | M22: =L22 -> 0 | N22: =M22 -> 0 | O22: =N22 -> 0 | P22: =O22 -> 0 | Q22: =P22 -> 0 | ... AD22: =AC22 -> 0
C23: Outros | J23: =I23 -> 0 | K23: =J23 -> 0 | L23: =K23 -> 0 | M23: =L23 -> 0 | N23: =M23 -> 0 | O23: =N23 -> 0 | P23: =O23 -> 0 | Q23: =P23 -> 0 | ... AD23: =AC23 -> 0
C24: item 4
C25: item 5
C27: Long-Term Assets | E27: =SUM(E28:E32) -> 0 | F27: =SUM(F28:F32) -> 0 | G27: =SUM(G28:G32) -> 0 | H27: =SUM(H28:H32) -> 741463 | I27: =SUM(I28:I32) -> 708901 | J27: =SUM(J28:J32) -> 708901 | K27: =SUM(K28:K32) -> 708901 | L27: =SUM(L28:L32) -> 708901 | ... AD27: =SUM(AD28:AD32) -> 708901
C28: Ativo Fiscal Diferido | H28: 6460 | I28: 8368 | J28: =I28 -> 8368 | K28: =J28 -> 8368 | L28: =K28 -> 8368 | M28: =L28 -> 8368 | N28: =M28 -> 8368 | O28: =N28 -> 8368 | P28: =O28 -> 8368 | Q28: =P28 -> 8368 | ... AD28: =AC28 -> 8368
C29: Valores e bens | H29: 45783 | I29: 65262 | J29: =I29 -> 65262 | K29: =J29 -> 65262 | L29: =K29 -> 65262 | M29: =L29 -> 65262 | N29: =M29 -> 65262 | O29: =N29 -> 65262 | P29: =O29 -> 65262 | Q29: =P29 -> 65262 | ... AD29: =AC29 -> 65262
C30: Conta-corrente com cooperados | H30: 689220 | I30: 635271 | J30: =I30 -> 635271 | K30: =J30 -> 635271 | L30: =K30 -> 635271 | M30: =L30 -> 635271 | N30: =M30 -> 635271 | O30: =N30 -> 635271 | P30: =O30 -> 635271 | Q30: =P30 -> 635271 | ... AD30: =AC30 -> 635271
C31: Bens destinados a venda | J31: =I31 -> 0 | K31: =J31 -> 0 | L31: =K31 -> 0 | M31: =L31 -> 0 | N31: =M31 -> 0 | O31: =N31 -> 0 | P31: =O31 -> 0 | Q31: =P31 -> 0 | ... AD31: =AC31 -> 0
C32: Impostos Diferidos | J32: =I32 -> 0 | K32: =J32 -> 0 | L32: =K32 -> 0 | M32: =L32 -> 0 | N32: =M32 -> 0 | O32: =N32 -> 0 | P32: =O32 -> 0 | Q32: =P32 -> 0 | ... AD32: =AC32 -> 0
C34: Permanent | E34: =SUM(E35:E40) -> 0 | F34: =SUM(F35:F40) -> 0 | G34: =SUM(G35:G40) -> 0 | H34: =SUM(H35:H41) -> 297589 | I34: =SUM(I35:I41) -> 407811 | J34: =SUM(J35:J41) -> 518804.4 | K34: =SUM(K35:K41) -> 578804.4 | L34: =SUM(L35:L41) -> 578804.4 | M34: =SUM(M35:M41) -> 578804.4 | N34: =SUM(N35:N41) -> 578804.4 | O34: =SUM(O35:O41) -> 578804.4 | ... AD34: =SUM(AD35:AD41) -> 578804.4
C35: Ágio | J35: =-'Cash Flow'!H38-'Goodwill, Taxes & Div.'!H29 -> 0 | K35: =J35 -> 0 | L35: =K35 -> 0 | M35: =L35 -> 0 | N35: =M35 -> 0 | O35: =N35 -> 0 | P35: =O35 -> 0 | Q35: =P35 -> 0 | R35: =Q35 -> 0 | ... AD35: =AC35 -> 0
C36: Diferido | J36: =I36 -> 0 | K36: =J36 -> 0 | L36: =K36 -> 0 | M36: =L36 -> 0 | N36: =M36 -> 0 | O36: =N36 -> 0 | P36: =O36 -> 0 | Q36: =P36 -> 0 | ... AD36: =AC36 -> 0
C37: PP&E | H37: 197195 | I37: 280066 | J37: ='Fixed Assets & CAPEX'!H10-J38 -> 419066 | K37: ='Fixed Assets & CAPEX'!I10-K38 -> 526929.74 | L37: ='Fixed Assets & CAPEX'!J10-L38 -> 590202.59 | M37: ='Fixed Assets & CAPEX'!K10-M38 -> 662514.42 | N37: ='Fixed Assets & CAPEX'!L10-N38 -> 745156.51 | O37: ='Fixed Assets & CAPEX'!M10-O38 -> 839604.61 | P37: ='Fixed Assets & CAPEX'!N10-P38 -> 947545.3 | Q37: ='Fixed Assets & CAPEX'!O10-Q38 -> 1070906.1 | ... AD37: ='Fixed Assets & CAPEX'!AB10-AD38 -> 2718339
C38: Intangíveis | J38: 0 | K38: =J38 -> 0 | L38: =K38 -> 0 | M38: =L38 -> 0 | N38: =M38 -> 0 | O38: =N38 -> 0 | P38: =O38 -> 0 | Q38: =P38 -> 0 | R38: =Q38 -> 0 | ... AD38: =AC38 -> 0
C39: Amortizacao | I39: 0 | J39: ='Fixed Assets & CAPEX'!H24 -> -28006.6 | K39: ='Fixed Assets & CAPEX'!I24 -> -75870.343 | L39: ='Fixed Assets & CAPEX'!J24 -> -139143.19 | M39: ='Fixed Assets & CAPEX'!K24 -> -211455.02 | N39: ='Fixed Assets & CAPEX'!L24 -> -294097.11 | O39: ='Fixed Assets & CAPEX'!M24 -> -388545.21 | P39: ='Fixed Assets & CAPEX'!N24 -> -496485.9 | Q39: ='Fixed Assets & CAPEX'!O24 -> -619846.68 | ... AD39: ='Fixed Assets & CAPEX'!AB24 -> -2267279.6
C40: Intangible Amortization | H40: 12791 | I40: 31238 | J40: =I40 -> 31238 | K40: =J40 -> 31238 | L40: =K40 -> 31238 | M40: =L40 -> 31238 | N40: =M40 -> 31238 | O40: =N40 -> 31238 | P40: =O40 -> 31238 | Q40: =P40 -> 31238 | ... AD40: =AC40 -> 31238
C41: Investimentos | H41: 87603 | I41: 96507 | J41: =I41 -> 96507 | K41: =J41 -> 96507 | L41: =K41 -> 96507 | M41: =L41 -> 96507 | N41: =M41 -> 96507 | O41: =N41 -> 96507 | P41: =O41 -> 96507 | Q41: =P41 -> 96507 | ... AD41: =AC41 -> 96507
C44: LIABILITIES & EQUITY | E44: =E46+E63+E77 -> 0 | F44: =F46+F63+F77 -> 0 | G44: =G46+G63+G77 -> 0 | H44: =H46+H63+H77+H73 -> 1414974 | I44: =I46+I63+I77+I73+I75 -> 1718166 | J44: =J46+J63+J77+J73+J75 -> 1778246 | K44: =K46+K63+K77+K73+K75 -> 1891710.1 | L44: =L46+L63+L77+L73+L75 -> 1879429.6 | M44: =M46+M63+M77+M73+M75 -> 1865087.1 | N44: =N46+N63+N77+N73+N75 -> 1905368.7 | O44: =O46+O63+O77+O73+O75 -> 1948614.3 | P44: =P46+P63+P77+P73+P75 -> 1995698 | ... AD44: =AD46+AD63+AD77+AD73+AD75 -> #DIV/0!
C46: Current Liabilities | E46: =SUM(E47:E61) -> 0 | F46: =SUM(F47:F61) -> 0 | G46: =SUM(G47:G61) -> 0 | H46: =SUM(H47:H56) -> 405908 | I46: =SUM(I47:I56) -> 506495 | J46: =SUM(J47:J56) -> 523744.12 | K46: =SUM(K47:K56) -> 591551.33 | L46: =SUM(L47:L56) -> 672637.27 | M46: =SUM(M47:M56) -> 728781.51 | N46: =SUM(N47:N56) -> 867606.23 | O46: =SUM(O47:O56) -> 1011976.5 | ... AD46: =SUM(AD47:AD56) -> #DIV/0!
C47: Débitos de operações de assit. à saúde | H47: 4653 | I47: 4911 | J47: ='Working Capital'!I21 -> 5281.3858 | K47: ='Working Capital'!J21 -> 5769.1408 | L47: ='Working Capital'!K21 -> 6203.5315 | M47: ='Working Capital'!L21 -> 6680.8723 | N47: ='Working Capital'!M21 -> 7211.2743 | O47: ='Working Capital'!N21 -> 7780.7038 | P47: ='Working Capital'!O21 -> 8400.6717 | Q47: ='Working Capital'!P21 -> 9070.4344 | ... AD47: ='Working Capital'!AC21 -> 22163.996
C48: Débitos de oper. assist. à saúde não rel. c/plano de saúde da op. | H48: 29653 | I48: 39339 | J48: ='Working Capital'!I22 -> 42305.933 | K48: ='Working Capital'!J22 -> 46213.038 | L48: ='Working Capital'!K22 -> 49692.675 | M48: ='Working Capital'!L22 -> 53516.359 | N48: ='Working Capital'!M22 -> 57765.083 | O48: ='Working Capital'!N22 -> 62326.432 | P48: ='Working Capital'!O22 -> 67292.613 | Q48: ='Working Capital'!P22 -> 72657.67 | ... AD48: ='Working Capital'!AC22 -> 177542.13
C49: Taxes | H49: =25896 -> 25896 | I49: =32706 -> 32706 | J49: =+'Working Capital'!I23 -> 35172.674 | K49: =+'Working Capital'!J23 -> 38420.998 | L49: =+'Working Capital'!K23 -> 41313.928 | M49: =+'Working Capital'!L23 -> 44492.896 | N49: =+'Working Capital'!M23 -> 48025.237 | O49: =+'Working Capital'!N23 -> 51817.491 | P49: =+'Working Capital'!O23 -> 55946.318 | Q49: =+'Working Capital'!P23 -> 60406.766 | ... V49: =+'Working Capital'!U23 -> 89604.054 | W49: =V49 -> 89604.054 | X49: =W49 -> 89604.054 | Y49: =X49 -> 89604.054 | Z49: =Y49 -> 89604.054 | AA49: =Z49 -> 89604.054 | AB49: =AA49 -> 89604.054 | AC49: =AB49 -> 89604.054 | AD49: =AC49 -> 89604.054
C50: Bank Short Term | H50: 75294 | I50: 49121 | J50: ='ST Inv. & Debt'!H14 -> 44928 | K50: ='ST Inv. & Debt'!I14 -> 84248.825 | L50: ='ST Inv. & Debt'!J14 -> 137426.11 | M50: ='ST Inv. & Debt'!K14 -> 120481.63 | N50: ='ST Inv. & Debt'!L14 -> 124575.83 | O50: ='ST Inv. & Debt'!M14 -> 126614.73 | P50: ='ST Inv. & Debt'!N14 -> 38897.913 | Q50: ='ST Inv. & Debt'!O14 -> 44454.758 | ... AD50: ='ST Inv. & Debt'!AB14 -> 0
C51: Tributos e contribuições a recolher - parcelamento | H51: 6767 | I51: 24196 | J51: ='Tributos a Recolher'!A7 -> 23402 | K51: ='Tributos a Recolher'!B7 -> 22606 | L51: ='Tributos a Recolher'!C7 -> 24436 | M51: ='Tributos a Recolher'!D7 -> 16987 | N51: ='Tributos a Recolher'!E7 -> 16987 | O51: ='Tributos a Recolher'!F7 -> 16987 | P51: ='Tributos a Recolher'!G7 -> 16987 | Q51: ='Tributos a Recolher'!H7 -> 16987 | R51: ='Tributos a Recolher'!I7 -> 16987
C52: Provisões técnicas de operações de assist. à saúde | H52: 171826 | I52: 217876 | J52: ='Working Capital'!I24 -> 234308.13 | K52: ='Working Capital'!J24 -> 255947.33 | L52: ='Working Capital'!K24 -> 275219.03 | M52: ='Working Capital'!L24 -> 296396.2 | N52: ='Working Capital'!M24 -> 319927.43 | O52: ='Working Capital'!N24 -> 345190.11 | P52: ='Working Capital'!O24 -> 372694.92 | Q52: ='Working Capital'!P24 -> 402408.87 | ... AD52: ='Working Capital'!AC24 -> 983303.34
C53: Dividends Payable | J53: ='Goodwill, Taxes & Div.'!H55 -> 0 | K53: ='Goodwill, Taxes & Div.'!I55 -> 0 | L53: ='Goodwill, Taxes & Div.'!J55 -> 0 | M53: ='Goodwill, Taxes & Div.'!K55 -> 0 | N53: ='Goodwill, Taxes & Div.'!L55 -> 0 | O53: ='Goodwill, Taxes & Div.'!M55 -> 0 | P53: ='Goodwill, Taxes & Div.'!N55 -> 0 | Q53: ='Goodwill, Taxes & Div.'!O55 -> 0 | ... AD53: ='Goodwill, Taxes & Div.'!AB55 -> #DIV/0!
C54: Current Portion of LT Debt
C55: Revolving Leverage | J55: ='ST Inv. & Debt'!H51 -> 0 | K55: ='ST Inv. & Debt'!I51 -> 0 | L55: ='ST Inv. & Debt'!J51 -> 0 | M55: ='ST Inv. & Debt'!K51 -> 51880.553 | N55: ='ST Inv. & Debt'!L51 -> 154768.37 | O55: ='ST Inv. & Debt'!M51 -> 262913.99 | P55: ='ST Inv. & Debt'!N51 -> 372358.18 | Q55: ='ST Inv. & Debt'!O51 -> 325981.38 | ... AD55: ='ST Inv. & Debt'!AB51 -> #DIV/0!
C56: Other Non-Op. Cur. Liabilities | H56: =SUM(H57:H61) -> 91819 | I56: =SUM(I57:I61) -> 138346 | J56: =SUM(J57:J61) -> 138346 | K56: =SUM(K57:K61) -> 138346 | L56: =SUM(L57:L61) -> 138346 | M56: =SUM(M57:M61) -> 138346 | N56: =SUM(N57:N61) -> 138346 | O56: =SUM(O57:O61) -> 138346 | ... AD56: =SUM(AD57:AD61) -> 138346
C57: Provisões | H57: 9189 | I57: 16143 | J57: =I57 -> 16143 | K57: =J57 -> 16143 | L57: =K57 -> 16143 | M57: =L57 -> 16143 | N57: =M57 -> 16143 | O57: =N57 -> 16143 | P57: =O57 -> 16143 | Q57: =P57 -> 16143 | ... AD57: =AC57 -> 16143
C58: Débitos com aquisição de carteira | H58: 11894 | I58: 12043 | J58: =I58 -> 12043 | K58: =J58 -> 12043 | L58: =K58 -> 12043 | M58: =L58 -> 12043 | N58: =M58 -> 12043 | O58: =N58 -> 12043 | P58: =O58 -> 12043 | Q58: =P58 -> 12043 | ... AD58: =AC58 -> 12043
C59: Débitos diversos | H59: 29948 | I59: 62665 | J59: =I59 -> 62665 | K59: =J59 -> 62665 | L59: =K59 -> 62665 | M59: =L59 -> 62665 | N59: =M59 -> 62665 | O59: =N59 -> 62665 | P59: =O59 -> 62665 | Q59: =P59 -> 62665 | ... AD59: =AC59 -> 62665
C60: Recebimento antecipado | H60: 40788 | I60: 47495 | J60: =I60 -> 47495 | K60: =J60 -> 47495 | L60: =K60 -> 47495 | M60: =L60 -> 47495 | N60: =M60 -> 47495 | O60: =N60 -> 47495 | P60: =O60 -> 47495 | Q60: =P60 -> 47495 | ... AD60: =AC60 -> 47495
C61: Item 5
C63: Long-Term Liabilities | E63: =SUM(E64:E66) -> 0 | F63: =SUM(F64:F66) -> 0 | G63: =SUM(G64:G66) -> 0 | H63: =SUM(H64:H66) -> 845134 | I63: =SUM(I64:I66) -> 1004560 | J63: =SUM(J64:J66) -> 1027420 | K63: =SUM(K64:K66) -> 1049688.4 | L63: =SUM(L64:L66) -> 916299.06 | ... AD63: =SUM(AD64:AD66) -> 494934
C64: LT Bank Debt | H64: 135784 | I64: 344986 | J64: ='ST Inv. & Debt'!H15 -> 391248 | K64: ='ST Inv. & Debt'!I15 -> 436122.39 | L64: ='ST Inv. & Debt'!J15 -> 327169.06 | M64: ='ST Inv. & Debt'!K15 -> 239227.76 | N64: ='ST Inv. & Debt'!L15 -> 151840.86 | O64: ='ST Inv. & Debt'!M15 -> 67727.774 | P64: ='ST Inv. & Debt'!N15 -> 77403.17 | Q64: ='ST Inv. & Debt'!O15 -> 88460.766 | ... AD64: ='ST Inv. & Debt'!AB15 -> 41700
C65: Empréstimos de coligadas | J65: =+'Working Capital'!I26 -> 0 | K65: =+'Working Capital'!J26 -> 0 | L65: =+'Working Capital'!K26 -> 0 | M65: =+'Working Capital'!L26 -> 0 | N65: =+'Working Capital'!M26 -> 0 | O65: =+'Working Capital'!N26 -> 0 | P65: =+'Working Capital'!O26 -> 0 | Q65: =+'Working Capital'!P26 -> 0 | ... AD65: =+'Working Capital'!AC26 -> 0
C66: Other Long-Term Liabilities | E66: =SUM(E67:E71) -> 0 | F66: =SUM(F67:F71) -> 0 | G66: =SUM(G67:G71) -> 0 | H66: =SUM(H67:H71) -> 709350 | I66: =SUM(I67:I71) -> 659574 | J66: =SUM(J67:J71) -> 636172 | K66: =SUM(K67:K71) -> 613566 | L66: =SUM(L67:L71) -> 589130 | ... AD66: =SUM(AD67:AD71) -> 453234
C67: Tributos e contribuições a recolher | H67: =664239 -> 664239 | I67: =417772 -> 417772 | J67: =I67 -> 417772 | K67: =J67 -> 417772 | L67: =K67 -> 417772 | M67: =L67 -> 417772 | N67: =M67 -> 417772 | O67: =N67 -> 417772 | P67: =O67 -> 417772 | Q67: =P67 -> 417772 | ... AD67: =AC67 -> 417772
C68: Provisão | H68: 8632 | I68: 22724 | J68: =I68 -> 22724 | K68: =J68 -> 22724 | L68: =K68 -> 22724 | M68: =L68 -> 22724 | N68: =M68 -> 22724 | O68: =N68 -> 22724 | P68: =O68 -> 22724 | Q68: =P68 -> 22724 | ... AD68: =AC68 -> 22724
C69: Tributos e contribuições a recolher - parcelamento | H69: 25159 | I69: 219078 | J69: ='Tributos a Recolher'!A10 -> 195676 | K69: ='Tributos a Recolher'!B10 -> 173070 | L69: ='Tributos a Recolher'!C10 -> 148634 | M69: ='Tributos a Recolher'!D10 -> 131647 | N69: ='Tributos a Recolher'!E10 -> 114660 | O69: ='Tributos a Recolher'!F10 -> 97673 | P69: ='Tributos a Recolher'!G10 -> 80686 | Q69: ='Tributos a Recolher'!H10 -> 63699 | ... T69: ='Tributos a Recolher'!K10 -> 12738 | U69: =T69 -> 12738 | V69: =U69 -> 12738 | W69: =V69 -> 12738 | X69: =W69 -> 12738 | Y69: =X69 -> 12738 | Z69: =Y69 -> 12738 | AA69: =Z69 -> 12738 | AB69: =AA69 -> 12738 | ... AD69: =AC69 -> 12738
C70: Débitos com Aquisição de Carteira | H70: 11015 | J70: =I70 -> 0 | K70: =J70 -> 0 | L70: =K70 -> 0 | M70: =L70 -> 0 | N70: =M70 -> 0 | O70: =N70 -> 0 | P70: =O70 -> 0 | Q70: =P70 -> 0 | ... AD70: =AC70 -> 0
C71: Débitos diversos | H71: 305 | J71: ='Working Capital'!I25 -> 0 | K71: ='Working Capital'!J25 -> 0 | L71: ='Working Capital'!K25 -> 0 | M71: ='Working Capital'!L25 -> 0 | N71: ='Working Capital'!M25 -> 0 | O71: ='Working Capital'!N25 -> 0 | P71: ='Working Capital'!O25 -> 0 | Q71: ='Working Capital'!P25 -> 0 | ... AD71: ='Working Capital'!AC25 -> 0
C73: Minority Interest | J73: =I73 -> 0 | K73: =J73 -> 0 | L73: =K73 -> 0 | M73: =L73 -> 0 | N73: =M73 -> 0 | O73: =N73 -> 0 | P73: =O73 -> 0 | Q73: =P73 -> 0 | ... AD73: =AC73 -> 0
C75: Antecipated Results | J75: =I75 -> 0 | K75: =J75 -> 0 | L75: =K75 -> 0 | M75: =L75 -> 0 | N75: =M75 -> 0 | O75: =N75 -> 0 | P75: =O75 -> 0 | Q75: =P75 -> 0 | ... AD75: =AC75 -> 0
C77: Shareholder's Equity | E77: =SUM(E78:E80) -> 0 | F77: =SUM(F78:F80) -> 0 | G77: =SUM(G78:G80) -> 0 | H77: =SUM(H78:H80) -> 163932 | I77: =SUM(I78:I80) -> 207111 | J77: =SUM(J78:J80) -> 227081.9 | K77: =SUM(K78:K80) -> 250470.42 | L77: =SUM(L78:L80) -> 290493.3 | ... AD77: =SUM(AD78:AD80) -> #VALUE!
C78: Capital | H78: 100818 | I78: 108963 | J78: =I78 -> 108963 | K78: =J78+'Goodwill, Taxes & Div.'!I53 -> 108963 | L78: =K78+'Goodwill, Taxes & Div.'!J53 -> 108963 | M78: =L78+'Goodwill, Taxes & Div.'!K53 -> 108963 | N78: =M78+'Goodwill, Taxes & Div.'!L53 -> 108963 | O78: =N78+'Goodwill, Taxes & Div.'!M53 -> 108963 | P78: =O78+'Goodwill, Taxes & Div.'!N53 -> 108963 | Q78: =P78+'Goodwill, Taxes & Div.'!O53 -> 108963 | R78: =Q78+'Goodwill, Taxes & Div.'!P53 -> 108963 | ... AD78: =AC78+'Goodwill, Taxes & Div.'!AB53 -> 108963
C79: Reserves | H79: 37118 | I79: 61606 | J79: =I79 -> 61606 | K79: =J79 -> 61606 | L79: =K79 -> 61606 | M79: =L79 -> 61606 | N79: =M79 -> 61606 | O79: =N79 -> 61606 | P79: =O79 -> 61606 | Q79: =P79 -> 61606 | ... AD79: =AC79 -> 61606
C80: Retained earnings | H80: 25996 | I80: 36542 | J80: =I80+'Income Statement'!J81-J53+'Cash Flow'!H46 -> 56512.898 | K80: =J80+'Income Statement'!K81-K53+'Cash Flow'!I46 -> 79901.416 | L80: =K80+'Income Statement'!L81-L53+'Cash Flow'!J46 -> 119924.3 | M80: =L80+'Income Statement'!M81-M53+'Cash Flow'!K46 -> 154365.85 | N80: =M80+'Income Statement'!N81-N53+'Cash Flow'!L46 -> 160196.64 | O80: =N80+'Income Statement'!O81-O53+'Cash Flow'!M46 -> 160172.05 | P80: =O80+'Income Statement'!P81-P53+'Cash Flow'!N46 -> 155620.23 | Q80: =P80+'Income Statement'!Q81-Q53+'Cash Flow'!O46 -> 213025.79 | ... AD80: =AC80+'Income Statement'!AD81-AD53+'Cash Flow'!AB46 -> #VALUE!
C83: Mismatch | E83: =E10-E44 -> 0 | F83: =F10-F44 -> 0 | G83: =G10-G44 -> 0 | H83: =H10-H44 -> 0 | I83: =I10-I44 -> 0 | J83: =J10-J44 -> 0 | K83: =K10-K44 -> 0 | L83: =L10-L44 -> 0 | ... AD83: =AD10-AD44 -> #DIV/0!
C89: Net Debt / LTM EBITDA

Sheet Working Capital
A2: 1 | B2: ='Revenues, COGS & SG&A'!B2 -> Base Case | C2: Scenario
A3: 2 | B3: ='Revenues, COGS & SG&A'!B3 -> Client Case | C3: =Output!G2 -> 1
A4: 3 | B4: ='Revenues, COGS & SG&A'!B4 -> Stress Case | I4: ='Balance Sheet'!J83 -> 0 | J4: ='Balance Sheet'!K83 -> 0 | K4: ='Balance Sheet'!L83 -> 0 | L4: ='Balance Sheet'!M83 -> 0 | M4: ='Balance Sheet'!N83 -> 0 | N4: ='Balance Sheet'!O83 -> 0 | O4: ='Balance Sheet'!P83 -> 0 | P4: ='Balance Sheet'!Q83 -> 0 | Q4: ='Balance Sheet'!R83 -> 0
B7: WORKING CAPITAL | D7: ='Revenues, COGS & SG&A'!D7 -> 39447 | E7: ='Revenues, COGS & SG&A'!E7 -> 39813 | F7: ='Revenues, COGS & SG&A'!F7 -> 40178 | G7: ='Revenues, COGS & SG&A'!G7 -> 40543 | H7: ='Revenues, COGS & SG&A'!H7 -> 40908 | I7: ='Revenues, COGS & SG&A'!I7 -> 41274 | J7: ='Revenues, COGS & SG&A'!J7 -> 41639 | K7: ='Revenues, COGS & SG&A'!K7 -> 42004 | ... AC7: ='Revenues, COGS & SG&A'!AC7 -> 48579
B8: R$ thousand
B10: BALANCE SHEET ACCOUNTS
B12: Assets
B13: ='Balance Sheet'!C14 -> Aplicações de liquidez imediata e valores em trânsito | D13: ='Balance Sheet'!E14 -> 0 | E13: ='Balance Sheet'!F14 -> 0 | F13: ='Balance Sheet'!G14 -> 0 | G13: ='Balance Sheet'!H14 -> 0 | H13: ='Balance Sheet'!I14 -> 0 | I13: =I31/360*I37 -> 0 | J13: =J31/360*J37 -> 0 | K13: =K31/360*K37 -> 0 | L13: =L31/360*L37 -> 0 | M13: =M31/360*M37 -> 0 | N13: =N31/360*N37 -> 0 | O13: =O31/360*O37 -> 0 | P13: =P31/360*P37 -> 0 | ... AC13: =AC31/360*AC37 -> 0
B14: ='Balance Sheet'!C15 -> Reserva Técnica | D14: ='Balance Sheet'!E15 -> 0 | E14: ='Balance Sheet'!F15 -> 0 | F14: ='Balance Sheet'!G15 -> 0 | G14: ='Balance Sheet'!H15 -> 102022 | H14: ='Balance Sheet'!I15 -> 172303 | I14: =I38/360*I31 -> 185298.03 | J14: =J38/360*J31 -> 202410.97 | K14: =K38/360*K31 -> 217651.62 | L14: =L38/360*L31 -> 234399.17 | M14: =M38/360*M31 -> 253008.39 | N14: =N38/360*N31 -> 272986.89 | O14: =O38/360*O31 -> 294738.53 | P14: =P38/360*P31 -> 318237.24 | ... AC14: =AC38/360*AC31 -> 777626.33
B15: ='Balance Sheet'!C16 -> Créd. operações pl. de assist. à saúde | D15: ='Balance Sheet'!E16 -> 0 | E15: ='Balance Sheet'!F16 -> 0 | F15: ='Balance Sheet'!G16 -> 0 | G15: ='Balance Sheet'!H16 -> 86898 | H15: ='Balance Sheet'!I16 -> 106236 | I15: =I39/360*I31 -> 114248.28 | J15: =J39/360*J31 -> 124799.52 | K15: =K39/360*K31 -> 134196.37 | L15: =L39/360*L31 -> 144522.33 | M15: =M39/360*M31 -> 155996.12 | N15: =N39/360*N31 -> 168314.16 | O15: =O39/360*O31 -> 181725.46 | P15: =P39/360*P31 -> 196213.94 | ... AC15: =AC39/360*AC31 -> 479457.18
B16: ='Balance Sheet'!C17 -> Despesas de comercialização diferidas | D16: ='Balance Sheet'!E22 -> 0 | E16: ='Balance Sheet'!F21 -> 0 | F16: ='Balance Sheet'!G21 -> 0 | G16: ='Balance Sheet'!H17 -> 9839 | H16: ='Balance Sheet'!I17 -> 9480 | I16: =I40/360*I31 -> 10194.978 | J16: =J40/360*J31 -> 11136.521 | K16: =K40/360*K31 -> 11975.052 | L16: =L40/360*L31 -> 12896.492 | M16: =M40/360*M31 -> 13920.359 | N16: =N40/360*N31 -> 15019.563 | O16: =O40/360*O31 -> 16216.324 | P16: =P40/360*P31 -> 17509.208 | ... AC16: =AC40/360*AC31 -> 42784.5
B17: ='Balance Sheet'!C18 -> Títulos e créditos a receber | D17: 0 | E17: 0 | F17: 0 | G17: ='Balance Sheet'!H18 -> 45149 | H17: ='Balance Sheet'!I18 -> 52275 | I17: =I41/360*I31 -> 56217.561 | J17: =J41/360*J31 -> 61409.456 | K17: =K41/360*K31 -> 66033.315 | L17: =L41/360*L31 -> 71114.356 | M17: =M41/360*M31 -> 76760.205 | N17: =N41/360*N31 -> 82821.481 | O17: =O41/360*O31 -> 89420.711 | P17: =P41/360*P31 -> 96549.982 | ... AC17: =AC41/360*AC31 -> 235924.02
B18: ='Balance Sheet'!C19 -> Outros valores e bens | G18: ='Balance Sheet'!H19 -> 12056 | H18: ='Balance Sheet'!I19 -> 32674 | I18: =I42/360*I31 -> 35138.261 | J18: =J42/360*J31 -> 38383.406 | K18: =K42/360*K31 -> 41273.506 | L18: =L42/360*L31 -> 44449.363 | M18: =M42/360*M31 -> 47978.248 | N18: =N42/360*N31 -> 51766.792 | O18: =O42/360*O31 -> 55891.579 | P18: =P42/360*P31 -> 60347.663 | ... AC18: =AC42/360*AC31 -> 147462.1
B20: Liabilities
B21: ='Balance Sheet'!C47 -> Débitos de operações de assit. à saúde | D21: ='Balance Sheet'!E47 -> 0 | E21: ='Balance Sheet'!F47 -> 0 | F21: ='Balance Sheet'!G47 -> 0 | G21: ='Balance Sheet'!H47 -> 4653 | H21: ='Balance Sheet'!I47 -> 4911 | I21: =I46/360*I31 -> 5281.3858 | J21: =J46/360*J31 -> 5769.1408 | K21: =K46/360*K31 -> 6203.5315 | L21: =L46/360*L31 -> 6680.8723 | M21: =M46/360*M31 -> 7211.2743 | N21: =N46/360*N31 -> 7780.7038 | O21: =O46/360*O31 -> 8400.6717 | P21: =P46/360*P31 -> 9070.4344 | ... AC21: =AC46/360*AC31 -> 22163.996
B22: ='Balance Sheet'!C48 -> Débitos de oper. assist. à saúde não rel. c/plano de saúde da op. | D22: ='Balance Sheet'!E48 -> 0 | E22: ='Balance Sheet'!F48 -> 0 | F22: ='Balance Sheet'!G48 -> 0 | G22: ='Balance Sheet'!H48 -> 29653 | H22: ='Balance Sheet'!I48 -> 39339 | I22: =I47/360*I31 -> 42305.933 | J22: =J47/360*J31 -> 46213.038 | K22: =K47/360*K31 -> 49692.675 | L22: =L47/360*L31 -> 53516.359 | M22: =M47/360*M31 -> 57765.083 | N22: =N47/360*N31 -> 62326.432 | O22: =O47/360*O31 -> 67292.613 | P22: =P47/360*P31 -> 72657.67 | ... AC22: =AC47/360*AC31 -> 177542.13
B23: ='Balance Sheet'!C49 -> Taxes | D23: ='Balance Sheet'!E49 -> 0 | E23: ='Balance Sheet'!F49 -> 0 | F23: ='Balance Sheet'!G49 -> 0 | G23: ='Balance Sheet'!H49 -> 25896 | H23: ='Balance Sheet'!I49 -> 32706 | I23: =I48/360*I31 -> 35172.674 | J23: =J48/360*J31 -> 38420.998 | K23: =K48/360*K31 -> 41313.928 | L23: =L48/360*L31 -> 44492.896 | M23: =M48/360*M31 -> 48025.237 | N23: =N48/360*N31 -> 51817.491 | O23: =O48/360*O31 -> 55946.318 | P23: =P48/360*P31 -> 60406.766 | ... AC23: =AC48/360*AC31 -> 147606.52
B24: ='Balance Sheet'!C52 -> Provisões técnicas de operações de assist. à saúde | D24: ='Balance Sheet'!E51 -> 0 | E24: ='Balance Sheet'!F51 -> 0 | F24: ='Balance Sheet'!G51 -> 0 | G24: ='Balance Sheet'!H52 -> 171826 | H24: ='Balance Sheet'!I52 -> 217876 | I24: =I49/360*I31 -> 234308.13 | J24: =J49/360*J31 -> 255947.33 | K24: =K49/360*K31 -> 275219.03 | L24: =L49/360*L31 -> 296396.2 | M24: =M49/360*M31 -> 319927.43 | N24: =N49/360*N31 -> 345190.11 | O24: =O49/360*O31 -> 372694.92 | P24: =P49/360*P31 -> 402408.87 | ... AC24: =AC49/360*AC31 -> 983303.34
B25: =+'Balance Sheet'!C71 -> Débitos diversos | D25: ='Balance Sheet'!E65 -> 0 | E25: ='Balance Sheet'!F65 -> 0 | F25: ='Balance Sheet'!G65 -> 0 | G25: ='Balance Sheet'!H71 -> 305 | H25: ='Balance Sheet'!I71 -> 0 | I25: =I50/360*I31 -> 0 | J25: =J50/360*J31 -> 0 | K25: =K50/360*K31 -> 0 | L25: =L50/360*L31 -> 0 | M25: =M50/360*M31 -> 0 | N25: =N50/360*N31 -> 0 | O25: =O50/360*O31 -> 0 | P25: =P50/360*P31 -> 0 | ... AC25: =AC50/360*AC31 -> 0
B26: =+'Balance Sheet'!C65 -> Empréstimos de coligadas | G26: =+'Balance Sheet'!H65 -> 0 | H26: =+'Balance Sheet'!I65 -> 0 | I26: =I51/360*I31 -> 0 | J26: =J51/360*J31 -> 0 | K26: =K51/360*K31 -> 0 | L26: =L51/360*L31 -> 0 | M26: =M51/360*M31 -> 0 | N26: =N51/360*N31 -> 0 | O26: =O51/360*O31 -> 0 | P26: =P51/360*P31 -> 0 | ... AC26: =AC51/360*AC31 -> 0
B27: =+'Balance Sheet'!C56 -> Other Non-Op. Cur. Liabilities
B29: INCOME STATEMENT ACCOUNTS
B31: Net Revenues | D31: ='Revenues, COGS & SG&A'!D34 -> 0 | E31: ='Revenues, COGS & SG&A'!E34 -> 0 | F31: ='Revenues, COGS & SG&A'!F34 -> 0 | G31: ='Revenues, COGS & SG&A'!G34 -> 2434971 | H31: ='Revenues, COGS & SG&A'!H34 -> 2853511 | I31: ='Revenues, COGS & SG&A'!I34 -> 3068721.7 | J31: ='Revenues, COGS & SG&A'!J34 -> 3352129.3 | K31: ='Revenues, COGS & SG&A'!K34 -> 3604529.7 | ... AC31: ='Revenues, COGS & SG&A'!AC34 -> 12878274
B32: COGS | D32: ='Revenues, COGS & SG&A'!D38 -> 0 | E32: ='Revenues, COGS & SG&A'!E38 -> 0 | F32: ='Revenues, COGS & SG&A'!F38 -> 0 | G32: ='Revenues, COGS & SG&A'!G38 -> 1897818 | H32: ='Revenues, COGS & SG&A'!H38 -> 2250776 | I32: ='Revenues, COGS & SG&A'!I38 -> 2425322.3 | J32: ='Revenues, COGS & SG&A'!J38 -> 2652824.4 | K32: ='Revenues, COGS & SG&A'!K38 -> 2825774.9 | ... AC32: ='Revenues, COGS & SG&A'!AC38 -> 10196585
B33: SG&A | D33: ='Revenues, COGS & SG&A'!D48 -> 0 | E33: ='Revenues, COGS & SG&A'!E48 -> 0 | F33: ='Revenues, COGS & SG&A'!F48 -> 0 | G33: ='Revenues, COGS & SG&A'!G48 -> 492128 | H33: ='Revenues, COGS & SG&A'!H48 -> 535439 | I33: ='Revenues, COGS & SG&A'!I48 -> 575821.61 | J33: ='Revenues, COGS & SG&A'!J48 -> 629000.81 | K33: ='Revenues, COGS & SG&A'!K48 -> 676361.78 | ... AC33: ='Revenues, COGS & SG&A'!AC48 -> 2290070.2
B35: AVERAGE TENOR - ASSETS
B37: =B13 -> Aplicações de liquidez imediata e valores em trânsito | D37: =IF(D31>0,D13/D31*360,) -> 0 | E37: =IF(E31>0,E13/E31*360,) -> 0 | F37: =IF(F31>0,F13/F31*360,) -> 0 | G37: =IF(G31>0,G13/G31*360,) -> 0 | H37: =IF(H31>0,H13/H31*360,) -> 0 | I37: =CHOOSE($C$3,I56,I71,I86) -> 0 | J37: =CHOOSE($C$3,J56,J71,J86) -> 0 | K37: =CHOOSE($C$3,K56,K71,K86) -> 0 | L37: =CHOOSE($C$3,L56,L71,L86) -> 0 | M37: =CHOOSE($C$3,M56,M71,M86) -> 0 | N37: =CHOOSE($C$3,N56,N71,N86) -> 0 | O37: =CHOOSE($C$3,O56,O71,O86) -> 0 | P37: =CHOOSE($C$3,P56,P71,P86) -> 0 | ... AC37: =CHOOSE($C$3,AC56,AC71,AC86) -> 0
B38: =B14 -> Reserva Técnica | D38: =IF(D32>0,D14/D32*360,) -> 0 | E38: =IF(E32>0,E14/E32*360,) -> 0 | F38: =IF(F32>0,F14/F32*360,) -> 0 | G38: =IF($G$31>0,G14/$G$31*360,) -> 15.083514 | H38: =IF(H31>0,H14/H31*360,) -> 21.73781 | I38: =CHOOSE($C$3,I57,I72,I87) -> 21.73781 | J38: =CHOOSE($C$3,J57,J72,J87) -> 21.73781 | K38: =CHOOSE($C$3,K57,K72,K87) -> 21.73781 | L38: =CHOOSE($C$3,L57,L72,L87) -> 21.73781 | M38: =CHOOSE($C$3,M57,M72,M87) -> 21.73781 | N38: =CHOOSE($C$3,N57,N72,N87) -> 21.73781 | O38: =CHOOSE($C$3,O57,O72,O87) -> 21.73781 | P38: =CHOOSE($C$3,P57,P72,P87) -> 21.73781 | ... AC38: =CHOOSE($C$3,AC57,AC72,AC87) -> 21.73781
B39: =B15 -> Créd. operações pl. de assist. à saúde | D39: =IF(D32>0,D15/D32*360,) -> 0 | E39: =IF(E32>0,E15/E32*360,) -> 0 | F39: =IF(F32>0,F15/F32*360,) -> 0 | G39: =IF(G31>0,G15/G31*360,) -> 12.847496 | H39: =IF(H31>0,H15/H31*360,) -> 13.402773 | I39: =CHOOSE($C$3,I58,I73,I88) -> 13.402773 | J39: =CHOOSE($C$3,J58,J73,J88) -> 13.402773 | K39: =CHOOSE($C$3,K58,K73,K88) -> 13.402773 | L39: =CHOOSE($C$3,L58,L73,L88) -> 13.402773 | M39: =CHOOSE($C$3,M58,M73,M88) -> 13.402773 | N39: =CHOOSE($C$3,N58,N73,N88) -> 13.402773 | O39: =CHOOSE($C$3,O58,O73,O88) -> 13.402773 | P39: =CHOOSE($C$3,P58,P73,P88) -> 13.402773 | ... AC39: =CHOOSE($C$3,AC58,AC73,AC88) -> 13.402773
B40: =B16 -> Despesas de comercialização diferidas | D40: =IF(D31>0,D16/D31*360,) -> 0 | E40: =IF(E31>0,E16/E31*360,) -> 0 | F40: =IF(F31>0,F16/F31*360,) -> 0 | G40: =IF(G31>0,G16/G31*360,) -> 1.4546539 | H40: =IF(H31>0,H16/H31*360,) -> 1.1960003 | I40: =CHOOSE($C$3,I59,I74,I89) -> 1.1960003 | J40: =CHOOSE($C$3,J59,J74,J89) -> 1.1960003 | K40: =CHOOSE($C$3,K59,K74,K89) -> 1.1960003 | L40: =CHOOSE($C$3,L59,L74,L89) -> 1.1960003 | M40: =CHOOSE($C$3,M59,M74,M89) -> 1.1960003 | N40: =CHOOSE($C$3,N59,N74,N89) -> 1.1960003 | O40: =CHOOSE($C$3,O59,O74,O89) -> 1.1960003 | P40: =CHOOSE($C$3,P59,P74,P89) -> 1.1960003 | ... AC40: =CHOOSE($C$3,AC59,AC74,AC89) -> 1.1960003
B41: =B17 -> Títulos e créditos a receber | G41: =IF(G31>0,G17/G31*360,) -> 6.6750857 | H41: =IF(H31>0,H17/H31*360,) -> 6.5950333 | I41: =CHOOSE($C$3,I60,I75,I90) -> 6.5950333 | J41: =CHOOSE($C$3,J60,J75,J90) -> 6.5950333 | K41: =CHOOSE($C$3,K60,K75,K90) -> 6.5950333 | L41: =CHOOSE($C$3,L60,L75,L90) -> 6.5950333 | M41: =CHOOSE($C$3,M60,M75,M90) -> 6.5950333 | N41: =CHOOSE($C$3,N60,N75,N90) -> 6.5950333 | O41: =CHOOSE($C$3,O60,O75,O90) -> 6.5950333 | P41: =CHOOSE($C$3,P60,P75,P90) -> 6.5950333 | ... AC41: =CHOOSE($C$3,AC60,AC75,AC90) -> 6.5950333
B42: =B18 -> Outros valores e bens | G42: =IF(G31>0,G18/G31*360,) -> 1.7824278 | H42: =IF(H31>0,H18/H31*360,) -> 4.1221639 | I42: =CHOOSE($C$3,I61,I76,I91) -> 4.1221639 | J42: =CHOOSE($C$3,J61,J76,J91) -> 4.1221639 | K42: =CHOOSE($C$3,K61,K76,K91) -> 4.1221639 | L42: =CHOOSE($C$3,L61,L76,L91) -> 4.1221639 | M42: =CHOOSE($C$3,M61,M76,M91) -> 4.1221639 | N42: =CHOOSE($C$3,N61,N76,N91) -> 4.1221639 | O42: =CHOOSE($C$3,O61,O76,O91) -> 4.1221639 | P42: =CHOOSE($C$3,P61,P76,P91) -> 4.1221639 | ... AC42: =CHOOSE($C$3,AC61,AC76,AC91) -> 4.1221639
B44: AVERAGE TENOR - LIABILITIES
B46: =B21 -> Débitos de operações de assit. à saúde | D46: =IF(D32>0,D21/D32*360,) -> 0 | E46: =IF(E32>0,E21/E32*360,) -> 0 | F46: =IF(F32>0,F21/F32*360,) -> 0 | G46: =IF(G31>0,G21/G31*360,) -> 0.68792606 | H46: =IF(H31>0,H21/H31*360,) -> 0.61957357 | I46: =CHOOSE($C$3,I62,I77,I92) -> 0.61957357 | J46: =CHOOSE($C$3,J62,J77,J92) -> 0.61957357 | K46: =CHOOSE($C$3,K62,K77,K92) -> 0.61957357 | L46: =CHOOSE($C$3,L62,L77,L92) -> 0.61957357 | M46: =CHOOSE($C$3,M62,M77,M92) -> 0.61957357 | N46: =CHOOSE($C$3,N62,N77,N92) -> 0.61957357 | O46: =CHOOSE($C$3,O62,O77,O92) -> 0.61957357 | P46: =CHOOSE($C$3,P62,P77,P92) -> 0.61957357 | ... AC46: =CHOOSE($C$3,AC62,AC77,AC92) -> 0.61957357
B47: =B22 -> Débitos de oper. assist. à saúde não rel. c/plano de saúde da op. | D47: =IF(D33>0,D22/D33*360,) -> 0 | E47: =IF(E33>0,E22/E33*360,) -> 0 | F47: =IF(F33>0,F22/F33*360,) -> 0 | G47: =IF(G31>0,G22/G31*360,) -> 4.3840686 | H47: =IF(H31>0,H22/H31*360,) -> 4.9630227 | I47: =CHOOSE($C$3,I63,I78,I93) -> 4.9630227 | J47: =CHOOSE($C$3,J63,J78,J93) -> 4.9630227 | K47: =CHOOSE($C$3,K63,K78,K93) -> 4.9630227 | L47: =CHOOSE($C$3,L63,L78,L93) -> 4.9630227 | M47: =CHOOSE($C$3,M63,M78,M93) -> 4.9630227 | N47: =CHOOSE($C$3,N63,N78,N93) -> 4.9630227 | O47: =CHOOSE($C$3,O63,O78,O93) -> 4.9630227 | P47: =CHOOSE($C$3,P63,P78,P93) -> 4.9630227 | ... AC47: =CHOOSE($C$3,AC63,AC78,AC93) -> 4.9630227
B48: =B23 -> Taxes | D48: =IF(D31>0,D23/D31*360,) -> 0 | E48: =IF(E31>0,E23/E31*360,) -> 0 | F48: =IF(F31>0,F23/F31*360,) -> 0 | G48: =IF(G31>0,G23/G31*360,) -> 3.8286123 | H48: =IF(H31>0,H23/H31*360,) -> 4.126201 | I48: =CHOOSE($C$3,I64,I79,I94) -> 4.126201 | J48: =CHOOSE($C$3,J64,J79,J94) -> 4.126201 | K48: =CHOOSE($C$3,K64,K79,K94) -> 4.126201 | L48: =CHOOSE($C$3,L64,L79,L94) -> 4.126201 | M48: =CHOOSE($C$3,M64,M79,M94) -> 4.126201 | N48: =CHOOSE($C$3,N64,N79,N94) -> 4.126201 | O48: =CHOOSE($C$3,O64,O79,O94) -> 4.126201 | P48: =CHOOSE($C$3,P64,P79,P94) -> 4.126201 | ... AC48: =CHOOSE($C$3,AC64,AC79,AC94) -> 4.126201
B49: =B24 -> Provisões técnicas de operações de assist. à saúde | D49: =IF(D31>0,D24/D31*360,) -> 0 | E49: =IF(E31>0,E24/E31*360,) -> 0 | F49: =IF(F31>0,F24/F31*360,) -> 0 | G49: =IF(G31>0,G24/G31*360,) -> 25.403736 | H49: =IF(H31>0,H24/H31*360,) -> 27.487317 | I49: =CHOOSE($C$3,I65,I80,I95) -> 27.487317 | J49: =CHOOSE($C$3,J65,J80,J95) -> 27.487317 | K49: =CHOOSE($C$3,K65,K80,K95) -> 27.487317 | L49: =CHOOSE($C$3,L65,L80,L95) -> 27.487317 | M49: =CHOOSE($C$3,M65,M80,M95) -> 27.487317 | N49: =CHOOSE($C$3,N65,N80,N95) -> 27.487317 | O49: =CHOOSE($C$3,O65,O80,O95) -> 27.487317 | P49: =CHOOSE($C$3,P65,P80,P95) -> 27.487317 | ... AC49: =CHOOSE($C$3,AC65,AC80,AC95) -> 27.487317
B50: =B25 -> Débitos diversos | D50: =IF(D33>0,D25/D33*360,) -> 0 | E50: =IF(E33>0,E25/E33*360,) -> 0 | F50: =IF(F33>0,F25/F33*360,) -> 0 | G50: =IF(G31>0,G25/G31*360,) -> 0.04509294 | H50: =IF(H31>0,H25/H31*360,) -> 0 | I50: =CHOOSE($C$3,I66,I81,I96) -> 0 | J50: =CHOOSE($C$3,J66,J81,J96) -> 0 | K50: =CHOOSE($C$3,K66,K81,K96) -> 0 | L50: =CHOOSE($C$3,L66,L81,L96) -> 0 | M50: =CHOOSE($C$3,M66,M81,M96) -> 0 | N50: =CHOOSE($C$3,N66,N81,N96) -> 0 | O50: =CHOOSE($C$3,O66,O81,O96) -> 0 | P50: =CHOOSE($C$3,P66,P81,P96) -> 0 | ... AC50: =CHOOSE($C$3,AC66,AC81,AC96) -> 0
B51: =+B26 -> Empréstimos de coligadas | G51: =IF(G31>0,G26/G31*360,) -> 0 | H51: =IF(H31>0,H26/H31*360,) -> 0 | I51: =CHOOSE($C$3,I67,I82,I97) -> 0 | J51: =CHOOSE($C$3,J67,J82,J97) -> 0 | K51: =CHOOSE($C$3,K67,K82,K97) -> 0 | L51: =CHOOSE($C$3,L67,L82,L97) -> 0 | M51: =CHOOSE($C$3,M67,M82,M97) -> 0 | N51: =CHOOSE($C$3,N67,N82,N97) -> 0 | O51: =CHOOSE($C$3,O67,O82,O97) -> 0 | P51: =CHOOSE($C$3,P67,P82,P97) -> 0 | ... AD51: =CHOOSE($C$3,AD67,AD82,AD97) -> 0
B52: =+B27 -> Other Non-Op. Cur. Liabilities | G52: =IF(G31>0,G27/G31*360,) -> 0 | H52: =IF(H31>0,H27/H31*360,) -> 0 | I52: =CHOOSE($C$3,I68,I83,I98) -> 0 | J52: =CHOOSE($C$3,J68,J83,J98) -> 0 | K52: =CHOOSE($C$3,K68,K83,K98) -> 0 | L52: =CHOOSE($C$3,L68,L83,L98) -> 0 | M52: =CHOOSE($C$3,M68,M83,M98) -> 0 | N52: =CHOOSE($C$3,N68,N83,N98) -> 0 | O52: =CHOOSE($C$3,O68,O83,O98) -> 0 | P52: =CHOOSE($C$3,P68,P83,P98) -> 0 | ... Z52: =CHOOSE($C$3,Z68,Z83,Z98) -> 0
B55: =B2 -> Base Case
B56: =B37 -> Aplicações de liquidez imediata e valores em trânsito | I56: =(H37) -> 0 | J56: =I56 -> 0 | K56: =J56 -> 0 | L56: =K56 -> 0 | M56: =L56 -> 0 | N56: =M56 -> 0 | O56: =N56 -> 0 | P56: =O56 -> 0 | Q56: =P56 -> 0 | ... AC56: =AB56 -> 0
B57: =B38 -> Reserva Técnica | I57: =(H38) -> 21.73781 | J57: =I57 -> 21.73781 | K57: =J57 -> 21.73781 | L57: =K57 -> 21.73781 | M57: =L57 -> 21.73781 | N57: =M57 -> 21.73781 | O57: =N57 -> 21.73781 | P57: =O57 -> 21.73781 | Q57: =P57 -> 21.73781 | ... AC57: =AB57 -> 21.73781
B58: =B39 -> Créd. operações pl. de assist. à saúde | I58: =(H39) -> 13.402773 | J58: =I58 -> 13.402773 | K58: =J58 -> 13.402773 | L58: =K58 -> 13.402773 | M58: =L58 -> 13.402773 | N58: =M58 -> 13.402773 | O58: =N58 -> 13.402773 | P58: =O58 -> 13.402773 | Q58: =P58 -> 13.402773 | ... AC58: =AB58 -> 13.402773
B59: =B40 -> Despesas de comercialização diferidas | I59: =(H40) -> 1.1960003 | J59: =I59 -> 1.1960003 | K59: =J59 -> 1.1960003 | L59: =K59 -> 1.1960003 | M59: =L59 -> 1.1960003 | N59: =M59 -> 1.1960003 | O59: =N59 -> 1.1960003 | P59: =O59 -> 1.1960003 | Q59: =P59 -> 1.1960003 | ... AC59: =AB59 -> 1.1960003
B60: =B41 -> Títulos e créditos a receber | I60: =(H41) -> 6.5950333 | J60: =I60 -> 6.5950333 | K60: =J60 -> 6.5950333 | L60: =K60 -> 6.5950333 | M60: =L60 -> 6.5950333 | N60: =M60 -> 6.5950333 | O60: =N60 -> 6.5950333 | P60: =O60 -> 6.5950333 | Q60: =P60 -> 6.5950333 | ... AC60: =AB60 -> 6.5950333
B61: =B42 -> Outros valores e bens | I61: =(H42) -> 4.1221639 | J61: =I61 -> 4.1221639 | K61: =J61 -> 4.1221639 | L61: =K61 -> 4.1221639 | M61: =L61 -> 4.1221639 | N61: =M61 -> 4.1221639 | O61: =N61 -> 4.1221639 | P61: =O61 -> 4.1221639 | Q61: =P61 -> 4.1221639 | ... AC61: =AB61 -> 4.1221639
B62: =B46 -> Débitos de operações de assit. à saúde | I62: =H46 -> 0.61957357 | J62: =I62 -> 0.61957357 | K62: =J62 -> 0.61957357 | L62: =K62 -> 0.61957357 | M62: =L62 -> 0.61957357 | N62: =M62 -> 0.61957357 | O62: =N62 -> 0.61957357 | P62: =O62 -> 0.61957357 | Q62: =P62 -> 0.61957357 | ... AC62: =AB62 -> 0.61957357
B63: =B47 -> Débitos de oper. assist. à saúde não rel. c/plano de saúde da op. | I63: =H47 -> 4.9630227 | J63: =I63 -> 4.9630227 | K63: =J63 -> 4.9630227 | L63: =K63 -> 4.9630227 | M63: =L63 -> 4.9630227 | N63: =M63 -> 4.9630227 | O63: =N63 -> 4.9630227 | P63: =O63 -> 4.9630227 | Q63: =P63 -> 4.9630227 | ... AC63: =AB63 -> 4.9630227
B64: =B48 -> Taxes | I64: =H48 -> 4.126201 | J64: =I64 -> 4.126201 | K64: =J64 -> 4.126201 | L64: =K64 -> 4.126201 | M64: =L64 -> 4.126201 | N64: =M64 -> 4.126201 | O64: =N64 -> 4.126201 | P64: =O64 -> 4.126201 | Q64: =P64 -> 4.126201 | ... AC64: =AB64 -> 4.126201
B65: =B49 -> Provisões técnicas de operações de assist. à saúde | I65: =H49 -> 27.487317 | J65: =I65 -> 27.487317 | K65: =J65 -> 27.487317 | L65: =K65 -> 27.487317 | M65: =L65 -> 27.487317 | N65: =M65 -> 27.487317 | O65: =N65 -> 27.487317 | P65: =O65 -> 27.487317 | Q65: =P65 -> 27.487317 | ... AC65: =AB65 -> 27.487317
B66: =B50 -> Débitos diversos | I66: =H50 -> 0 | J66: =I66 -> 0 | K66: =J66 -> 0 | L66: =K66 -> 0 | M66: =L66 -> 0 | N66: =M66 -> 0 | O66: =N66 -> 0 | P66: =O66 -> 0 | Q66: =P66 -> 0 | ... AC66: =AB66 -> 0
B67: =+B51 -> Empréstimos de coligadas | I67: =H51 -> 0 | J67: =I67 -> 0 | K67: =J67 -> 0 | L67: =K67 -> 0 | M67: =L67 -> 0 | N67: =M67 -> 0 | O67: =N67 -> 0 | P67: =O67 -> 0 | Q67: =P67 -> 0 | ... AC67: =AB67 -> 0
B68: =+B27 -> Other Non-Op. Cur. Liabilities | I68: =H52 -> 0 | J68: =I68 -> 0 | K68: =J68 -> 0 | L68: =K68 -> 0 | M68: =L68 -> 0 | N68: =M68 -> 0 | O68: =N68 -> 0 | P68: =O68 -> 0 | Q68: =P68 -> 0 | ... AC68: =AB68 -> 0
B70: =B3 -> Client Case
B71: =B56 -> Aplicações de liquidez imediata e valores em trânsito | I71: =I56 -> 0 | J71: =J56 -> 0 | K71: =K56 -> 0 | L71: =L56 -> 0 | M71: =M56 -> 0 | N71: =N56 -> 0 | O71: =O56 -> 0 | P71: =P56 -> 0 | ... AC71: =AC56 -> 0
B72: =B57 -> Reserva Técnica | I72: =I57 -> 21.73781 | J72: =J57 -> 21.73781 | K72: =K57 -> 21.73781 | L72: =L57 -> 21.73781 | M72: =M57 -> 21.73781 | N72: =N57 -> 21.73781 | O72: =O57 -> 21.73781 | P72: =P57 -> 21.73781 | ... AC72: =AC57 -> 21.73781
B73: =B58 -> Créd. operações pl. de assist. à saúde | I73: =I58 -> 13.402773 | J73: =J58 -> 13.402773 | K73: =K58 -> 13.402773 | L73: =L58 -> 13.402773 | M73: =M58 -> 13.402773 | N73: =N58 -> 13.402773 | O73: =O58 -> 13.402773 | P73: =P58 -> 13.402773 | ... AC73: =AC58 -> 13.402773
B74: =B59 -> Despesas de comercialização diferidas | I74: =I59 -> 1.1960003 | J74: =J59 -> 1.1960003 | K74: =K59 -> 1.1960003 | L74: =L59 -> 1.1960003 | M74: =M59 -> 1.1960003 | N74: =N59 -> 1.1960003 | O74: =O59 -> 1.1960003 | P74: =P59 -> 1.1960003 | ... AC74: =AC59 -> 1.1960003
B75: =B60 -> Títulos e créditos a receber | I75: =I60 -> 6.5950333 | J75: =J60 -> 6.5950333 | K75: =K60 -> 6.5950333 | L75: =L60 -> 6.5950333 | M75: =M60 -> 6.5950333 | N75: =N60 -> 6.5950333 | O75: =O60 -> 6.5950333 | P75: =P60 -> 6.5950333 | ... AC75: =AC60 -> 6.5950333
B76: =B61 -> Outros valores e bens | I76: =I61 -> 4.1221639 | J76: =J61 -> 4.1221639 | K76: =K61 -> 4.1221639 | L76: =L61 -> 4.1221639 | M76: =M61 -> 4.1221639 | N76: =N61 -> 4.1221639 | O76: =O61 -> 4.1221639 | P76: =P61 -> 4.1221639 | ... AC76: =AC61 -> 4.1221639
B77: =B62 -> Débitos de operações de assit. à saúde | I77: =I62 -> 0.61957357 | J77: =J62 -> 0.61957357 | K77: =K62 -> 0.61957357 | L77: =L62 -> 0.61957357 | M77: =M62 -> 0.61957357 | N77: =N62 -> 0.61957357 | O77: =O62 -> 0.61957357 | P77: =P62 -> 0.61957357 | ... AC77: =AC62 -> 0.61957357
B78: =B63 -> Débitos de oper. assist. à saúde não rel. c/plano de saúde da op. | I78: =I63 -> 4.9630227 | J78: =J63 -> 4.9630227 | K78: =K63 -> 4.9630227 | L78: =L63 -> 4.9630227 | M78: =M63 -> 4.9630227 | N78: =N63 -> 4.9630227 | O78: =O63 -> 4.9630227 | P78: =P63 -> 4.9630227 | ... AC78: =AC63 -> 4.9630227
B79: =B64 -> Taxes | I79: =I64 -> 4.126201 | J79: =J64 -> 4.126201 | K79: =K64 -> 4.126201 | L79: =L64 -> 4.126201 | M79: =M64 -> 4.126201 | N79: =N64 -> 4.126201 | O79: =O64 -> 4.126201 | P79: =P64 -> 4.126201 | ... AC79: =AC64 -> 4.126201
B80: =B65 -> Provisões técnicas de operações de assist. à saúde | I80: =I65 -> 27.487317 | J80: =J65 -> 27.487317 | K80: =K65 -> 27.487317 | L80: =L65 -> 27.487317 | M80: =M65 -> 27.487317 | N80: =N65 -> 27.487317 | O80: =O65 -> 27.487317 | P80: =P65 -> 27.487317 | ... AC80: =AC65 -> 27.487317
B81: =B66 -> Débitos diversos | I81: =I66 -> 0 | J81: =J66 -> 0 | K81: =K66 -> 0 | L81: =L66 -> 0 | M81: =M66 -> 0 | N81: =N66 -> 0 | O81: =O66 -> 0 | P81: =P66 -> 0 | ... AC81: =AC66 -> 0
B82: =+B67 -> Empréstimos de coligadas | I82: =I67 -> 0 | J82: =J67 -> 0 | K82: =K67 -> 0 | L82: =L67 -> 0 | M82: =M67 -> 0 | N82: =N67 -> 0 | O82: =O67 -> 0 | P82: =P67 -> 0 | ... AC82: =AC67 -> 0
B83: =+B27 -> Other Non-Op. Cur. Liabilities | I83: =I68 -> 0 | J83: =J68 -> 0 | K83: =K68 -> 0 | L83: =L68 -> 0 | M83: =M68 -> 0 | N83: =N68 -> 0 | O83: =O68 -> 0 | P83: =P68 -> 0 | ... AC83: =AC68 -> 0
B85: =B4 -> Stress Case
B86: =B71 -> Aplicações de liquidez imediata e valores em trânsito | I86: =I71 -> 0 | J86: =J71 -> 0 | K86: =K71 -> 0 | L86: =L71 -> 0 | M86: =M71 -> 0 | N86: =N71 -> 0 | O86: =O71 -> 0 | P86: =P71 -> 0 | ... AC86: =AC71 -> 0
B87: =B72 -> Reserva Técnica | I87: =I72 -> 21.73781 | J87: =J72 -> 21.73781 | K87: =K72 -> 21.73781 | L87: =L72 -> 21.73781 | M87: =M72 -> 21.73781 | N87: =N72 -> 21.73781 | O87: =O72 -> 21.73781 | P87: =P72 -> 21.73781 | ... AC87: =AC72 -> 21.73781
B88: =B73 -> Créd. operações pl. de assist. à saúde | I88: =I73 -> 13.402773 | J88: =J73 -> 13.402773 | K88: =K73 -> 13.402773 | L88: =L73 -> 13.402773 | M88: =M73 -> 13.402773 | N88: =N73 -> 13.402773 | O88: =O73 -> 13.402773 | P88: =P73 -> 13.402773 | ... AC88: =AC73 -> 13.402773
B89: =B74 -> Despesas de comercialização diferidas | I89: =I74 -> 1.1960003 | J89: =J74 -> 1.1960003 | K89: =K74 -> 1.1960003 | L89: =L74 -> 1.1960003 | M89: =M74 -> 1.1960003 | N89: =N74 -> 1.1960003 | O89: =O74 -> 1.1960003 | P89: =P74 -> 1.1960003 | ... AC89: =AC74 -> 1.1960003
B90: =B75 -> Títulos e créditos a receber | I90: =I75 -> 6.5950333 | J90: =J75 -> 6.5950333 | K90: =K75 -> 6.5950333 | L90: =L75 -> 6.5950333 | M90: =M75 -> 6.5950333 | N90: =N75 -> 6.5950333 | O90: =O75 -> 6.5950333 | P90: =P75 -> 6.5950333 | ... AC90: =AC75 -> 6.5950333
B91: =B76 -> Outros valores e bens | I91: =I76 -> 4.1221639 | J91: =J76 -> 4.1221639 | K91: =K76 -> 4.1221639 | L91: =L76 -> 4.1221639 | M91: =M76 -> 4.1221639 | N91: =N76 -> 4.1221639 | O91: =O76 -> 4.1221639 | P91: =P76 -> 4.1221639 | ... AC91: =AC76 -> 4.1221639
B92: =B77 -> Débitos de operações de assit. à saúde | I92: =I77 -> 0.61957357 | J92: =J77 -> 0.61957357 | K92: =K77 -> 0.61957357 | L92: =L77 -> 0.61957357 | M92: =M77 -> 0.61957357 | N92: =N77 -> 0.61957357 | O92: =O77 -> 0.61957357 | P92: =P77 -> 0.61957357 | ... AC92: =AC77 -> 0.61957357
B93: =B78 -> Débitos de oper. assist. à saúde não rel. c/plano de saúde da op. | I93: =I78 -> 4.9630227 | J93: =J78 -> 4.9630227 | K93: =K78 -> 4.9630227 | L93: =L78 -> 4.9630227 | M93: =M78 -> 4.9630227 | N93: =N78 -> 4.9630227 | O93: =O78 -> 4.9630227 | P93: =P78 -> 4.9630227 | ... AC93: =AC78 -> 4.9630227
B94: =B79 -> Taxes | I94: =I79 -> 4.126201 | J94: =J79 -> 4.126201 | K94: =K79 -> 4.126201 | L94: =L79 -> 4.126201 | M94: =M79 -> 4.126201 | N94: =N79 -> 4.126201 | O94: =O79 -> 4.126201 | P94: =P79 -> 4.126201 | ... AC94: =AC79 -> 4.126201
B95: =B80 -> Provisões técnicas de operações de assist. à saúde | I95: =I80 -> 27.487317 | J95: =J80 -> 27.487317 | K95: =K80 -> 27.487317 | L95: =L80 -> 27.487317 | M95: =M80 -> 27.487317 | N95: =N80 -> 27.487317 | O95: =O80 -> 27.487317 | P95: =P80 -> 27.487317 | ... AC95: =AC80 -> 27.487317
B96: =B81 -> Débitos diversos | I96: =I81 -> 0 | J96: =J81 -> 0 | K96: =K81 -> 0 | L96: =L81 -> 0 | M96: =M81 -> 0 | N96: =N81 -> 0 | O96: =O81 -> 0 | P96: =P81 -> 0 | ... AC96: =AC81 -> 0
B97: =+B82 -> Empréstimos de coligadas | I97: =I82 -> 0 | J97: =J82 -> 0 | K97: =K82 -> 0 | L97: =L82 -> 0 | M97: =M82 -> 0 | N97: =N82 -> 0 | O97: =O82 -> 0 | P97: =P82 -> 0 | ... AC97: =AC82 -> 0
B98: =+B27 -> Other Non-Op. Cur. Liabilities | I98: =I83 -> 0 | J98: =J83 -> 0 | K98: =K83 -> 0 | L98: =L83 -> 0 | M98: =M83 -> 0 | N98: =N83 -> 0 | O98: =O83 -> 0 | P98: =P83 -> 0 | ... AC98: =AC83 -> 0
I100: 1 | J100: 0.99773092 | K100: 0.99773092 | L100: 0.99773092 | M100: 0.99773092 | N100: 0.99773092 | O100: 1 | P100: 1 | Q100: 1 | R100: 1 | S100: 1 | T100: 1 | U100: 1 | V100: 1 | W100: 1 | X100: 1 | Y100: 1 | Z100: 1

Sheet ST Inv. & Debt
H4: ='Balance Sheet'!J83 -> 0 | I4: ='Balance Sheet'!K83 -> 0 | J4: ='Balance Sheet'!L83 -> 0 | K4: ='Balance Sheet'!M83 -> 0 | L4: ='Balance Sheet'!N83 -> 0 | M4: ='Balance Sheet'!O83 -> 0 | N4: ='Balance Sheet'!P83 -> 0 | O4: ='Balance Sheet'!Q83 -> 0 | ... R4: ='Balance Sheet'!T83 -> 33974
I5: 0.5 | J5: 1.5 | K5: 2.5 | L5: 3.5 | M5: 4.5 | N5: 5.5 | O5: 6.5
A7: =1+A6 -> 1 | B7: ST INVESTMENTS & DEBT | D7: ='Fixed Assets & CAPEX'!D7 -> 39813 | E7: ='Fixed Assets & CAPEX'!E7 -> 40178 | F7: ='Fixed Assets & CAPEX'!F7 -> 40543 | G7: ='Fixed Assets & CAPEX'!G7 -> 40908 | H7: ='Fixed Assets & CAPEX'!H7 -> 41274 | I7: ='Fixed Assets & CAPEX'!I7 -> 41639 | J7: ='Fixed Assets & CAPEX'!J7 -> 42004 | K7: ='Fixed Assets & CAPEX'!K7 -> 42369 | ... AB7: ='Fixed Assets & CAPEX'!AB7 -> 48579
A8: =1+A7 -> 2 | B8: R$ thousand
A9: =1+A8 -> 3
A10: =1+A9 -> 4 | B10: BALANCE SHEET ACCOUNTS
A11: =1+A10 -> 5
A12: =1+A11 -> 6 | B12: End of the Period ST Investments | H12: =H41 -> 149443.51 | I12: =I41 -> 165864.86 | J12: =J41 -> 120594.37 | K12: =K41 -> 70000 | L12: =L41 -> 70000 | M12: =M41 -> 70000 | N12: =N41 -> 70000 | O12: =O41 -> 70000 | ... AB12: =AB41 -> #DIV/0!
A13: =1+A12 -> 7 | B13: End of the Period Additional Leverage | H13: =H51 -> 0 | I13: =I51 -> 0 | J13: =J51 -> 0 | K13: =K51 -> 51880.553 | L13: =L51 -> 154768.37 | M13: =M51 -> 262913.99 | N13: =N51 -> 372358.18 | O13: =O51 -> 325981.38 | ... AB13: =AB51 -> #DIV/0!
A14: =1+A13 -> 8 | B14: End of the Period ST Debt | H14: =SUM(I110:I110)+$F$125*SUM(I126:I126)+$F$143*SUM(I144:I144)+$F$159*SUM(I160:I160)+F175*SUM(I176:I176)+$F$191*H33*SUM(I192:I192)+$F$209*H33*SUM(I210:I210)+$F$227*H33*SUM(I228:I228)+$F$245*H33*SUM(I246:I246)+$F$263*H34*SUM(I264:I264)+SUM(H327) -> 44928 | I14: =SUM(J110:J110)+$F$125*SUM(J126:J126)+$F$143*SUM(J144:J144)+$F$159*SUM(J160:J160)+G175*SUM(J176:J176)+$F$191*I33*SUM(J192:J192)+$F$209*I33*SUM(J210:J210)+$F$227*I33*SUM(J228:J228)+$F$245*I33*SUM(J246:J246)+$F$263*I34*SUM(J264:J264)+SUM(I327) -> 84248.825 | J14: =SUM(K110:K110)+$F$125*SUM(K126:K126)+$F$143*SUM(K144:K144)+$F$159*SUM(K160:K160)+H175*SUM(K176:K176)+$F$191*J33*SUM(K192:K192)+$F$209*J33*SUM(K210:K210)+$F$227*J33*SUM(K228:K228)+$F$245*J33*SUM(K246:K246)+$F$263*J34*SUM(K264:K264)+SUM(J327) -> 137426.11 | K14: =SUM(L110:L110)+$F$125*SUM(L126:L126)+$F$143*SUM(L144:L144)+$F$159*SUM(L160:L160)+I175*SUM(L176:L176)+$F$191*K33*SUM(L192:L192)+$F$209*K33*SUM(L210:L210)+$F$227*K33*SUM(L228:L228)+$F$245*K33*SUM(L246:L246)+$F$263*K34*SUM(L264:L264)+SUM(K327) -> 120481.63 | L14: =SUM(M110:M110)+$F$125*SUM(M126:M126)+$F$143*SUM(M144:M144)+$F$159*SUM(M160:M160)+J175*SUM(M176:M176)+$F$191*L33*SUM(M192:M192)+$F$209*L33*SUM(M210:M210)+$F$227*L33*SUM(M228:M228)+$F$245*L33*SUM(M246:M246)+$F$263*L34*SUM(M264:M264)+SUM(L327) -> 124575.83 | M14: =SUM(N110:N110)+$F$125*SUM(N126:N126)+$F$143*SUM(N144:N144)+$F$159*SUM(N160:N160)+K175*SUM(N176:N176)+$F$191*M33*SUM(N192:N192)+$F$209*M33*SUM(N210:N210)+$F$227*M33*SUM(N228:N228)+$F$245*M33*SUM(N246:N246)+$F$263*M34*SUM(N264:N264)+SUM(M327) -> 126614.73 | N14: =SUM(O110:O110)+$F$125*SUM(O126:O126)+$F$143*SUM(O144:O144)+$F$159*SUM(O160:O160)+L175*SUM(O176:O176)+$F$191*N33*SUM(O192:O192)+$F$209*N33*SUM(O210:O210)+$F$227*N33*SUM(O228:O228)+$F$245*N33*SUM(O246:O246)+$F$263*N34*SUM(O264:O264)+SUM(N327) -> 38897.913 | O14: =SUM(P110:P110)+$F$125*SUM(P126:P126)+$F$143*SUM(P144:P144)+$F$159*SUM(P160:P160)+M175*SUM(P176:P176)+$F$191*O33*SUM(P192:P192)+$F$209*O33*SUM(P210:P210)+$F$227*O33*SUM(P228:P228)+$F$245*O33*SUM(P246:P246)+$F$263*O34*SUM(P264:P264)+SUM(O327) -> 44454.758 | ... AB14: =SUM(AC110:AC110)+$F$125*SUM(AC126:AC126)+$F$143*SUM(AC144:AC144)+$F$159*SUM(AC160:AC160)+Z175*SUM(AC176:AC176)+$F$191*AB33*SUM(AC192:AC192)+$F$209*AB33*SUM(AC210:AC210)+$F$227*AB33*SUM(AC228:AC228)+$F$245*AB33*SUM(AC246:AC246)+$F$263*AB34*SUM(AC264:AC264)+SUM(AB327) -> 0
A15: =1+A14 -> 9 | B15: End of the Period LT Debt | H15: =H128+I146+I162+I178+H33*(I194+I212+I230+I248+I266)+I111+H328 -> 391248 | I15: =J128+J146+J162+J178+I33*(J194+J212+J230+J248+J266)+J111+I328 -> 436122.39 | J15: =K128+K146+K162+K178+J33*(K194+K212+K230+K248+K266)+K111+J328 -> 327169.06 | K15: =L128+L146+L162+L178+K33*(L194+L212+L230+L248+L266)+L111+K328 -> 239227.76 | L15: =M128+M146+M162+M178+L33*(M194+M212+M230+M248+M266)+M111+L328 -> 151840.86 | M15: =N128+N146+N162+N178+M33*(N194+N212+N230+N248+N266)+N111+M328 -> 67727.774 | N15: =O128+O146+O162+O178+N33*(O194+O212+O230+O248+O266)+O111+N328 -> 77403.17 | O15: =P128+P146+P162+P178+O33*(P194+P212+P230+P248+P266)+P111+O328 -> 88460.766 | P15: =Q128+Q146+Q162+Q178+P33*(Q194+Q212+Q230+Q248+Q266)+Q111+P328 -> 94148.018 | ... AB15: =AC128+AC146+AC162+AC178+AB33*(AC194+AC212+AC230+AC248+AC266)+AC111+AB328 -> 41700
A16: =1+A15 -> 10
A17: =1+A16 -> 11 | B17: INCOME STATEMENT ACCOUNTS
A18: =1+A17 -> 12
A19: =1+A18 -> 13 | B19: Total Financial Income | H19: =H47 -> 9627.4446 | I19: =I47 -> 5616.1586 | J19: =J47 -> 5106.2911 | K19: =K47 -> 2048.8105 | L19: =L47 -> 0 | M19: =M47 -> 0 | N19: =N47 -> 0 | O19: =O47 -> 0 | ... AB19: =AB47 -> #DIV/0!
A20: =1+A19 -> 14 | B20: Total Interest Expenses | H20: =-SUM(H60,H120,H138,H154,H170,H186,H202,H220,H238,H256,H274,H338) -> -52413.042 | I20: =-SUM(I60,I120,I138,I154,I170,I186,I202,I220,I238,I256,I274,I338) -> -44494.359 | J20: =-SUM(J60,J120,J138,J154,J170,J186,J202,J220,J238,J256,J274,J338) -> -47368.432 | K20: =-SUM(K60,K120,K138,K154,K170,K186,K202,K220,K238,K256,K274,K338) -> -44815.328 | L20: =-SUM(L60,L120,L138,L154,L170,L186,L202,L220,L238,L256,L274,L338) -> -40575.356 | M20: =-SUM(M60,M120,M138,M154,M170,M186,M202,M220,M238,M256,M274,M338) -> -44102.34 | N20: =-SUM(N60,N120,N138,N154,N170,N186,N202,N220,N238,N256,N274,N338) -> -47823.728 | O20: =-SUM(O60,O120,O138,O154,O170,O186,O202,O220,O238,O256,O274,O338) -> -53718.068 | ... AB20: =-SUM(AB60,AB120,AB138,AB154,AB170,AB186,AB202,AB220,AB238,AB256,AB274,AB338) -> #DIV/0!
A21: =1+A20 -> 15 | B21: Total FX Expense | H21: =SUM(H22:H23) -> 0 | I21: =SUM(I22:I23) -> 0 | J21: =SUM(J22:J23) -> 0 | K21: =SUM(K22:K23) -> 0 | L21: =SUM(L22:L23) -> 0 | M21: =SUM(M22:M23) -> 0 | N21: =SUM(N22:N23) -> 0 | O21: =SUM(O22:O23) -> 0 | ... AB21: =SUM(AB22:AB23) -> 0
A22: =1+A21 -> 16 | B22: Total FX Cash Expense | H22: =-SUM(H203,H221,H239,H257,H275) -> 0 | I22: =-SUM(I203,I221,I239,I257,I275) -> 0 | J22: =-SUM(J203,J221,J239,J257,J275) -> 0 | K22: =-SUM(K203,K221,K239,K257,K275) -> 0 | L22: =-SUM(L203,L221,L239,L257,L275) -> 0 | M22: =-SUM(M203,M221,M239,M257,M275) -> 0 | N22: =-SUM(N203,N221,N239,N257,N275) -> 0 | O22: =-SUM(O203,O221,O239,O257,O275) -> 0 | ... AB22: =-SUM(AB203,AB221,AB239,AB257,AB275) -> 0
A23: =1+A22 -> 17 | B23: Total FX Non-Cash Expense | H23: =-SUM(H204,H222,H240,H258,H276) -> 0 | I23: =-SUM(I204,I222,I240,I258,I276) -> 0 | J23: =-SUM(J204,J222,J240,J258,J276) -> 0 | K23: =-SUM(K204,K222,K240,K258,K276) -> 0 | L23: =-SUM(L204,L222,L240,L258,L276) -> 0 | M23: =-SUM(M204,M222,M240,M258,M276) -> 0 | N23: =-SUM(N204,N222,N240,N258,N276) -> 0 | O23: =-SUM(O204,O222,O240,O258,O276) -> 0 | ... AB23: =-SUM(AB204,AB222,AB240,AB258,AB276) -> 0
A24: =1+A23 -> 18
A25: =1+A24 -> 19 | B25: CASH FLOW ACCOUNTS
A26: =1+A25 -> 20
A27: =1+A26 -> 21 | B27: Total FX Non-Cash Expense | H27: =SUM(H204,H222,H240,H258,H276) -> 0 | I27: =SUM(I204,I222,I240,I258,I276) -> 0 | J27: =SUM(J204,J222,J240,J258,J276) -> 0 | K27: =SUM(K204,K222,K240,K258,K276) -> 0 | L27: =SUM(L204,L222,L240,L258,L276) -> 0 | M27: =SUM(M204,M222,M240,M258,M276) -> 0 | N27: =SUM(N204,N222,N240,N258,N276) -> 0 | O27: =SUM(O204,O222,O240,O258,O276) -> 0 | ... AB27: =SUM(AB204,AB222,AB240,AB258,AB276) -> 0
A28: =1+A27 -> 22 | B28: Debt Issuance | H28: =H65+H282+H125+H143 -> 95360 | I28: =I65+I282+I125 -> 132359.12 | J28: =J65+J282 -> 31636.424 | K28: =K65+K282 -> 36155.914 | L28: =L65+L282 -> 41321.044 | M28: =M65+M282 -> 47224.051 | N28: =N65+N282 -> 53970.343 | O28: =O65+O282 -> 61680.393 | P28: =P65+P282 -> 60563.306 | Q28: =Q65+Q282 -> 61510.654 | ... AB28: =AB65+AB282 -> 63218.573
A29: =1+A28 -> 23 | B29: Debt Amortization | H29: =-SUM(H110,H127,H145,H161,H177,$F191*G$33*H192,$F209*G$33*H210,$F227*G$33*H228,$F245*G$33*H246,$F263*G$34*H264,H326)-G51 -> -53291 | I29: =-SUM(I110,I127,I145,I161,I177,$F191*H$33*I192,$F209*H$33*I210,$F227*H$33*I228,$F245*H$33*I246,$F263*H$34*I264,I326)-H51 -> -48163.912 | J29: =-SUM(J110,J127,J145,J161,J177,$F191*I$33*J192,$F209*I$33*J210,$F227*I$33*J228,$F245*I$33*J246,$F263*I$34*J264,J326)-I51 -> -87412.467 | K29: =-SUM(K110,K127,K145,K161,K177,$F191*J$33*K192,$F209*J$33*K210,$F227*J$33*K228,$F245*J$33*K246,$F263*J$34*K264,K326)-J51 -> -141041.7 | L29: =-SUM(L110,L127,L145,L161,L177,$F191*K$33*L192,$F209*K$33*L210,$F227*K$33*L228,$F245*K$33*L246,$F263*K$34*L264,L326)-K51 -> -176494.28 | M29: =-SUM(M110,M127,M145,M161,M177,$F191*L$33*M192,$F209*L$33*M210,$F227*L$33*M228,$F245*L$33*M246,$F263*L$34*M264,M326)-L51 -> -284066.61 | N29: =-SUM(N110,N127,N145,N161,N177,$F191*M$33*N192,$F209*M$33*N210,$F227*M$33*N228,$F245*M$33*N246,$F263*M$34*N264,N326)-M51 -> -394925.76 | O29: =-SUM(O110,O127,O145,O161,O177,$F191*N$33*O192,$F209*N$33*O210,$F227*N$33*O228,$F245*N$33*O246,$F263*N$34*O264,O326)-N51 -> -417424.13 | ... AB29: =-SUM(AB110,AB127,AB145,AB161,AB177,$F191*AA$33*AB192,$F209*AA$33*AB210,$F227*AA$33*AB228,$F245*AA$33*AB246,$F263*AA$34*AB264,AB326)-AA51 -> #VALUE!
A30: =1+A29 -> 24
A31: =1+A30 -> 25 | B31: END OF THE PERIOD FX
A32: =1+A31 -> 26
A33: =1+A32 -> 27 | B33: End of the Period BRL / USD | H33: =Anual!S45 -> 1.8758 | I33: =Anual!T45 -> 2 | J33: =Anual!U45 -> 2.1 | K33: =Anual!V45 -> 2.1926471 | L33: =Anual!W45 -> 2.3001298 | M33: =Anual!X45 -> 2.4128812 | N33: =Anual!Y45 -> 2.507504 | O33: =Anual!Z45 -> 2.5812541 | ... AB33: =Anual!AM45 -> 0
A34: =1+A33 -> 28 | B34: End of the Period BRL / EUR | H34: =Anual!S48 -> 2.4306616 | I34: =Anual!T48 -> 2.56 | J34: =Anual!U48 -> 2.814 | K34: =Anual!V48 -> 2.9381471 | L34: =Anual!W48 -> 3.0821739 | M34: =Anual!X48 -> 3.2332608 | N34: =Anual!Y48 -> 3.3600554 | O34: =Anual!Z48 -> 3.4588805 | ... AB34: =Anual!AM48 -> 0
A35: =1+A34 -> 29
A36: =1+A35 -> 30
A37: =1+A36 -> 31 | B37: SHORT TERM INVESTMENTS - BRL | D37: =$G$7 -> 40908
A38: =1+A37 -> 32
A39: =1+A38 -> 33 | B39: Initial Balance | G39: ='Balance Sheet'!H13 -> 119958 | H39: ='Balance Sheet'!I13 -> 228486 | I39: ='Balance Sheet'!J13 -> 149443.51 | J39: ='Balance Sheet'!K13 -> 165864.86 | K39: ='Balance Sheet'!L13 -> 120594.37 | L39: ='Balance Sheet'!M13 -> 70000 | M39: ='Balance Sheet'!N13 -> 70000 | N39: ='Balance Sheet'!O13 -> 70000 | ... AB39: ='Balance Sheet'!AC13 -> #VALUE!
A40: =1+A39 -> 34 | B40: Change | H40: =H41-H39 -> -79042.49 | I40: =I41-I39 -> 16421.349 | J40: =J41-J39 -> -45270.491 | K40: =K41-K39 -> -50594.368 | L40: =L41-L39 -> 0 | M40: =M41-M39 -> 0 | N40: =N41-N39 -> 0 | O40: =O41-O39 -> 0 | ... AB40: =AB41-AB39 -> #DIV/0!
A41: =1+A40 -> 35 | B41: Final Balance | G41: ='Balance Sheet'!I13 -> 228486 | H41: ='Balance Sheet'!J13 -> 149443.51 | I41: ='Balance Sheet'!K13 -> 165864.86 | J41: ='Balance Sheet'!L13 -> 120594.37 | K41: ='Balance Sheet'!M13 -> 70000 | L41: ='Balance Sheet'!N13 -> 70000 | M41: ='Balance Sheet'!O13 -> 70000 | N41: ='Balance Sheet'!P13 -> 70000 | ... AB41: ='Balance Sheet'!AD13 -> #DIV/0!
A42: =1+A41 -> 36
A43: =1+A42 -> 37 | B43: Pre Curve | F43: %CDI | G43: =AVERAGE(Anual!R54,Anual!Q54)/100 -> 0.096263694 | H43: =AVERAGE(Anual!S54:T54)/100 -> 0.089918738 | I43: =AVERAGE(Anual!T54:U54)/100 -> 0.071190854 | J43: =AVERAGE(Anual!U54:V54)/100 -> 0.077477629 | K43: =AVERAGE(Anual!V54:W54)/100 -> 0.08998852 | L43: =AVERAGE(Anual!W54:X54)/100 -> 0.096667089 | M43: =AVERAGE(Anual!X54:Y54)/100 -> 0.0971 | N43: =AVERAGE(Anual!Y54:Z54)/100 -> 0.09585 | O43: =AVERAGE(Anual!Z54:AA54)/100 -> 0.0946 | ... X43: =AVERAGE(Anual!AI54:AJ54)/100 -> 0.0896 | Y43: =Anual!AK54/100 -> 0.0896 | Z43: =Anual!AL54/100 -> 0.0896 | AA43: =Anual!AM54/100 -> 0 | AB43: =Anual!AN54/100 -> 0
A44: =1+A43 -> 38 | B44: Effective FRA | H44: =$F45*H43 -> 0.080926864 | I44: =$F45*I43 -> 0.064071768 | J44: =$F45*J43 -> 0.069729866 | K44: =$F45*K43 -> 0.080989668 | L44: =$F45*L43 -> 0.08700038 | M44: =$F45*M43 -> 0.08739 | N44: =$F45*N43 -> 0.086265 | O44: =$F45*O43 -> 0.08514 | ... AB44: =$F45*AB43 -> 0
A45: =1+A44 -> 39 | B45: Effective Margin | F45: 0.9 | G45: =$F45*G43 -> 0.086637325 | H45: =$F45*H43 -> 0.080926864 | I45: =$F45*I43 -> 0.064071768 | J45: =$F45*J43 -> 0.069729866 | K45: =$F45*K43 -> 0.080989668 | L45: =$F45*L43 -> 0.08700038 | M45: =$F45*M43 -> 0.08739 | N45: =$F45*N43 -> 0.086265 | ... AB45: =$F45*AB43 -> 0
A46: =1+A45 -> 40
A47: =1+A46 -> 41 | B47: Financial Income | G47: =IF(G41>0,AVERAGE(G41,G39)*G45,0) -> 15094.128 | H47: =IF((AVERAGE(H41,H39)-$F54)>0,(AVERAGE(H41,H39)-$F54)*H45,0) -> 9627.4446 | I47: =IF((AVERAGE(I41,I39)-$F54)>0,(AVERAGE(I41,I39)-$F54)*I45,0) -> 5616.1586 | J47: =IF((AVERAGE(J41,J39)-$F54)>0,(AVERAGE(J41,J39)-$F54)*J45,0) -> 5106.2911 | K47: =IF((AVERAGE(K41,K39)-$F54)>0,(AVERAGE(K41,K39)-$F54)*K45,0) -> 2048.8105 | L47: =IF((AVERAGE(L41,L39)-$F54)>0,(AVERAGE(L41,L39)-$F54)*L45,0) -> 0 | M47: =IF((AVERAGE(M41,M39)-$F54)>0,(AVERAGE(M41,M39)-$F54)*M45,0) -> 0 | N47: =IF((AVERAGE(N41,N39)-$F54)>0,(AVERAGE(N41,N39)-$F54)*N45,0) -> 0 | O47: =IF((AVERAGE(O41,O39)-$F54)>0,(AVERAGE(O41,O39)-$F54)*O45,0) -> 0 | ... AB47: =IF((AVERAGE(AB41,AB39)-$F54)>0,(AVERAGE(AB41,AB39)-$F54)*AB45,0) -> #DIV/0!
A48: =1+A47 -> 42
A49: =1+A48 -> 43
A50: =1+A49 -> 44 | B50: ADDITIONAL LEVERAGE - BRL | D50: =$G$7 -> 40908
A51: =1+A50 -> 45 | B51: REVOLVE AMOUNT | D51: Quando identificado falta de caixa, excel capta CP | H51: =IF('Cash Flow'!H56+'Cash Flow'!H58<'ST Inv. & Debt'!$F$54,'ST Inv. & Debt'!$F$54-('Cash Flow'!H56+'Cash Flow'!H58),0) -> 0 | I51: =IF('Cash Flow'!I56+'Cash Flow'!I58<'ST Inv. & Debt'!$F$54,'ST Inv. & Debt'!$F$54-('Cash Flow'!I56+'Cash Flow'!I58),0) -> 0 | J51: =IF('Cash Flow'!J56+'Cash Flow'!J58<'ST Inv. & Debt'!$F$54,'ST Inv. & Debt'!$F$54-('Cash Flow'!J56+'Cash Flow'!J58),0) -> 0 | K51: =IF('Cash Flow'!K56+'Cash Flow'!K58<'ST Inv. & Debt'!$F$54,'ST Inv. & Debt'!$F$54-('Cash Flow'!K56+'Cash Flow'!K58),0) -> 51880.553 | L51: =IF('Cash Flow'!L56+'Cash Flow'!L58<'ST Inv. & Debt'!$F$54,'ST Inv. & Debt'!$F$54-('Cash Flow'!L56+'Cash Flow'!L58),0) -> 154768.37 | M51: =IF('Cash Flow'!M56+'Cash Flow'!M58<'ST Inv. & Debt'!$F$54,'ST Inv. & Debt'!$F$54-('Cash Flow'!M56+'Cash Flow'!M58),0) -> 262913.99 | N51: =IF('Cash Flow'!N56+'Cash Flow'!N58<'ST Inv. & Debt'!$F$54,'ST Inv. & Debt'!$F$54-('Cash Flow'!N56+'Cash Flow'!N58),0) -> 372358.18 | O51: =IF('Cash Flow'!O56+'Cash Flow'!O58<'ST Inv. & Debt'!$F$54,'ST Inv. & Debt'!$F$54-('Cash Flow'!O56+'Cash Flow'!O58),0) -> 325981.38 | ... AB51: =IF('Cash Flow'!AB56+'Cash Flow'!AB58<'ST Inv. & Debt'!$F$54,'ST Inv. & Debt'!$F$54-('Cash Flow'!AB56+'Cash Flow'!AB58),0) -> #DIV/0!
A52: =1+A51 -> 46
A53: =1+A52 -> 47
A54: =1+A53 -> 48 | D54: Minimum Cash | F54: 70000
A55: =1+A54 -> 49
A56: =1+A55 -> 50 | B56: Pre Curve | F56: CDI+ | H56: =AVERAGE(Anual!S54:T54)/100 -> 0.089918738 | I56: =AVERAGE(Anual!T54:U54)/100 -> 0.071190854 | J56: =AVERAGE(Anual!U54:V54)/100 -> 0.077477629 | K56: =AVERAGE(Anual!V54:W54)/100 -> 0.08998852 | L56: =AVERAGE(Anual!W54:X54)/100 -> 0.096667089 | M56: =AVERAGE(Anual!X54:Y54)/100 -> 0.0971 | N56: =AVERAGE(Anual!Y54:Z54)/100 -> 0.09585 | O56: =AVERAGE(Anual!Z54:AA54)/100 -> 0.0946 | ... AB56: =AVERAGE(Anual!AM54:AN54)/100 -> #DIV/0!
A57: =1+A56 -> 51 | B57: Effective FRA | H57: 0.096015681 | I57: 0.12356687 | J57: 0.12290962 | K57: 0.090296685 | L57: 0.071789647 | M57: 0.085106119 | N57: 0.089319698 | O57: 0.095997229 | P57: 0.085146953 | Q57: 0.083846822 | R57: 0.094207452 | S57: 0.094207452 | T57: 0.078127889 | U57: 0.07490519 | V57: 0.092863892 | W57: 0.092481879 | X57: 0.091336642 | Y57: 0.069511659 | Z57: 0.066321478 | AA57: 0.088858195 | AB57: 0.089971092
A58: =1+A57 -> 52 | B58: Effective Margin | F58: 0.04 | H58: =((1+H56)*(1+$F58))-1 -> 0.13351549 | I58: =((1+I56)*(1+$F58))-1 -> 0.11403849 | J58: =((1+J56)*(1+$F58))-1 -> 0.12057673 | K58: =((1+K56)*(1+$F58))-1 -> 0.13358806 | L58: =((1+L56)*(1+$F58))-1 -> 0.14053377 | M58: =((1+M56)*(1+$F58))-1 -> 0.140984 | N58: =((1+N56)*(1+$F58))-1 -> 0.139684 | O58: =((1+O56)*(1+$F58))-1 -> 0.138384 | ... AB58: =((1+AB56)*(1+$F58))-1 -> #DIV/0!
A59: =1+A58 -> 53
A60: =1+A59 -> 54 | B60: Interest Expense | H60: =H58*G51 -> 0 | I60: =I58*H51 -> 0 | J60: =J58*I51 -> 0 | K60: =K58*J51 -> 0 | L60: =L58*K51 -> 7290.9699 | M60: =M58*L51 -> 21819.863 | N60: =N58*M51 -> 36724.878 | O60: =O58*N51 -> 51528.414 | ... AB60: =AB58*AA51 -> #DIV/0!
A61: =1+A60 -> 55
A62: =1+A61 -> 56
A63: =1+A62 -> 57 | B63: DEBT ISSUANCE - BRL | D63: =$G$7 -> 40908
A64: =1+A63 -> 58 | G64: =G111/4 -> 98526.75
A65: =1+A64 -> 59 | B65: Debt Issuance | H65: 0 | I65: =H112 -> 0 | J65: 0 | K65: 0 | L65: 0 | M65: 0 | N65: 0 | O65: 0 | P65: 0 | Q65: 0 | R65: 0 | S65: 0 | T65: 0 | U65: 0 | V65: 0 | W65: 0 | X65: 0 | Y65: 0 | Z65: 0 | AA65: 0 | AB65: 0
A66: =1+A65 -> 60 | B66: Initial Balance | H66: =G111+H65 -> 394107 | I66: =H111+I65 -> 344986 | J66: =I111+J65 -> 313887 | K66: =J111+K65 -> 262863 | L66: =K111+L65 -> 176334 | M66: =L111+M65 -> 117556 | N66: =M111+N65 -> 58778 | O66: =N111+O65 -> 0
A67: =1+A66 -> 61 | B67: % Amt Issuance #0 | F67: =$F$110 -> 1 | K67: =IF(SUM($H67:J67)>=$H65,0,$H65*$F67) -> 0 | L67: =IF(SUM($H67:K67)>=$H65,0,$H65*$F67) -> 0 | M67: =IF(SUM($H67:L67)>=$H65,0,$H65*$F67) -> 0 | N67: =IF(SUM($H67:M67)>=$H65,0,$H65*$F67) -> 0 | O67: =IF(SUM($H67:N67)>=$H65,0,$H65*$F67) -> 0 | P67: =IF(SUM($H67:O67)>=$H65,0,$H65*$F67) -> 0 | Q67: =IF(SUM($H67:P67)>=$H65,0,$H65*$F67) -> 0 | R67: =IF(SUM($H67:Q67)>=$H65,0,$H65*$F67) -> 0 | ... AB67: =IF(SUM($H67:AA67)>=$H65,0,$H65*$F67) -> 0
A68: =1+A67 -> 62 | B68: % Amt Issuance #1 | F68: =$F$110 -> 1 | I68: =IF(SUM($H68:H68)>=$I65,0,$I65*$F68) -> 0 | J68: =IF(SUM($H68:I68)>=$I65,0,$I65*$F68) -> 0 | K68: =IF(SUM($H68:J68)>=$I65,0,$I65*$F68) -> 0 | L68: =IF(SUM($H68:K68)>=$I65,0,$I65*$F68) -> 0 | M68: =IF(SUM($H68:L68)>=$I65,0,$I65*$F68) -> 0 | N68: =IF(SUM($H68:M68)>=$I65,0,$I65*$F68) -> 0 | O68: =IF(SUM($H68:N68)>=$I65,0,$I65*$F68) -> 0 | P68: =IF(SUM($H68:O68)>=$I65,0,$I65*$F68) -> 0 | ... AB68: =IF(SUM($H68:AA68)>=$I65,0,$I65*$F68) -> 0
A69: =1+A68 -> 63 | B69: % Amt Issuance #2 | F69: =$F$110 -> 1 | J69: 0 | K69: =IF(SUM($H69:J69)>=$J65,0,$J65*$F69) -> 0 | L69: =IF(SUM($H69:K69)>=$J65,0,$J65*$F69) -> 0 | M69: =IF(SUM($H69:L69)>=$J65,0,$J65*$F69) -> 0 | N69: =IF(SUM($H69:M69)>=$J65,0,$J65*$F69) -> 0 | O69: =IF(SUM($H69:N69)>=$J65,0,$J65*$F69) -> 0 | P69: =IF(SUM($H69:O69)>=$J65,0,$J65*$F69) -> 0 | Q69: =IF(SUM($H69:P69)>=$J65,0,$J65*$F69) -> 0 | R69: =IF(SUM($H69:Q69)>=$J65,0,$J65*$F69) -> 0 | ... AB69: =IF(SUM($H69:AA69)>=$J65,0,$J65*$F69) -> 0
A70: =1+A69 -> 64 | B70: % Amt Issuance #3 | F70: =$F$110 -> 1 | K70: =IF(SUM($H70:J70)>=$K65,0,$K65*$F70) -> 0 | L70: =IF(SUM($H70:K70)>=$K65,0,$K65*$F70) -> 0 | M70: =IF(SUM($H70:L70)>=$K65,0,$K65*$F70) -> 0 | N70: =IF(SUM($H70:M70)>=$K65,0,$K65*$F70) -> 0 | O70: =IF(SUM($H70:N70)>=$K65,0,$K65*$F70) -> 0 | P70: =IF(SUM($H70:O70)>=$K65,0,$K65*$F70) -> 0 | Q70: =IF(SUM($H70:P70)>=$K65,0,$K65*$F70) -> 0 | R70: =IF(SUM($H70:Q70)>=$K65,0,$K65*$F70) -> 0 | ... AB70: =IF(SUM($H70:AA70)>=$K65,0,$K65*$F70) -> 0
A71: =1+A70 -> 65 | B71: % Amt Issuance #4 | F71: =$F$110 -> 1 | L71: =IF(SUM($H71:K71)>=$L65,0,$L65*$F71) -> 0 | M71: =IF(SUM($H71:L71)>=$L65,0,$L65*$F71) -> 0 | N71: =IF(SUM($H71:M71)>=$L65,0,$L65*$F71) -> 0 | O71: =IF(SUM($H71:N71)>=$L65,0,$L65*$F71) -> 0 | P71: =IF(SUM($H71:O71)>=$L65,0,$L65*$F71) -> 0 | Q71: =IF(SUM($H71:P71)>=$L65,0,$L65*$F71) -> 0 | R71: =IF(SUM($H71:Q71)>=$L65,0,$L65*$F71) -> 0 | S71: =IF(SUM($H71:R71)>=$L65,0,$L65*$F71) -> 0 | ... AB71: =IF(SUM($H71:AA71)>=$L65,0,$L65*$F71) -> 0
A72: =1+A71 -> 66 | B72: % Amt Issuance #5 | F72: =$F$110 -> 1 | M72: =IF(SUM($H72:L72)>=$M65,0,$M65*$F72) -> 0 | N72: =IF(SUM($H72:M72)>=$M65,0,$M65*$F72) -> 0 | O72: =IF(SUM($H72:N72)>=$M65,0,$M65*$F72) -> 0 | P72: =IF(SUM($H72:O72)>=$M65,0,$M65*$F72) -> 0 | Q72: =IF(SUM($H72:P72)>=$M65,0,$M65*$F72) -> 0 | R72: =IF(SUM($H72:Q72)>=$M65,0,$M65*$F72) -> 0 | S72: =IF(SUM($H72:R72)>=$M65,0,$M65*$F72) -> 0 | T72: =IF(SUM($H72:S72)>=$M65,0,$M65*$F72) -> 0 | ... AB72: =IF(SUM($H72:AA72)>=$M65,0,$M65*$F72) -> 0
A73: =1+A72 -> 67 | B73: % Amt Issuance #6 | F73: =$F$110 -> 1 | N73: =IF(SUM($H73:M73)>=$N65,0,$N65*$F73) -> 0 | O73: =IF(SUM($H73:N73)>=$N65,0,$N65*$F73) -> 0 | P73: =IF(SUM($H73:O73)>=$N65,0,$N65*$F73) -> 0 | Q73: =IF(SUM($H73:P73)>=$N65,0,$N65*$F73) -> 0 | R73: =IF(SUM($H73:Q73)>=$N65,0,$N65*$F73) -> 0 | S73: =IF(SUM($H73:R73)>=$N65,0,$N65*$F73) -> 0 | T73: =IF(SUM($H73:S73)>=$N65,0,$N65*$F73) -> 0 | U73: =IF(SUM($H73:T73)>=$N65,0,$N65*$F73) -> 0 | ... AB73: =IF(SUM($H73:AA73)>=$N65,0,$N65*$F73) -> 0
A74: =1+A73 -> 68 | B74: % Amt Issuance #7 | F74: =$F$110 -> 1 | O74: =IF(SUM($H74:N74)>=$O65,0,$O65*$F74) -> 0 | P74: =IF(SUM($H74:O74)>=$O65,0,$O65*$F74) -> 0 | Q74: =IF(SUM($H74:P74)>=$O65,0,$O65*$F74) -> 0 | R74: =IF(SUM($H74:Q74)>=$O65,0,$O65*$F74) -> 0 | S74: =IF(SUM($H74:R74)>=$O65,0,$O65*$F74) -> 0 | T74: =IF(SUM($H74:S74)>=$O65,0,$O65*$F74) -> 0 | U74: =IF(SUM($H74:T74)>=$O65,0,$O65*$F74) -> 0 | V74: =IF(SUM($H74:U74)>=$O65,0,$O65*$F74) -> 0 | ... AB74: =IF(SUM($H74:AA74)>=$O65,0,$O65*$F74) -> 0
A75: =1+A74 -> 69 | B75: % Amt Issuance #8 | F75: =$F$110 -> 1 | P75: =IF(SUM($H75:O75)>=$P65,0,$P65*$F75) -> 0 | Q75: =IF(SUM($H75:P75)>=$P65,0,$P65*$F75) -> 0 | R75: =IF(SUM($H75:Q75)>=$P65,0,$P65*$F75) -> 0 | S75: =IF(SUM($H75:R75)>=$P65,0,$P65*$F75) -> 0 | T75: =IF(SUM($H75:S75)>=$P65,0,$P65*$F75) -> 0 | U75: =IF(SUM($H75:T75)>=$P65,0,$P65*$F75) -> 0 | V75: =IF(SUM($H75:U75)>=$P65,0,$P65*$F75) -> 0 | W75: =IF(SUM($H75:V75)>=$P65,0,$P65*$F75) -> 0 | ... AB75: =IF(SUM($H75:AA75)>=$P65,0,$P65*$F75) -> 0
A76: =1+A75 -> 70 | B76: % Amt Issuance #9 | F76: =$F$110 -> 1 | Q76: =IF(SUM($H76:P76)>=$Q65,0,$Q65*$F76) -> 0 | R76: =IF(SUM($H76:Q76)>=$Q65,0,$Q65*$F76) -> 0 | S76: =IF(SUM($H76:R76)>=$Q65,0,$Q65*$F76) -> 0 | T76: =IF(SUM($H76:S76)>=$Q65,0,$Q65*$F76) -> 0 | U76: =IF(SUM($H76:T76)>=$Q65,0,$Q65*$F76) -> 0 | V76: =IF(SUM($H76:U76)>=$Q65,0,$Q65*$F76) -> 0 | W76: =IF(SUM($H76:V76)>=$Q65,0,$Q65*$F76) -> 0 | X76: =IF(SUM($H76:W76)>=$Q65,0,$Q65*$F76) -> 0 | ... AB76: =IF(SUM($H76:AA76)>=$Q65,0,$Q65*$F76) -> 0
A77: =1+A76 -> 71 | B77: % Amt Issuance #10 | F77: =$F$110 -> 1 | R77: =IF(SUM($H77:Q77)>=$R65,0,$R65*$F77) -> 0 | S77: =IF(SUM($H77:R77)>=$R65,0,$R65*$F77) -> 0 | T77: =IF(SUM($H77:S77)>=$R65,0,$R65*$F77) -> 0 | U77: =IF(SUM($H77:T77)>=$R65,0,$R65*$F77) -> 0 | V77: =IF(SUM($H77:U77)>=$R65,0,$R65*$F77) -> 0 | W77: =IF(SUM($H77:V77)>=$R65,0,$R65*$F77) -> 0 | X77: =IF(SUM($H77:W77)>=$R65,0,$R65*$F77) -> 0 | Y77: =IF(SUM($H77:X77)>=$R65,0,$R65*$F77) -> 0 | ... AB77: =IF(SUM($H77:AA77)>=$R65,0,$R65*$F77) -> 0
A78: =1+A77 -> 72 | B78: % Amt Issuance #11 | F78: =$F$110 -> 1 | S78: =IF(SUM($H78:R78)>=$S65,0,$S65*$F78) -> 0 | T78: =IF(SUM($H78:S78)>=$S65,0,$S65*$F78) -> 0 | U78: =IF(SUM($H78:T78)>=$S65,0,$S65*$F78) -> 0 | V78: =IF(SUM($H78:U78)>=$S65,0,$S65*$F78) -> 0 | W78: =IF(SUM($H78:V78)>=$S65,0,$S65*$F78) -> 0 | X78: =IF(SUM($H78:W78)>=$S65,0,$S65*$F78) -> 0 | Y78: =IF(SUM($H78:X78)>=$S65,0,$S65*$F78) -> 0 | Z78: =IF(SUM($H78:Y78)>=$S65,0,$S65*$F78) -> 0 | ... AB78: =IF(SUM($H78:AA78)>=$S65,0,$S65*$F78) -> 0
A79: =1+A78 -> 73 | B79: % Amt Issuance #12 | F79: =$F$110 -> 1 | T79: =IF(SUM($H79:S79)>=$T65,0,$T65*$F79) -> 0 | U79: =IF(SUM($H79:T79)>=$T65,0,$T65*$F79) -> 0 | V79: =IF(SUM($H79:U79)>=$T65,0,$T65*$F79) -> 0 | W79: =IF(SUM($H79:V79)>=$T65,0,$T65*$F79) -> 0 | X79: =IF(SUM($H79:W79)>=$T65,0,$T65*$F79) -> 0 | Y79: =IF(SUM($H79:X79)>=$T65,0,$T65*$F79) -> 0 | Z79: =IF(SUM($H79:Y79)>=$T65,0,$T65*$F79) -> 0 | AA79: =IF(SUM($H79:Z79)>=$T65,0,$T65*$F79) -> 0 | AB79: =IF(SUM($H79:AA79)>=$T65,0,$T65*$F79) -> 0
A80: =1+A79 -> 74 | B80: % Amt Issuance #13 | F80: =$F$110 -> 1 | U80: =IF(SUM($H80:T80)>=$U65,0,$U65*$F80) -> 0 | V80: =IF(SUM($H80:U80)>=$U65,0,$U65*$F80) -> 0 | W80: =IF(SUM($H80:V80)>=$U65,0,$U65*$F80) -> 0 | X80: =IF(SUM($H80:W80)>=$U65,0,$U65*$F80) -> 0 | Y80: =IF(SUM($H80:X80)>=$U65,0,$U65*$F80) -> 0 | Z80: =IF(SUM($H80:Y80)>=$U65,0,$U65*$F80) -> 0 | AA80: =IF(SUM($H80:Z80)>=$U65,0,$U65*$F80) -> 0 | AB80: =IF(SUM($H80:AA80)>=$U65,0,$U65*$F80) -> 0
A81: =1+A80 -> 75 | B81: % Amt Issuance #14 | F81: =$F$110 -> 1 | V81: =IF(SUM($H81:U81)>=$V65,0,$V65*$F81) -> 0 | W81: =IF(SUM($H81:V81)>=$V65,0,$V65*$F81) -> 0 | X81: =IF(SUM($H81:W81)>=$V65,0,$V65*$F81) -> 0 | Y81: =IF(SUM($H81:X81)>=$V65,0,$V65*$F81) -> 0 | Z81: =IF(SUM($H81:Y81)>=$V65,0,$V65*$F81) -> 0 | AA81: =IF(SUM($H81:Z81)>=$V65,0,$V65*$F81) -> 0 | AB81: =IF(SUM($H81:AA81)>=$V65,0,$V65*$F81) -> 0
A82: =1+A81 -> 76 | B82: % Amt Issuance #15 | F82: =$F$110 -> 1 | W82: =IF(SUM($H82:V82)>=$W65,0,$W65*$F82) -> 0 | X82: =IF(SUM($H82:W82)>=$W65,0,$W65*$F82) -> 0 | Y82: =IF(SUM($H82:X82)>=$W65,0,$W65*$F82) -> 0 | Z82: =IF(SUM($H82:Y82)>=$W65,0,$W65*$F82) -> 0 | AA82: =IF(SUM($H82:Z82)>=$W65,0,$W65*$F82) -> 0 | AB82: =IF(SUM($H82:AA82)>=$W65,0,$W65*$F82) -> 0
A83: =1+A82 -> 77 | B83: % Amt Issuance #16 | F83: =$F$110 -> 1 | X83: =IF(SUM($H83:W83)>=$X65,0,$X65*$F83) -> 0 | Y83: =IF(SUM($H83:X83)>=$X65,0,$X65*$F83) -> 0 | Z83: =IF(SUM($H83:Y83)>=$X65,0,$X65*$F83) -> 0 | AA83: =IF(SUM($H83:Z83)>=$X65,0,$X65*$F83) -> 0 | AB83: =IF(SUM($H83:AA83)>=$X65,0,$X65*$F83) -> 0
A84: =1+A83 -> 78 | B84: % Amt Issuance #17 | F84: =$F$110 -> 1 | Y84: =IF(SUM($H84:X84)>=$Y65,0,$Y65*$F84) -> 0 | Z84: =IF(SUM($H84:Y84)>=$Y65,0,$Y65*$F84) -> 0 | AA84: =IF(SUM($H84:Z84)>=$Y65,0,$Y65*$F84) -> 0 | AB84: =IF(SUM($H84:AA84)>=$Y65,0,$Y65*$F84) -> 0
A85: =1+A84 -> 79 | B85: % Amt Issuance #18 | F85: =$F$110 -> 1 | Z85: =IF(SUM($H85:Y85)>=$Z65,0,$Z65*$F85) -> 0 | AA85: =IF(SUM($H85:Z85)>=$Z65,0,$Z65*$F85) -> 0 | AB85: =IF(SUM($H85:AA85)>=$Z65,0,$Z65*$F85) -> 0
A86: =1+A85 -> 80 | B86: % Amt Issuance #19 | F86: =$F$110 -> 1 | AA86: =IF(SUM($H86:Z86)>=$AA65,0,$AA65*$F86) -> 0 | AB86: =IF(SUM($H86:AA86)>=$AA65,0,$AA65*$F86) -> 0
A87: =1+A86 -> 81 | B87: % Amt Issuance #20 | F87: =$F$110 -> 1 | AB87: =IF(SUM($H87:AA87)>=$AB65,0,$AB65*$F87) -> 0
A88: =1+A87 -> 82 | B88: % Amt Issuance #21 | F88: =$F$110 -> 1
A89: =1+A88 -> 83 | B89: % Amt Issuance #22 | F89: =$F$110 -> 1
A90: =1+A89 -> 84 | B90: % Amt Issuance #23 | F90: =$F$110 -> 1
A91: =1+A90 -> 85 | B91: % Amt Issuance #24 | F91: =$F$110 -> 1
A92: =1+A91 -> 86 | B92: % Amt Issuance #25 | F92: =$F$110 -> 1
A93: =1+A92 -> 87 | B93: % Amt Issuance #26 | F93: =$F$110 -> 1
A94: =1+A93 -> 88 | B94: % Amt Issuance #27 | F94: =$F$110 -> 1
A95: =1+A94 -> 89 | B95: % Amt Issuance #28 | F95: =$F$110 -> 1
A96: =1+A95 -> 90 | B96: % Amt Issuance #29 | F96: =$F$110 -> 1
A97: =1+A96 -> 91 | B97: % Amt Issuance #30 | F97: =$F$110 -> 1
A98: =1+A97 -> 92 | B98: % Amt Issuance #31 | F98: =$F$110 -> 1
A99: =1+A98 -> 93 | B99: % Amt Issuance #32 | F99: =$F$110 -> 1
... A109: =1+A108 -> 103 | B109: % Amt Issuance #42 | F109: =$F$110 -> 1
A110: =1+A109 -> 104 | B110: Periodical Standard Amortization | F110: 1 | H110: ='Balance Sheet'!I50 -> 49121 | I110: =955+30144 -> 31099 | J110: =601+50423 -> 51024 | K110: =145+86384 -> 86529 | L110: =(69+176265)/3 -> 58778 | M110: =L110 -> 58778 | N110: =M110 -> 58778 | P110: =O110 -> 0 | Q110: =P110 -> 0 | R110: =Q110 -> 0 | S110: =R110 -> 0 | T110: =S110 -> 0 | U110: =T110 -> 0 | V110: =U110 -> 0 | W110: =V110 -> 0 | ... AB110: =AA110 -> 0
A111: =1+A110 -> 105 | B111: Final Balance | G111: ='Balance Sheet'!I64+'Balance Sheet'!I50 -> 394107 | H111: =H66-H110 -> 344986 | I111: =I66-I110 -> 313887 | J111: =J66-J110 -> 262863 | K111: =K66-K110 -> 176334 | L111: =L66-L110 -> 117556 | M111: =M66-M110 -> 58778 | N111: =N66-N110 -> 0 | O111: =O66-O110 -> 0 | ... AB111: =AB66-AB110 -> 0
G112: 64000 | I112: 0 | J112: =I111*25% -> 78471.75 | K112: =J111*25% -> 65715.75 | L112: =K111*25% -> 44083.5 | M112: =L111*25% -> 29389
A113: =1+A112 -> 1 | B113: Benchmark | F113: Pré | G113: 19569 | H113: =H43 -> 0.089918738 | I113: =I43 -> 0.071190854 | J113: =J43 -> 0.077477629 | K113: =K43 -> 0.08998852 | L113: =L43 -> 0.096667089 | M113: =M43 -> 0.0971 | N113: =N43 -> 0.09585 | O113: =O43 -> 0.0946 | ... S113: =S43 -> 0.0921 | T113: =Anual!AF54/100 -> 0.0921 | U113: =Anual!AG54/100 -> 0.0921 | V113: =Anual!AH54/100 -> 0.0921 | W113: =Anual!AI54/100 -> 0.0896 | X113: =Anual!AJ54/100 -> 0.0896 | Y113: =Anual!AK54/100 -> 0.0896 | Z113: =Anual!AL54/100 -> 0.0896 | AA113: =Anual!AM54/100 -> 0 | AB113: =Anual!AN54/100 -> 0
...

Sheet Fixed Assets & CAPEX
A2: 1 | B2: ='Revenues, COGS & SG&A'!B2 -> Base Case | C2: Scenario
A3: 2 | B3: ='Revenues, COGS & SG&A'!B3 -> Client Case | C3: =Output!G2 -> 1 | H3: ='Balance Sheet'!J83 -> 0 | I3: ='Balance Sheet'!K83 -> 0 | J3: ='Balance Sheet'!L83 -> 0 | K3: ='Balance Sheet'!M83 -> 0 | L3: ='Balance Sheet'!N83 -> 0 | M3: ='Balance Sheet'!O83 -> 0 | N3: ='Balance Sheet'!P83 -> 0 | O3: ='Balance Sheet'!Q83 -> 0
A4: 3 | B4: ='Revenues, COGS & SG&A'!B4 -> Stress Case
H6: 1 | I6: 2 | J6: 3 | K6: 4 | L6: 5 | M6: 6 | N6: 7 | O6: 8 | P6: 9 | Q6: 10 | R6: 11 | S6: 12 | T6: 13 | U6: 14 | V6: 15 | W6: 16 | X6: 17 | Y6: 18 | Z6: 19 | AA6: 20 | AB6: 21
B7: FIXED ASSETS & CAPEX | D7: ='Revenues, COGS & SG&A'!E7 -> 39813 | E7: ='Revenues, COGS & SG&A'!F7 -> 40178 | F7: ='Revenues, COGS & SG&A'!G7 -> 40543 | G7: =+'Revenues, COGS & SG&A'!C5 -> 40908 | H7: ='Revenues, COGS & SG&A'!I7 -> 41274 | I7: ='Revenues, COGS & SG&A'!J7 -> 41639 | J7: ='Revenues, COGS & SG&A'!K7 -> 42004 | K7: ='Revenues, COGS & SG&A'!L7 -> 42369 | L7: ='Revenues, COGS & SG&A'!M7 -> 42735 | M7: ='Revenues, COGS & SG&A'!N7 -> 43100 | N7: ='Revenues, COGS & SG&A'!O7 -> 43465 | O7: ='Revenues, COGS & SG&A'!P7 -> 43830 | ... AB7: ='Revenues, COGS & SG&A'!AC7 -> 48579
B8: R$ thousand
B10: BALANCE SHEET ACCOUNTS | H10: =SUM(H12:H22) -> 419066 | I10: =SUM(I12:I22) -> 526929.74 | J10: =SUM(J12:J22) -> 590202.59 | K10: =SUM(K12:K22) -> 662514.42 | L10: =SUM(L12:L22) -> 745156.51 | M10: =SUM(M12:M22) -> 839604.61 | N10: =SUM(N12:N22) -> 947545.3 | O10: =SUM(O12:O22) -> 1070906.1 | ... AB10: =SUM(AB12:AB22) -> 2718339
B12: Terrenos | G12: ='Balance Sheet'!I37+'Balance Sheet'!I38 -> 280066 | H12: =G12+H37 -> 419066 | I12: =H12+I37 -> 526929.74 | J12: =I12+J37 -> 590202.59 | K12: =J12+K37 -> 662514.42 | L12: =K12+L37 -> 745156.51 | M12: =L12+M37 -> 839604.61 | N12: =M12+N37 -> 947545.3 | O12: =N12+O37 -> 1070906.1 | ... AB12: =AA12+AB37 -> 2718339
B13: Edificações | H13: =G13+H38-H80 -> 0 | I13: =H13+I38-I80 -> 0 | J13: =I13+J38-J80 -> 0 | K13: =J13+K38-K80 -> 0 | L13: =K13+L38-L80 -> 0 | M13: =L13+M38-M80 -> 0 | N13: =M13+N38-N80 -> 0 | O13: =N13+O38-O80 -> 0 | ... AB13: =AA13+AB38-AB80 -> 0
B14: Veículos | H14: =G14+H39-H81 -> 0 | I14: =H14+I39-I81 -> 0 | J14: =I14+J39-J81 -> 0 | K14: =J14+K39-K81 -> 0 | L14: =K14+L39-L81 -> 0 | M14: =L14+M39-M81 -> 0 | N14: =M14+N39-N81 -> 0 | O14: =N14+O39-O81 -> 0 | ... AB14: =AA14+AB39-AB81 -> 0
B15: Máquinas e Equipamentos | H15: =G15+H40-H82 -> 0 | I15: =H15+I40-I82 -> 0 | J15: =I15+J40-J82 -> 0 | K15: =J15+K40-K82 -> 0 | L15: =K15+L40-L82 -> 0 | M15: =L15+M40-M82 -> 0 | N15: =M15+N40-N82 -> 0 | O15: =N15+O40-O82 -> 0 | ... AB15: =AA15+AB40-AB82 -> 0
B16: Outros | H16: =G16+H41-H83 -> 0 | I16: =H16+I41-I83 -> 0 | J16: =I16+J41-J83 -> 0 | K16: =J16+K41-K83 -> 0 | L16: =K16+L41-L83 -> 0 | M16: =L16+M41-M83 -> 0 | N16: =M16+N41-N83 -> 0 | O16: =N16+O41-O83 -> 0 | ... AB16: =AA16+AB41-AB83 -> 0
B17: Centro distribuição | H17: =G17+H42-H84 -> 0 | I17: =H17+I42-I84 -> 0 | J17: =I17+J42-J84 -> 0 | K17: =J17+K42-K84 -> 0 | L17: =K17+L42-L84 -> 0 | M17: =L17+M42-M84 -> 0 | N17: =M17+N42-N84 -> 0 | O17: =N17+O42-O84 -> 0 | ... AB17: =AA17+AB42-AB84 -> 0
B18: Capex 7 | H18: =G18+H43-H85 -> 0 | I18: =H18+I43-I85 -> 0 | J18: =I18+J43-J85 -> 0 | K18: =J18+K43-K85 -> 0 | L18: =K18+L43-L85 -> 0 | M18: =L18+M43-M85 -> 0 | N18: =M18+N43-N85 -> 0 | O18: =N18+O43-O85 -> 0 | ... AB18: =AA18+AB43-AB85 -> 0
B19: Capex 8 | H19: =G19+H44-H86 -> 0 | I19: =H19+I44-I86 -> 0 | J19: =I19+J44-J86 -> 0 | K19: =J19+K44-K86 -> 0 | L19: =K19+L44-L86 -> 0 | M19: =L19+M44-M86 -> 0 | N19: =M19+N44-N86 -> 0 | O19: =N19+O44-O86 -> 0 | ... AB19: =AA19+AB44-AB86 -> 0
B20: Capex 9 | H20: =G20+H45-H87 -> 0 | I20: =H20+I45-I87 -> 0 | J20: =I20+J45-J87 -> 0 | K20: =J20+K45-K87 -> 0 | L20: =K20+L45-L87 -> 0 | M20: =L20+M45-M87 -> 0 | N20: =M20+N45-N87 -> 0 | O20: =N20+O45-O87 -> 0 | ... AB20: =AA20+AB45-AB87 -> 0
B21: Capex 10 | H21: =G21+H46-H88 -> 0 | I21: =H21+I46-I88 -> 0 | J21: =I21+J46-J88 -> 0 | K21: =J21+K46-K88 -> 0 | L21: =K21+L46-L88 -> 0 | M21: =L21+M46-M88 -> 0 | N21: =M21+N46-N88 -> 0 | O21: =N21+O46-O88 -> 0 | ... AB21: =AA21+AB46-AB88 -> 0
B22: Capex 11 | H22: =G22+H47-H89 -> 0 | I22: =H22+I47-I89 -> 0 | J22: =I22+J47-J89 -> 0 | K22: =J22+K47-K89 -> 0 | L22: =K22+L47-L89 -> 0 | M22: =L22+M47-M89 -> 0 | N22: =M22+N47-N89 -> 0 | O22: =N22+O47-O89 -> 0 | ... AB22: =AA22+AB47-AB89 -> 0
B24: Assets Amortization | G24: ='Balance Sheet'!I39 -> 0 | H24: =G24-H77 -> -28006.6 | I24: =H24-I77 -> -75870.343 | J24: =I24-J77 -> -139143.19 | K24: =J24-K77 -> -211455.02 | L24: =K24-L77 -> -294097.11 | M24: =L24-M77 -> -388545.21 | N24: =M24-N77 -> -496485.9 | O24: =N24-O77 -> -619846.68 | ... AB24: =AA24-AB77 -> -2267279.6
B26: INCOME STATEMENT ACCOUNTS
B28: Depreciation | H28: =H77 -> 28006.6 | I28: =I77 -> 47863.743 | J28: =J77 -> 63272.849 | K28: =K77 -> 72311.827 | L28: =L77 -> 82642.088 | M28: =M77 -> 94448.101 | N28: =N77 -> 107940.69 | O28: =O77 -> 123360.79 | ... AB28: =AB77 -> 126437.15
B30: CASH FLOW ACCOUNTS
B32: CapEx | H32: =H35 -> 139000 | I32: =I35 -> 107863.74 | J32: =J35 -> 63272.849 | K32: =K35 -> 72311.827 | L32: =L35 -> 82642.088 | M32: =M35 -> 94448.101 | N32: =N35 -> 107940.69 | O32: =O35 -> 123360.79 | ... AB32: =AB35 -> 126437.15
B33: Depreciation | H33: =H28 -> 28006.6 | I33: =I28 -> 47863.743 | J33: =J28 -> 63272.849 | K33: =K28 -> 72311.827 | L33: =L28 -> 82642.088 | M33: =M28 -> 94448.101 | N33: =N28 -> 107940.69 | O33: =O28 -> 123360.79 | ... AB33: =AB28 -> 126437.15
B35: CAPEX | H35: =SUM(H37:H47) -> 139000 | I35: =SUM(I37:I47) -> 107863.74 | J35: =SUM(J37:J47) -> 63272.849 | K35: =SUM(K37:K47) -> 72311.827 | L35: =SUM(L37:L47) -> 82642.088 | M35: =SUM(M37:M47) -> 94448.101 | N35: =SUM(N37:N47) -> 107940.69 | O35: =SUM(O37:O47) -> 123360.79 | ... AB35: =SUM(AB37:AB47) -> 126437.15
B37: =B12 -> Terrenos | H37: =CHOOSE($C$3,H104,H117,H130) -> 139000 | I37: =CHOOSE($C$3,I104,I117,I130) -> 107863.74 | J37: =CHOOSE($C$3,J104,J117,J130) -> 63272.849 | K37: =CHOOSE($C$3,K104,K117,K130) -> 72311.827 | L37: =CHOOSE($C$3,L104,L117,L130) -> 82642.088 | M37: =CHOOSE($C$3,M104,M117,M130) -> 94448.101 | N37: =CHOOSE($C$3,N104,N117,N130) -> 107940.69 | O37: =CHOOSE($C$3,O104,O117,O130) -> 123360.79 | ... AB37: =CHOOSE($C$3,AB104,AB117,AB130) -> 126437.15
B38: =B13 -> Edificações | H38: =CHOOSE($C$3,H105,H118,H131) -> 0 | I38: =CHOOSE($C$3,I105,I118,I131) -> 0 | J38: =CHOOSE($C$3,J105,J118,J131) -> 0 | K38: =CHOOSE($C$3,K105,K118,K131) -> 0 | L38: =CHOOSE($C$3,L105,L118,L131) -> 0 | M38: =CHOOSE($C$3,M105,M118,M131) -> 0 | N38: =CHOOSE($C$3,N105,N118,N131) -> 0 | O38: =CHOOSE($C$3,O105,O118,O131) -> 0 | ... AB38: =CHOOSE($C$3,AB105,AB118,AB131) -> 0
B39: =B14 -> Veículos | H39: =CHOOSE($C$3,H106,H119,H132) -> 0 | I39: =CHOOSE($C$3,I106,I119,I132) -> 0 | J39: =CHOOSE($C$3,J106,J119,J132) -> 0 | K39: =CHOOSE($C$3,K106,K119,K132) -> 0 | L39: =CHOOSE($C$3,L106,L119,L132) -> 0 | M39: =CHOOSE($C$3,M106,M119,M132) -> 0 | N39: =CHOOSE($C$3,N106,N119,N132) -> 0 | O39: =CHOOSE($C$3,O106,O119,O132) -> 0 | ... AB39: =CHOOSE($C$3,AB106,AB119,AB132) -> 0
B40: =B15 -> Máquinas e Equipamentos | H40: =CHOOSE($C$3,H107,H120,H133) -> 0 | I40: =CHOOSE($C$3,I107,I120,I133) -> 0 | J40: =CHOOSE($C$3,J107,J120,J133) -> 0 | K40: =CHOOSE($C$3,K107,K120,K133) -> 0 | L40: =CHOOSE($C$3,L107,L120,L133) -> 0 | M40: =CHOOSE($C$3,M107,M120,M133) -> 0 | N40: =CHOOSE($C$3,N107,N120,N133) -> 0 | O40: =CHOOSE($C$3,O107,O120,O133) -> 0 | ... AB40: =CHOOSE($C$3,AB107,AB120,AB133) -> 0
B41: =B16 -> Outros | H41: =CHOOSE($C$3,H108,H121,H134) -> 0 | I41: =CHOOSE($C$3,I108,I121,I134) -> 0 | J41: =CHOOSE($C$3,J108,J121,J134) -> 0 | K41: =CHOOSE($C$3,K108,K121,K134) -> 0 | L41: =CHOOSE($C$3,L108,L121,L134) -> 0 | M41: =CHOOSE($C$3,M108,M121,M134) -> 0 | N41: =CHOOSE($C$3,N108,N121,N134) -> 0 | O41: =CHOOSE($C$3,O108,O121,O134) -> 0 | ... AB41: =CHOOSE($C$3,AB108,AB121,AB134) -> 0
B42: =B17 -> Centro distribuição | H42: =CHOOSE($C$3,H109,H122,H135) -> 0 | I42: =CHOOSE($C$3,I109,I122,I135) -> 0 | J42: =CHOOSE($C$3,J109,J122,J135) -> 0 | K42: =CHOOSE($C$3,K109,K122,K135) -> 0 | L42: =CHOOSE($C$3,L109,L122,L135) -> 0 | M42: =CHOOSE($C$3,M109,M122,M135) -> 0 | N42: =CHOOSE($C$3,N109,N122,N135) -> 0 | O42: =CHOOSE($C$3,O109,O122,O135) -> 0 | ... AB42: =CHOOSE($C$3,AB109,AB122,AB135) -> 0
B43: =B18 -> Capex 7 | H43: =CHOOSE($C$3,H110,H123,H136) -> 0 | I43: =CHOOSE($C$3,I110,I123,I136) -> 0 | J43: =CHOOSE($C$3,J110,J123,J136) -> 0 | K43: =CHOOSE($C$3,K110,K123,K136) -> 0 | L43: =CHOOSE($C$3,L110,L123,L136) -> 0 | M43: =CHOOSE($C$3,M110,M123,M136) -> 0 | N43: =CHOOSE($C$3,N110,N123,N136) -> 0 | O43: =CHOOSE($C$3,O110,O123,O136) -> 0 | ... AB43: =CHOOSE($C$3,AB110,AB123,AB136) -> 0
B44: =B19 -> Capex 8 | H44: =CHOOSE($C$3,H111,H124,H137) -> 0 | I44: =CHOOSE($C$3,I111,I124,I137) -> 0 | J44: =CHOOSE($C$3,J111,J124,J137) -> 0 | K44: =CHOOSE($C$3,K111,K124,K137) -> 0 | L44: =CHOOSE($C$3,L111,L124,L137) -> 0 | M44: =CHOOSE($C$3,M111,M124,M137) -> 0 | N44: =CHOOSE($C$3,N111,N124,N137) -> 0 | O44: =CHOOSE($C$3,O111,O124,O137) -> 0 | ... AB44: =CHOOSE($C$3,AB111,AB124,AB137) -> 0
B45: =B20 -> Capex 9 | H45: =CHOOSE($C$3,H112,H125,H138) -> 0 | I45: =CHOOSE($C$3,I112,I125,I138) -> 0 | J45: =CHOOSE($C$3,J112,J125,J138) -> 0 | K45: =CHOOSE($C$3,K112,K125,K138) -> 0 | L45: =CHOOSE($C$3,L112,L125,L138) -> 0 | M45: =CHOOSE($C$3,M112,M125,M138) -> 0 | N45: =CHOOSE($C$3,N112,N125,N138) -> 0 | O45: =CHOOSE($C$3,O112,O125,O138) -> 0 | ... AB45: =CHOOSE($C$3,AB112,AB125,AB138) -> 0
B46: =B21 -> Capex 10 | H46: =CHOOSE($C$3,H113,H126,H139) -> 0 | I46: =CHOOSE($C$3,I113,I126,I139) -> 0 | J46: =CHOOSE($C$3,J113,J126,J139) -> 0 | K46: =CHOOSE($C$3,K113,K126,K139) -> 0 | L46: =CHOOSE($C$3,L113,L126,L139) -> 0 | M46: =CHOOSE($C$3,M113,M126,M139) -> 0 | N46: =CHOOSE($C$3,N113,N126,N139) -> 0 | O46: =CHOOSE($C$3,O113,O126,O139) -> 0 | ... AB46: =CHOOSE($C$3,AB113,AB126,AB139) -> 0
B47: =B22 -> Capex 11 | H47: =CHOOSE($C$3,H114,H127,H140) -> 0 | I47: =CHOOSE($C$3,I114,I127,I140) -> 0 | J47: =CHOOSE($C$3,J114,J127,J140) -> 0 | K47: =CHOOSE($C$3,K114,K127,K140) -> 0 | L47: =CHOOSE($C$3,L114,L127,L140) -> 0 | M47: =CHOOSE($C$3,M114,M127,M140) -> 0 | N47: =CHOOSE($C$3,N114,N127,N140) -> 0 | O47: =CHOOSE($C$3,O114,O127,O140) -> 0 | ... AB47: =CHOOSE($C$3,AB114,AB127,AB140) -> 0
B49: DEPRECIAÇÂO CAPEX | G49: Tempo de depreciação (anos)
B51: =B37 -> Terrenos | G51: 7 | H51: =SUM(OFFSET(H37,0,IF(H$6>$G51,-$G51,-H$6),1,IF(H$6>$G51,$G51,H$6)))*(1/$G51) -> 0 | I51: =SUM(OFFSET(I37,0,IF(I$6>$G51,-$G51,-I$6),1,IF(I$6>$G51,$G51,I$6)))*(1/$G51) -> 19857.143 | J51: =SUM(OFFSET(J37,0,IF(J$6>$G51,-$G51,-J$6),1,IF(J$6>$G51,$G51,J$6)))*(1/$G51) -> 35266.249 | K51: =SUM(OFFSET(K37,0,IF(K$6>$G51,-$G51,-K$6),1,IF(K$6>$G51,$G51,K$6)))*(1/$G51) -> 44305.227 | L51: =SUM(OFFSET(L37,0,IF(L$6>$G51,-$G51,-L$6),1,IF(L$6>$G51,$G51,L$6)))*(1/$G51) -> 54635.488 | M51: =SUM(OFFSET(M37,0,IF(M$6>$G51,-$G51,-M$6),1,IF(M$6>$G51,$G51,M$6)))*(1/$G51) -> 66441.501 | N51: =SUM(OFFSET(N37,0,IF(N$6>$G51,-$G51,-N$6),1,IF(N$6>$G51,$G51,N$6)))*(1/$G51) -> 79934.087 | O51: =SUM(OFFSET(O37,0,IF(O$6>$G51,-$G51,-O$6),1,IF(O$6>$G51,$G51,O$6)))*(1/$G51) -> 95354.185 | ... AB51: =SUM(OFFSET(AB37,0,IF(AB$6>$G51,-$G51,-AB$6),1,IF(AB$6>$G51,$G51,AB$6)))*(1/$G51) -> 126437.15
B52: =B38 -> Edificações | G52: 10 | H52: =SUM(OFFSET(H38,0,IF(H$6>$G52,-$G52,-H$6),1,IF(H$6>$G52,$G52,H$6)))*(1/$G52) -> 0 | I52: =SUM(OFFSET(I38,0,IF(I$6>$G52,-$G52,-I$6),1,IF(I$6>$G52,$G52,I$6)))*(1/$G52) -> 0 | J52: =SUM(OFFSET(J38,0,IF(J$6>$G52,-$G52,-J$6),1,IF(J$6>$G52,$G52,J$6)))*(1/$G52) -> 0 | K52: =SUM(OFFSET(K38,0,IF(K$6>$G52,-$G52,-K$6),1,IF(K$6>$G52,$G52,K$6)))*(1/$G52) -> 0 | L52: =SUM(OFFSET(L38,0,IF(L$6>$G52,-$G52,-L$6),1,IF(L$6>$G52,$G52,L$6)))*(1/$G52) -> 0 | M52: =SUM(OFFSET(M38,0,IF(M$6>$G52,-$G52,-M$6),1,IF(M$6>$G52,$G52,M$6)))*(1/$G52) -> 0 | N52: =SUM(OFFSET(N38,0,IF(N$6>$G52,-$G52,-N$6),1,IF(N$6>$G52,$G52,N$6)))*(1/$G52) -> 0 | O52: =SUM(OFFSET(O38,0,IF(O$6>$G52,-$G52,-O$6),1,IF(O$6>$G52,$G52,O$6)))*(1/$G52) -> 0 | ... AB52: =SUM(OFFSET(AB38,0,IF(AB$6>$G52,-$G52,-AB$6),1,IF(AB$6>$G52,$G52,AB$6)))*(1/$G52) -> 0
B53: =B39 -> Veículos | G53: 10 | H53: =SUM(OFFSET(H39,0,IF(H$6>$G53,-$G53,-H$6),1,IF(H$6>$G53,$G53,H$6)))*(1/$G53) -> 0 | I53: =SUM(OFFSET(I39,0,IF(I$6>$G53,-$G53,-I$6),1,IF(I$6>$G53,$G53,I$6)))*(1/$G53) -> 0 | J53: =SUM(OFFSET(J39,0,IF(J$6>$G53,-$G53,-J$6),1,IF(J$6>$G53,$G53,J$6)))*(1/$G53) -> 0 | K53: =SUM(OFFSET(K39,0,IF(K$6>$G53,-$G53,-K$6),1,IF(K$6>$G53,$G53,K$6)))*(1/$G53) -> 0 | L53: =SUM(OFFSET(L39,0,IF(L$6>$G53,-$G53,-L$6),1,IF(L$6>$G53,$G53,L$6)))*(1/$G53) -> 0 | M53: =SUM(OFFSET(M39,0,IF(M$6>$G53,-$G53,-M$6),1,IF(M$6>$G53,$G53,M$6)))*(1/$G53) -> 0 | N53: =SUM(OFFSET(N39,0,IF(N$6>$G53,-$G53,-N$6),1,IF(N$6>$G53,$G53,N$6)))*(1/$G53) -> 0 | O53: =SUM(OFFSET(O39,0,IF(O$6>$G53,-$G53,-O$6),1,IF(O$6>$G53,$G53,O$6)))*(1/$G53) -> 0 | ... AB53: =SUM(OFFSET(AB39,0,IF(AB$6>$G53,-$G53,-AB$6),1,IF(AB$6>$G53,$G53,AB$6)))*(1/$G53) -> 0
B54: =B40 -> Máquinas e Equipamentos | G54: 10 | H54: =SUM(OFFSET(H40,0,IF(H$6>$G54,-$G54,-H$6),1,IF(H$6>$G54,$G54,H$6)))*(1/$G54) -> 0 | I54: =SUM(OFFSET(I40,0,IF(I$6>$G54,-$G54,-I$6),1,IF(I$6>$G54,$G54,I$6)))*(1/$G54) -> 0 | J54: =SUM(OFFSET(J40,0,IF(J$6>$G54,-$G54,-J$6),1,IF(J$6>$G54,$G54,J$6)))*(1/$G54) -> 0 | K54: =SUM(OFFSET(K40,0,IF(K$6>$G54,-$G54,-K$6),1,IF(K$6>$G54,$G54,K$6)))*(1/$G54) -> 0 | L54: =SUM(OFFSET(L40,0,IF(L$6>$G54,-$G54,-L$6),1,IF(L$6>$G54,$G54,L$6)))*(1/$G54) -> 0 | M54: =SUM(OFFSET(M40,0,IF(M$6>$G54,-$G54,-M$6),1,IF(M$6>$G54,$G54,M$6)))*(1/$G54) -> 0 | N54: =SUM(OFFSET(N40,0,IF(N$6>$G54,-$G54,-N$6),1,IF(N$6>$G54,$G54,N$6)))*(1/$G54) -> 0 | O54: =SUM(OFFSET(O40,0,IF(O$6>$G54,-$G54,-O$6),1,IF(O$6>$G54,$G54,O$6)))*(1/$G54) -> 0 | ... AB54: =SUM(OFFSET(AB40,0,IF(AB$6>$G54,-$G54,-AB$6),1,IF(AB$6>$G54,$G54,AB$6)))*(1/$G54) -> 0
B55: =B41 -> Outros | G55: 10 | H55: =SUM(OFFSET(H41,0,IF(H$6>$G55,-$G55,-H$6),1,IF(H$6>$G55,$G55,H$6)))*(1/$G55) -> 0 | I55: =SUM(OFFSET(I41,0,IF(I$6>$G55,-$G55,-I$6),1,IF(I$6>$G55,$G55,I$6)))*(1/$G55) -> 0 | J55: =SUM(OFFSET(J41,0,IF(J$6>$G55,-$G55,-J$6),1,IF(J$6>$G55,$G55,J$6)))*(1/$G55) -> 0 | K55: =SUM(OFFSET(K41,0,IF(K$6>$G55,-$G55,-K$6),1,IF(K$6>$G55,$G55,K$6)))*(1/$G55) -> 0 | L55: =SUM(OFFSET(L41,0,IF(L$6>$G55,-$G55,-L$6),1,IF(L$6>$G55,$G55,L$6)))*(1/$G55) -> 0 | M55: =SUM(OFFSET(M41,0,IF(M$6>$G55,-$G55,-M$6),1,IF(M$6>$G55,$G55,M$6)))*(1/$G55) -> 0 | N55: =SUM(OFFSET(N41,0,IF(N$6>$G55,-$G55,-N$6),1,IF(N$6>$G55,$G55,N$6)))*(1/$G55) -> 0 | O55: =SUM(OFFSET(O41,0,IF(O$6>$G55,-$G55,-O$6),1,IF(O$6>$G55,$G55,O$6)))*(1/$G55) -> 0 | ... AB55: =SUM(OFFSET(AB41,0,IF(AB$6>$G55,-$G55,-AB$6),1,IF(AB$6>$G55,$G55,AB$6)))*(1/$G55) -> 0
B56: =B42 -> Centro distribuição | G56: 10 | H56: =SUM(OFFSET(H42,0,IF(H$6>$G56,-$G56,-H$6),1,IF(H$6>$G56,$G56,H$6)))*(1/$G56) -> 0 | I56: =SUM(OFFSET(I42,0,IF(I$6>$G56,-$G56,-I$6),1,IF(I$6>$G56,$G56,I$6)))*(1/$G56) -> 0 | J56: =SUM(OFFSET(J42,0,IF(J$6>$G56,-$G56,-J$6),1,IF(J$6>$G56,$G56,J$6)))*(1/$G56) -> 0 | K56: =SUM(OFFSET(K42,0,IF(K$6>$G56,-$G56,-K$6),1,IF(K$6>$G56,$G56,K$6)))*(1/$G56) -> 0 | L56: =SUM(OFFSET(L42,0,IF(L$6>$G56,-$G56,-L$6),1,IF(L$6>$G56,$G56,L$6)))*(1/$G56) -> 0 | M56: =SUM(OFFSET(M42,0,IF(M$6>$G56,-$G56,-M$6),1,IF(M$6>$G56,$G56,M$6)))*(1/$G56) -> 0 | N56: =SUM(OFFSET(N42,0,IF(N$6>$G56,-$G56,-N$6),1,IF(N$6>$G56,$G56,N$6)))*(1/$G56) -> 0 | O56: =SUM(OFFSET(O42,0,IF(O$6>$G56,-$G56,-O$6),1,IF(O$6>$G56,$G56,O$6)))*(1/$G56) -> 0 | ... AB56: =SUM(OFFSET(AB42,0,IF(AB$6>$G56,-$G56,-AB$6),1,IF(AB$6>$G56,$G56,AB$6)))*(1/$G56) -> 0
B57: =B43 -> Capex 7 | G57: 1 | H57: =SUM(OFFSET(H43,0,IF(H$6>$G57,-$G57,-H$6),1,IF(H$6>$G57,$G57,H$6)))*(1/$G57) -> 0 | I57: =SUM(OFFSET(I43,0,IF(I$6>$G57,-$G57,-I$6),1,IF(I$6>$G57,$G57,I$6)))*(1/$G57) -> 0 | J57: =SUM(OFFSET(J43,0,IF(J$6>$G57,-$G57,-J$6),1,IF(J$6>$G57,$G57,J$6)))*(1/$G57) -> 0 | K57: =SUM(OFFSET(K43,0,IF(K$6>$G57,-$G57,-K$6),1,IF(K$6>$G57,$G57,K$6)))*(1/$G57) -> 0 | L57: =SUM(OFFSET(L43,0,IF(L$6>$G57,-$G57,-L$6),1,IF(L$6>$G57,$G57,L$6)))*(1/$G57) -> 0 | M57: =SUM(OFFSET(M43,0,IF(M$6>$G57,-$G57,-M$6),1,IF(M$6>$G57,$G57,M$6)))*(1/$G57) -> 0 | N57: =SUM(OFFSET(N43,0,IF(N$6>$G57,-$G57,-N$6),1,IF(N$6>$G57,$G57,N$6)))*(1/$G57) -> 0 | O57: =SUM(OFFSET(O43,0,IF(O$6>$G57,-$G57,-O$6),1,IF(O$6>$G57,$G57,O$6)))*(1/$G57) -> 0 | ... AB57: =SUM(OFFSET(AB43,0,IF(AB$6>$G57,-$G57,-AB$6),1,IF(AB$6>$G57,$G57,AB$6)))*(1/$G57) -> 0
B58: =B44 -> Capex 8 | G58: 1 | H58: =SUM(OFFSET(H44,0,IF(H$6>$G58,-$G58,-H$6),1,IF(H$6>$G58,$G58,H$6)))*(1/$G58) -> 0 | I58: =SUM(OFFSET(I44,0,IF(I$6>$G58,-$G58,-I$6),1,IF(I$6>$G58,$G58,I$6)))*(1/$G58) -> 0 | J58: =SUM(OFFSET(J44,0,IF(J$6>$G58,-$G58,-J$6),1,IF(J$6>$G58,$G58,J$6)))*(1/$G58) -> 0 | K58: =SUM(OFFSET(K44,0,IF(K$6>$G58,-$G58,-K$6),1,IF(K$6>$G58,$G58,K$6)))*(1/$G58) -> 0 | L58: =SUM(OFFSET(L44,0,IF(L$6>$G58,-$G58,-L$6),1,IF(L$6>$G58,$G58,L$6)))*(1/$G58) -> 0 | M58: =SUM(OFFSET(M44,0,IF(M$6>$G58,-$G58,-M$6),1,IF(M$6>$G58,$G58,M$6)))*(1/$G58) -> 0 | N58: =SUM(OFFSET(N44,0,IF(N$6>$G58,-$G58,-N$6),1,IF(N$6>$G58,$G58,N$6)))*(1/$G58) -> 0 | O58: =SUM(OFFSET(O44,0,IF(O$6>$G58,-$G58,-O$6),1,IF(O$6>$G58,$G58,O$6)))*(1/$G58) -> 0 | ... AB58: =SUM(OFFSET(AB44,0,IF(AB$6>$G58,-$G58,-AB$6),1,IF(AB$6>$G58,$G58,AB$6)))*(1/$G58) -> 0
B59: =B45 -> Capex 9 | G59: 1 | H59: =SUM(OFFSET(H45,0,IF(H$6>$G59,-$G59,-H$6),1,IF(H$6>$G59,$G59,H$6)))*(1/$G59) -> 0 | I59: =SUM(OFFSET(I45,0,IF(I$6>$G59,-$G59,-I$6),1,IF(I$6>$G59,$G59,I$6)))*(1/$G59) -> 0 | J59: =SUM(OFFSET(J45,0,IF(J$6>$G59,-$G59,-J$6),1,IF(J$6>$G59,$G59,J$6)))*(1/$G59) -> 0 | K59: =SUM(OFFSET(K45,0,IF(K$6>$G59,-$G59,-K$6),1,IF(K$6>$G59,$G59,K$6)))*(1/$G59) -> 0 | L59: =SUM(OFFSET(L45,0,IF(L$6>$G59,-$G59,-L$6),1,IF(L$6>$G59,$G59,L$6)))*(1/$G59) -> 0 | M59: =SUM(OFFSET(M45,0,IF(M$6>$G59,-$G59,-M$6),1,IF(M$6>$G59,$G59,M$6)))*(1/$G59) -> 0 | N59: =SUM(OFFSET(N45,0,IF(N$6>$G59,-$G59,-N$6),1,IF(N$6>$G59,$G59,N$6)))*(1/$G59) -> 0 | O59: =SUM(OFFSET(O45,0,IF(O$6>$G59,-$G59,-O$6),1,IF(O$6>$G59,$G59,O$6)))*(1/$G59) -> 0 | ... AB59: =SUM(OFFSET(AB45,0,IF(AB$6>$G59,-$G59,-AB$6),1,IF(AB$6>$G59,$G59,AB$6)))*(1/$G59) -> 0
B60: =B46 -> Capex 10 | G60: 1 | H60: =SUM(OFFSET(H46,0,IF(H$6>$G60,-$G60,-H$6),1,IF(H$6>$G60,$G60,H$6)))*(1/$G60) -> 0 | I60: =SUM(OFFSET(I46,0,IF(I$6>$G60,-$G60,-I$6),1,IF(I$6>$G60,$G60,I$6)))*(1/$G60) -> 0 | J60: =SUM(OFFSET(J46,0,IF(J$6>$G60,-$G60,-J$6),1,IF(J$6>$G60,$G60,J$6)))*(1/$G60) -> 0 | K60: =SUM(OFFSET(K46,0,IF(K$6>$G60,-$G60,-K$6),1,IF(K$6>$G60,$G60,K$6)))*(1/$G60) -> 0 | L60: =SUM(OFFSET(L46,0,IF(L$6>$G60,-$G60,-L$6),1,IF(L$6>$G60,$G60,L$6)))*(1/$G60) -> 0 | M60: =SUM(OFFSET(M46,0,IF(M$6>$G60,-$G60,-M$6),1,IF(M$6>$G60,$G60,M$6)))*(1/$G60) -> 0 | N60: =SUM(OFFSET(N46,0,IF(N$6>$G60,-$G60,-N$6),1,IF(N$6>$G60,$G60,N$6)))*(1/$G60) -> 0 | O60: =SUM(OFFSET(O46,0,IF(O$6>$G60,-$G60,-O$6),1,IF(O$6>$G60,$G60,O$6)))*(1/$G60) -> 0 | ... AB60: =SUM(OFFSET(AB46,0,IF(AB$6>$G60,-$G60,-AB$6),1,IF(AB$6>$G60,$G60,AB$6)))*(1/$G60) -> 0
B61: =B47 -> Capex 11 | G61: 1 | H61: =SUM(OFFSET(H47,0,IF(H$6>$G61,-$G61,-H$6),1,IF(H$6>$G61,$G61,H$6)))*(1/$G61) -> 0 | I61: =SUM(OFFSET(I47,0,IF(I$6>$G61,-$G61,-I$6),1,IF(I$6>$G61,$G61,I$6)))*(1/$G61) -> 0 | J61: =SUM(OFFSET(J47,0,IF(J$6>$G61,-$G61,-J$6),1,IF(J$6>$G61,$G61,J$6)))*(1/$G61) -> 0 | K61: =SUM(OFFSET(K47,0,IF(K$6>$G61,-$G61,-K$6),1,IF(K$6>$G61,$G61,K$6)))*(1/$G61) -> 0 | L61: =SUM(OFFSET(L47,0,IF(L$6>$G61,-$G61,-L$6),1,IF(L$6>$G61,$G61,L$6)))*(1/$G61) -> 0 | M61: =SUM(OFFSET(M47,0,IF(M$6>$G61,-$G61,-M$6),1,IF(M$6>$G61,$G61,M$6)))*(1/$G61) -> 0 | N61: =SUM(OFFSET(N47,0,IF(N$6>$G61,-$G61,-N$6),1,IF(N$6>$G61,$G61,N$6)))*(1/$G61) -> 0 | O61: =SUM(OFFSET(O47,0,IF(O$6>$G61,-$G61,-O$6),1,IF(O$6>$G61,$G61,O$6)))*(1/$G61) -> 0 | ... AB61: =SUM(OFFSET(AB47,0,IF(AB$6>$G61,-$G61,-AB$6),1,IF(AB$6>$G61,$G61,AB$6)))*(1/$G61) -> 0
B63: DEPRECIAÇÂO HISTÒRICA | G63: Tempo de depreciação (anos)
H64: 0.85964781 | I64: =SUM(H65:O65)-G65 -> 224042.8
B65: =B51 -> Terrenos | F65: ='Balance Sheet'!I37+'Balance Sheet'!I39+'Balance Sheet'!I38 -> 280066 | G65: 10 | H65: =F65/G65 -> 28006.6 | I65: =H65 -> 28006.6 | J65: =I65 -> 28006.6 | K65: =J65 -> 28006.6 | L65: =K65 -> 28006.6 | M65: =L65 -> 28006.6 | N65: =M65 -> 28006.6 | O65: =N65 -> 28006.6 | P65: =O65 -> 28006.6 | ... S65: =R65 -> 28006.6 | W65: 0 | X65: 0 | Y65: 0 | Z65: 0 | AA65: 0 | AB65: 0
B66: =B52 -> Edificações | G66: 0
B67: =B53 -> Veículos | G67: 0
B68: =B54 -> Máquinas e Equipamentos | G68: 0
B69: =B55 -> Outros | G69: 0
B70: =B56 -> Centro distribuição | G70: 0
B71: =B57 -> Capex 7 | G71: 0
B72: =B58 -> Capex 8 | G72: 0
B73: =B59 -> Capex 9 | G73: 0
B74: =B60 -> Capex 10 | G74: 0
B75: =B61 -> Capex 11 | G75: 0
I76: =50298-39492 -> 10806 | J76: =56550-48555 -> 7995 | K76: =52346-52264 -> 82
B77: DEPRECIAÇÂO TOTAL | G77: Tempo de depreciação (anos) | H77: =SUM(H79:H89) -> 28006.6 | I77: =SUM(I79:I89) -> 47863.743 | J77: =SUM(J79:J89) -> 63272.849 | K77: =SUM(K79:K89) -> 72311.827 | L77: =SUM(L79:L89) -> 82642.088 | M77: =SUM(M79:M89) -> 94448.101 | N77: =SUM(N79:N89) -> 107940.69 | O77: =SUM(O79:O89) -> 123360.79 | ... AB77: =SUM(AB79:AB89) -> 126437.15
B79: =B65 -> Terrenos | H79: =H65+H51 -> 28006.6 | I79: =I65+I51 -> 47863.743 | J79: =J65+J51 -> 63272.849 | K79: =K65+K51 -> 72311.827 | L79: =L65+L51 -> 82642.088 | M79: =M65+M51 -> 94448.101 | N79: =N65+N51 -> 107940.69 | O79: =O65+O51 -> 123360.79 | ... AB79: =AB65+AB51 -> 126437.15
B80: =B66 -> Edificações | H80: =H66+H52 -> 0 | I80: =I66+I52 -> 0 | J80: =J66+J52 -> 0 | K80: =K66+K52 -> 0 | L80: =L66+L52 -> 0 | M80: =M66+M52 -> 0 | N80: =N66+N52 -> 0 | O80: =O66+O52 -> 0 | ... AB80: =AB66+AB52 -> 0
B81: =B67 -> Veículos | H81: =H67+H53 -> 0 | I81: =I67+I53 -> 0 | J81: =J67+J53 -> 0 | K81: =K67+K53 -> 0 | L81: =L67+L53 -> 0 | M81: =M67+M53 -> 0 | N81: =N67+N53 -> 0 | O81: =O67+O53 -> 0 | ... AB81: =AB67+AB53 -> 0
B82: =B68 -> Máquinas e Equipamentos | H82: =H68+H54 -> 0 | I82: =I68+I54 -> 0 | J82: =J68+J54 -> 0 | K82: =K68+K54 -> 0 | L82: =L68+L54 -> 0 | M82: =M68+M54 -> 0 | N82: =N68+N54 -> 0 | O82: =O68+O54 -> 0 | ... AB82: =AB68+AB54 -> 0
B83: =B69 -> Outros | H83: =H69+H55 -> 0 | I83: =I69+I55 -> 0 | J83: =J69+J55 -> 0 | K83: =K69+K55 -> 0 | L83: =L69+L55 -> 0 | M83: =M69+M55 -> 0 | N83: =N69+N55 -> 0 | O83: =O69+O55 -> 0 | ... AB83: =AB69+AB55 -> 0
B84: =B70 -> Centro distribuição | H84: =H70+H56 -> 0 | I84: =I70+I56 -> 0 | J84: =J70+J56 -> 0 | K84: =K70+K56 -> 0 | L84: =L70+L56 -> 0 | M84: =M70+M56 -> 0 | N84: =N70+N56 -> 0 | O84: =O70+O56 -> 0 | ... AB84: =AB70+AB56 -> 0
B85: =B71 -> Capex 7 | H85: =H71+H57 -> 0 | I85: =I71+I57 -> 0 | J85: =J71+J57 -> 0 | K85: =K71+K57 -> 0 | L85: =L71+L57 -> 0 | M85: =M71+M57 -> 0 | N85: =N71+N57 -> 0 | O85: =O71+O57 -> 0 | ... AB85: =AB71+AB57 -> 0
B86: =B72 -> Capex 8 | H86: =H72+H58 -> 0 | I86: =I72+I58 -> 0 | J86: =J72+J58 -> 0 | K86: =K72+K58 -> 0 | L86: =L72+L58 -> 0 | M86: =M72+M58 -> 0 | N86: =N72+N58 -> 0 | O86: =O72+O58 -> 0 | ... AB86: =AB72+AB58 -> 0
B87: =B73 -> Capex 9 | H87: =H73+H59 -> 0 | I87: =I73+I59 -> 0 | J87: =J73+J59 -> 0 | K87: =K73+K59 -> 0 | L87: =L73+L59 -> 0 | M87: =M73+M59 -> 0 | N87: =N73+N59 -> 0 | O87: =O73+O59 -> 0 | ... AB87: =AB73+AB59 -> 0
B88: =B74 -> Capex 10 | H88: =H74+H60 -> 0 | I88: =I74+I60 -> 0 | J88: =J74+J60 -> 0 | K88: =K74+K60 -> 0 | L88: =L74+L60 -> 0 | M88: =M74+M60 -> 0 | N88: =N74+N60 -> 0 | O88: =O74+O60 -> 0 | ... AB88: =AB74+AB60 -> 0
B89: =B75 -> Capex 11 | H89: =H75+H61 -> 0 | I89: =I75+I61 -> 0 | J89: =J75+J61 -> 0 | K89: =K75+K61 -> 0 | L89: =L75+L61 -> 0 | M89: =M75+M61 -> 0 | N89: =N75+N61 -> 0 | O89: =O75+O61 -> 0 | ... AB89: =AB75+AB61 -> 0
B91: Avaliação Patrimonial
B92: Total Dep. Expense | H92: =IF(G92-($G93*$G92)<0,0,G92-($G93*$G92)) -> 0 | I92: =IF(H92-($G93*$G92)<0,0,H92-($G93*$G92)) -> 0 | J92: =IF(I92-($G93*$G92)<0,0,I92-($G93*$G92)) -> 0 | K92: =IF(J92-($G93*$G92)<0,0,J92-($G93*$G92)) -> 0 | L92: =IF(K92-($G93*$G92)<0,0,K92-($G93*$G92)) -> 0 | M92: =IF(L92-($G93*$G92)<0,0,L92-($G93*$G92)) -> 0 | N92: =IF(M92-($G93*$G92)<0,0,M92-($G93*$G92)) -> 0 | O92: =IF(N92-($G93*$G92)<0,0,N92-($G93*$G92)) -> 0 | ... AB92: =IF(AA92-($G93*$G92)<0,0,AA92-($G93*$G92)) -> 0
B93: % por ano | G93: 0.1
B96: Diferidos
B97: Prazo Amortização | G97: 8 | H97: =SUM(OFFSET(H83,0,IF(H$6>$G97,-$G97,-H$6),1,IF(H$6>$G97,$G97,H$6)))*(1/$G97) -> 0 | I97: =SUM(OFFSET(I83,0,IF(I$6>$G97,-$G97,-I$6),1,IF(I$6>$G97,$G97,I$6)))*(1/$G97) -> 0 | J97: =SUM(OFFSET(J83,0,IF(J$6>$G97,-$G97,-J$6),1,IF(J$6>$G97,$G97,J$6)))*(1/$G97) -> 0 | K97: =SUM(OFFSET(K83,0,IF(K$6>$G97,-$G97,-K$6),1,IF(K$6>$G97,$G97,K$6)))*(1/$G97) -> 0 | L97: =SUM(OFFSET(L83,0,IF(L$6>$G97,-$G97,-L$6),1,IF(L$6>$G97,$G97,L$6)))*(1/$G97) -> 0 | M97: =SUM(OFFSET(M83,0,IF(M$6>$G97,-$G97,-M$6),1,IF(M$6>$G97,$G97,M$6)))*(1/$G97) -> 0 | N97: =SUM(OFFSET(N83,0,IF(N$6>$G97,-$G97,-N$6),1,IF(N$6>$G97,$G97,N$6)))*(1/$G97) -> 0 | O97: =SUM(OFFSET(O83,0,IF(O$6>$G97,-$G97,-O$6),1,IF(O$6>$G97,$G97,O$6)))*(1/$G97) -> 0 | ... AB97: =SUM(OFFSET(AB83,0,IF(AB$6>$G97,-$G97,-AB$6),1,IF(AB$6>$G97,$G97,AB$6)))*(1/$G97) -> 0
B98: Ágio Gerado | G98: 500000
B101: NEW CAPEX
H102: 0.52863
B103: =B2 -> Base Case | H103: =AVERAGE(H104:N104) -> 95354.185
B104: =B12 -> Terrenos | H104: 139000 | I104: =I28+60000 -> 107863.74 | J104: =J28 -> 63272.849 | K104: =K28 -> 72311.827 | L104: =L28 -> 82642.088 | M104: =M28 -> 94448.101 | N104: =N28 -> 107940.69 | O104: =O28 -> 123360.79 | P104: =P28 -> 121126.61 | Q104: =Q28 -> 123021.31 | ... AB104: =AB28 -> 126437.15
B105: =B13 -> Edificações | S105: 0 | T105: 0 | U105: 0 | V105: 0 | W105: 0 | X105: 0 | Y105: 0 | Z105: 0 | AA105: 0 | AB105: 0
B106: =B14 -> Veículos | H106: 0 | I106: 0 | J106: 0 | K106: 0 | L106: 0 | M106: 0 | N106: 0 | O106: 0 | P106: 0 | Q106: 0 | R106: 0 | S106: 0 | T106: 0 | U106: 0 | V106: 0 | W106: 0 | X106: 0 | Y106: 0 | Z106: 0 | AA106: 0 | AB106: 0
B107: =B15 -> Máquinas e Equipamentos | H107: 0 | I107: 0 | J107: 0 | K107: 0 | L107: 0 | M107: 0 | N107: 0 | O107: 0 | P107: 0 | Q107: 0 | R107: 0 | S107: 0 | T107: 0 | U107: 0 | V107: 0 | W107: 0 | X107: 0 | Y107: 0 | Z107: 0 | AA107: 0 | AB107: 0
B108: =B16 -> Outros | H108: 0 | I108: 0 | J108: 0 | K108: 0 | L108: 0 | M108: 0 | N108: 0 | O108: 0 | P108: 0 | Q108: 0 | R108: 0 | S108: 0 | T108: 0 | U108: 0 | V108: 0 | W108: 0 | X108: 0 | Y108: 0 | Z108: 0 | AA108: 0 | AB108: 0
B109: =B17 -> Centro distribuição | H109: 0 | I109: 0 | J109: 0 | K109: 0 | L109: 0 | M109: 0 | N109: 0 | O109: 0 | P109: 0 | Q109: 0 | R109: 0 | S109: 0 | T109: 0 | U109: 0 | V109: 0 | W109: 0 | X109: 0 | Y109: 0 | Z109: 0 | AA109: 0 | AB109: 0
B110: =B18 -> Capex 7 | H110: 0 | I110: 0 | J110: 0 | K110: 0 | L110: 0 | M110: 0 | N110: 0 | O110: 0 | P110: 0 | Q110: 0 | R110: 0 | S110: 0 | T110: 0 | U110: 0 | V110: 0 | W110: 0 | X110: 0 | Y110: 0 | Z110: 0 | AA110: 0 | AB110: 0
B111: =B19 -> Capex 8 | H111: 0 | I111: 0 | J111: 0 | K111: 0 | L111: 0 | M111: 0 | N111: 0 | O111: 0 | P111: 0 | Q111: 0 | R111: 0 | S111: 0 | T111: 0 | U111: 0 | V111: 0 | W111: 0 | X111: 0 | Y111: 0 | Z111: 0 | AA111: 0 | AB111: 0
B112: =B20 -> Capex 9 | H112: 0 | I112: 0 | J112: 0 | K112: 0 | L112: 0 | M112: 0 | N112: 0 | O112: 0 | P112: 0 | Q112: 0 | R112: 0 | S112: 0 | T112: 0 | U112: 0 | V112: 0 | W112: 0 | X112: 0 | Y112: 0 | Z112: 0 | AA112: 0 | AB112: 0
B113: =B21 -> Capex 10 | H113: 0 | I113: 0 | J113: 0 | K113: 0 | L113: 0 | M113: 0 | N113: 0 | O113: 0 | P113: 0 | Q113: 0 | R113: 0 | S113: 0 | T113: 0 | U113: 0 | V113: 0 | W113: 0 | X113: 0 | Y113: 0 | Z113: 0 | AA113: 0 | AB113: 0
B114: =B22 -> Capex 11 | H114: 0 | I114: 0 | J114: 0 | K114: 0 | L114: 0 | M114: 0 | N114: 0 | O114: 0 | P114: 0 | Q114: 0 | R114: 0 | S114: 0 | T114: 0 | U114: 0 | V114: 0 | W114: 0 | X114: 0 | Y114: 0 | Z114: 0 | AA114: 0 | AB114: 0
H115: =SUM(H104:H114) -> 139000 | I115: =SUM(I104:I114) -> 107863.74 | J115: =SUM(J104:J114) -> 63272.849 | K115: =SUM(K104:K114) -> 72311.827 | L115: =SUM(L104:L114) -> 82642.088 | M115: =SUM(M104:M114) -> 94448.101 | N115: =SUM(N104:N114) -> 107940.69 | O115: =SUM(O104:O114) -> 123360.79 | ... R115: =SUM(R104:R114) -> 131556.8
B116: =B3 -> Client Case
B117: =B12 -> Terrenos | H117: =H104 -> 139000 | I117: =I104 -> 107863.74 | J117: =J104 -> 63272.849 | K117: =K104 -> 72311.827 | L117: =L104 -> 82642.088 | M117: =M104 -> 94448.101 | N117: =N104 -> 107940.69 | O117: =O104 -> 123360.79 | ... AB117: =AB104 -> 126437.15
B118: =B13 -> Edificações | H118: =H105 -> 0 | I118: =I105 -> 0 | J118: =J105 -> 0 | K118: =K105 -> 0 | L118: =L105 -> 0 | M118: =M105 -> 0 | N118: =N105 -> 0 | O118: =O105 -> 0 | ... AB118: =AB105 -> 0
B119: =B14 -> Veículos | H119: =H106 -> 0 | I119: =I106 -> 0 | J119: =J106 -> 0 | K119: =K106 -> 0 | L119: =L106 -> 0 | M119: =M106 -> 0 | N119: =N106 -> 0 | O119: =O106 -> 0 | ... AB119: =AB106 -> 0
B120: =B15 -> Máquinas e Equipamentos | H120: =H107 -> 0 | I120: =I107 -> 0 | J120: =J107 -> 0 | K120: =K107 -> 0 | L120: =L107 -> 0 | M120: =M107 -> 0 | N120: =N107 -> 0 | O120: =O107 -> 0 | ... AB120: =AB107 -> 0
...

Sheet Cash Flow
H5: ='Balance Sheet'!J83 -> 0 | I5: ='Balance Sheet'!K83 -> 0 | J5: ='Balance Sheet'!L83 -> 0 | K5: ='Balance Sheet'!M83 -> 0 | L5: ='Balance Sheet'!N83 -> 0 | M5: ='Balance Sheet'!O83 -> 0 | N5: ='Balance Sheet'!P83 -> 0 | O5: ='Balance Sheet'!Q83 -> 0 | ... Q5: ='Balance Sheet'!S83 -> 16987
B7: CASH FLOW | D7: ='Revenues, COGS & SG&A'!E7 -> 39813 | E7: ='Revenues, COGS & SG&A'!F7 -> 40178 | F7: ='Revenues, COGS & SG&A'!G7 -> 40543 | G7: ='Revenues, COGS & SG&A'!H7 -> 40908 | H7: ='Revenues, COGS & SG&A'!I7 -> 41274 | I7: ='Revenues, COGS & SG&A'!J7 -> 41639 | J7: ='Revenues, COGS & SG&A'!K7 -> 42004 | K7: ='Revenues, COGS & SG&A'!L7 -> 42369 | ... AB7: ='Revenues, COGS & SG&A'!AC7 -> 48579
B8: R$ thousand
B10: CASH FLOW FROM OPERATIONS | H10: =SUM(H12:H19) -> 42084.51 | I10: =SUM(I12:I19) -> 63491.881 | J10: =SUM(J12:J19) -> 96384.401 | K10: =SUM(K12:K19) -> 99158.693 | L10: =SUM(L12:L19) -> 80033.961 | M10: =SUM(M12:M19) -> 85363.665 | N10: =SUM(N12:N19) -> 93524.922 | O10: =SUM(O12:O19) -> 170110.15 | ... AB10: =SUM(AB12:AB19) -> #DIV/0!
B12: Net Income | H12: ='Income Statement'!J81 -> 19970.898 | I12: ='Income Statement'!K81 -> 23388.519 | J12: ='Income Statement'!L81 -> 40022.884 | K12: ='Income Statement'!M81 -> 34441.552 | L12: ='Income Statement'!N81 -> 5830.7836 | M12: ='Income Statement'!O81 -> -24.583116 | N12: ='Income Statement'!P81 -> -4551.8246 | O12: ='Income Statement'!Q81 -> 57405.56 | ... AB12: ='Income Statement'!AD81 -> #DIV/0!
B13: Deferred Taxes
B14: Depreciation | H14: ='Fixed Assets & CAPEX'!H77 -> 28006.6 | I14: ='Fixed Assets & CAPEX'!I77 -> 47863.743 | J14: ='Fixed Assets & CAPEX'!J77 -> 63272.849 | K14: ='Fixed Assets & CAPEX'!K77 -> 72311.827 | L14: ='Fixed Assets & CAPEX'!L77 -> 82642.088 | M14: ='Fixed Assets & CAPEX'!M77 -> 94448.101 | N14: ='Fixed Assets & CAPEX'!N77 -> 107940.69 | O14: ='Fixed Assets & CAPEX'!O77 -> 123360.79 | ... AB14: ='Fixed Assets & CAPEX'!AB77 -> 126437.15
B15: Amort. of Acquisition Goodwill | H15: ='Income Statement'!J46 -> 0 | I15: ='Income Statement'!K46 -> 0 | J15: ='Income Statement'!L46 -> 0 | K15: ='Income Statement'!M46 -> 0 | L15: ='Income Statement'!N46 -> 0 | M15: ='Income Statement'!O46 -> 0 | N15: ='Income Statement'!P46 -> 0 | O15: ='Income Statement'!Q46 -> 0 | ... AB15: ='Income Statement'!AD46 -> 0
B16: FX (Gain) / Loss
B17: Equity Income & Others
B18: Provisão Previdenciaria
B19: Changes in Working Capital | H19: =SUM(H20:H32) -> -5892.988 | I19: =SUM(I20:I32) -> -7760.3803 | J19: =SUM(J20:J32) -> -6911.332 | K19: =SUM(K20:K32) -> -7594.6858 | L19: =SUM(L20:L32) -> -8438.9109 | M19: =SUM(M20:M32) -> -9059.8534 | N19: =SUM(N20:N32) -> -9863.94 | O19: =SUM(O20:O32) -> -10656.197 | ... AB19: =SUM(AB20:AB32) -> 0
B20: ='Working Capital'!B13 -> Aplicações de liquidez imediata e valores em trânsito | H20: ='Working Capital'!H13-'Working Capital'!I13 -> 0 | I20: ='Working Capital'!I13-'Working Capital'!J13 -> 0 | J20: ='Working Capital'!J13-'Working Capital'!K13 -> 0 | K20: ='Working Capital'!K13-'Working Capital'!L13 -> 0 | L20: ='Working Capital'!L13-'Working Capital'!M13 -> 0 | M20: ='Working Capital'!M13-'Working Capital'!N13 -> 0 | N20: ='Working Capital'!N13-'Working Capital'!O13 -> 0 | O20: ='Working Capital'!O13-'Working Capital'!P13 -> 0 | ... AB20: ='Working Capital'!AB13-'Working Capital'!AC13 -> 0
B21: ='Working Capital'!B14 -> Reserva Técnica | H21: ='Working Capital'!H14-'Working Capital'!I14 -> -12995.028 | I21: ='Working Capital'!I14-'Working Capital'!J14 -> -17112.942 | J21: ='Working Capital'!J14-'Working Capital'!K14 -> -15240.648 | K21: ='Working Capital'!K14-'Working Capital'!L14 -> -16747.557 | L21: ='Working Capital'!L14-'Working Capital'!M14 -> -18609.215 | M21: ='Working Capital'!M14-'Working Capital'!N14 -> -19978.498 | N21: ='Working Capital'!N14-'Working Capital'!O14 -> -21751.644 | O21: ='Working Capital'!O14-'Working Capital'!P14 -> -23498.703 | ... AB21: ='Working Capital'!AB14-'Working Capital'!AC14 -> 0
B22: ='Working Capital'!B15 -> Créd. operações pl. de assist. à saúde | H22: ='Working Capital'!H15-'Working Capital'!I15 -> -8012.2795 | I22: ='Working Capital'!I15-'Working Capital'!J15 -> -10551.241 | J22: ='Working Capital'!J15-'Working Capital'!K15 -> -9396.8499 | K22: ='Working Capital'!K15-'Working Capital'!L15 -> -10325.958 | L22: ='Working Capital'!L15-'Working Capital'!M15 -> -11473.791 | M22: ='Working Capital'!M15-'Working Capital'!N15 -> -12318.043 | N22: ='Working Capital'!N15-'Working Capital'!O15 -> -13411.302 | O22: ='Working Capital'!O15-'Working Capital'!P15 -> -14488.478 | ... AB22: ='Working Capital'!AB15-'Working Capital'!AC15 -> 0
B23: ='Working Capital'!B16 -> Despesas de comercialização diferidas | H23: ='Working Capital'!H16-'Working Capital'!I16 -> -714.97806 | I23: ='Working Capital'!I16-'Working Capital'!J16 -> -941.54302 | J23: ='Working Capital'!J16-'Working Capital'!K16 -> -838.53061 | K23: ='Working Capital'!K16-'Working Capital'!L16 -> -921.43982 | L23: ='Working Capital'!L16-'Working Capital'!M16 -> -1023.867 | M23: ='Working Capital'!M16-'Working Capital'!N16 -> -1099.2041 | N23: ='Working Capital'!N16-'Working Capital'!O16 -> -1196.7614 | O23: ='Working Capital'!O16-'Working Capital'!P16 -> -1292.8835 | ... AB23: ='Working Capital'!AB16-'Working Capital'!AC16 -> 0
B24: ='Working Capital'!B17 -> Títulos e créditos a receber | H24: ='Working Capital'!H17-'Working Capital'!I17 -> -3942.561 | I24: ='Working Capital'!I17-'Working Capital'!J17 -> -5191.8947 | J24: ='Working Capital'!J17-'Working Capital'!K17 -> -4623.8594 | K24: ='Working Capital'!K17-'Working Capital'!L17 -> -5081.0408 | L24: ='Working Capital'!L17-'Working Capital'!M17 -> -5645.8491 | M24: ='Working Capital'!M17-'Working Capital'!N17 -> -6061.2757 | N24: ='Working Capital'!N17-'Working Capital'!O17 -> -6599.2303 | O24: ='Working Capital'!O17-'Working Capital'!P17 -> -7129.2706 | ... AB24: ='Working Capital'!AB17-'Working Capital'!AC17 -> 0
B25: ='Working Capital'!B18 -> Outros valores e bens | H25: ='Working Capital'!H18-'Working Capital'!I18 -> -2464.2609 | I25: ='Working Capital'!I18-'Working Capital'!J18 -> -3245.1452 | J25: ='Working Capital'!J18-'Working Capital'!K18 -> -2890.1001 | K25: ='Working Capital'!K18-'Working Capital'!L18 -> -3175.857 | L25: ='Working Capital'!L18-'Working Capital'!M18 -> -3528.8852 | M25: ='Working Capital'!M18-'Working Capital'!N18 -> -3788.5437 | N25: ='Working Capital'!N18-'Working Capital'!O18 -> -4124.7872 | O25: ='Working Capital'!O18-'Working Capital'!P18 -> -4456.0839 | ... AB25: ='Working Capital'!AB18-'Working Capital'!AC18 -> 0
B26: ='Working Capital'!B21 -> Débitos de operações de assit. à saúde | H26: ='Working Capital'!I21-'Working Capital'!H21 -> 370.38579 | I26: ='Working Capital'!J21-'Working Capital'!I21 -> 487.75504 | J26: ='Working Capital'!K21-'Working Capital'!J21 -> 434.3907 | K26: ='Working Capital'!L21-'Working Capital'!K21 -> 477.34082 | L26: ='Working Capital'!M21-'Working Capital'!L21 -> 530.40201 | M26: ='Working Capital'!N21-'Working Capital'!M21 -> 569.42946 | N26: ='Working Capital'!O21-'Working Capital'!N21 -> 619.96787 | O26: ='Working Capital'!P21-'Working Capital'!O21 -> 669.76275 | ... AB26: ='Working Capital'!AC21-'Working Capital'!AB21 -> 0
B27: ='Working Capital'!B22 -> Débitos de oper. assist. à saúde não rel. c/plano de saúde da op. | H27: ='Working Capital'!I22-'Working Capital'!H22 -> 2966.9327 | I27: ='Working Capital'!J22-'Working Capital'!I22 -> 3907.1056 | J27: ='Working Capital'!K22-'Working Capital'!J22 -> 3479.6367 | K27: ='Working Capital'!L22-'Working Capital'!K22 -> 3823.6837 | L27: ='Working Capital'!M22-'Working Capital'!L22 -> 4248.7242 | M27: ='Working Capital'!N22-'Working Capital'!M22 -> 4561.3491 | N27: ='Working Capital'!O22-'Working Capital'!N22 -> 4966.1812 | O27: ='Working Capital'!P22-'Working Capital'!O22 -> 5365.0574 | ... AB27: ='Working Capital'!AC22-'Working Capital'!AB22 -> 0
B28: ='Working Capital'!B23 -> Taxes | H28: ='Working Capital'!I23-'Working Capital'!H23 -> 2466.6743 | I28: ='Working Capital'!J23-'Working Capital'!I23 -> 3248.3234 | J28: ='Working Capital'!K23-'Working Capital'!J23 -> 2892.9306 | K28: ='Working Capital'!L23-'Working Capital'!K23 -> 3178.9674 | L28: ='Working Capital'!M23-'Working Capital'!L23 -> 3532.3413 | M28: ='Working Capital'!N23-'Working Capital'!M23 -> 3792.2541 | N28: ='Working Capital'!O23-'Working Capital'!N23 -> 4128.8269 | O28: ='Working Capital'!P23-'Working Capital'!O23 -> 4460.4481 | ... AB28: ='Working Capital'!AC23-'Working Capital'!AB23 -> 0
B29: ='Working Capital'!B24 -> Provisões técnicas de operações de assist. à saúde | H29: ='Working Capital'!I24-'Working Capital'!H24 -> 16432.127 | I29: ='Working Capital'!J24-'Working Capital'!I24 -> 21639.201 | J29: ='Working Capital'!K24-'Working Capital'!J24 -> 19271.698 | K29: ='Working Capital'!L24-'Working Capital'!K24 -> 21177.175 | L29: ='Working Capital'!M24-'Working Capital'!L24 -> 23531.229 | M29: ='Working Capital'!N24-'Working Capital'!M24 -> 25262.678 | N29: ='Working Capital'!O24-'Working Capital'!N24 -> 27504.809 | O29: ='Working Capital'!P24-'Working Capital'!O24 -> 29713.954 | ... AB29: ='Working Capital'!AC24-'Working Capital'!AB24 -> 0
B30: ='Working Capital'!B25 -> Débitos diversos | H30: ='Working Capital'!I25-'Working Capital'!H25 -> 0 | I30: ='Working Capital'!J25-'Working Capital'!I25 -> 0 | J30: ='Working Capital'!K25-'Working Capital'!J25 -> 0 | K30: ='Working Capital'!L25-'Working Capital'!K25 -> 0 | L30: ='Working Capital'!M25-'Working Capital'!L25 -> 0 | M30: ='Working Capital'!N25-'Working Capital'!M25 -> 0 | N30: ='Working Capital'!O25-'Working Capital'!N25 -> 0 | O30: ='Working Capital'!P25-'Working Capital'!O25 -> 0 | ... AB30: ='Working Capital'!AC25-'Working Capital'!AB25 -> 0
B31: =+'Working Capital'!B26 -> Empréstimos de coligadas | H31: ='Working Capital'!I26-'Working Capital'!H26 -> 0 | I31: ='Working Capital'!J26-'Working Capital'!I26 -> 0 | J31: ='Working Capital'!K26-'Working Capital'!J26 -> 0 | K31: ='Working Capital'!L26-'Working Capital'!K26 -> 0 | L31: ='Working Capital'!M26-'Working Capital'!L26 -> 0 | M31: ='Working Capital'!N26-'Working Capital'!M26 -> 0 | N31: ='Working Capital'!O26-'Working Capital'!N26 -> 0 | O31: ='Working Capital'!P26-'Working Capital'!O26 -> 0 | ... AB31: ='Working Capital'!AC26-'Working Capital'!AB26 -> 0
B32: =+'Working Capital'!B27 -> Other Non-Op. Cur. Liabilities | H32: ='Working Capital'!I27-'Working Capital'!H27 -> 0 | I32: ='Working Capital'!J27-'Working Capital'!I27 -> 0 | J32: ='Working Capital'!K27-'Working Capital'!J27 -> 0 | K32: ='Working Capital'!L27-'Working Capital'!K27 -> 0 | L32: ='Working Capital'!M27-'Working Capital'!L27 -> 0 | M32: ='Working Capital'!N27-'Working Capital'!M27 -> 0 | N32: ='Working Capital'!O27-'Working Capital'!N27 -> 0 | O32: ='Working Capital'!P27-'Working Capital'!O27 -> 0 | ... AB32: ='Working Capital'!AC27-'Working Capital'!AB27 -> 0
B34: CASH FLOW FROM INVESTING | H34: =SUM(H36:H39) -> -139000 | I34: =SUM(I36:I39) -> -107863.74 | J34: =SUM(J36:J39) -> -63272.849 | K34: =SUM(K36:K39) -> -72311.827 | L34: =SUM(L36:L39) -> -82642.088 | M34: =SUM(M36:M39) -> -94448.101 | N34: =SUM(N36:N39) -> -107940.69 | O34: =SUM(O36:O39) -> -123360.79 | ... AB34: =SUM(AB36:AB39) -> -126437.15
B36: CAPEX | H36: =-'Fixed Assets & CAPEX'!H35 -> -139000 | I36: =-'Fixed Assets & CAPEX'!I35 -> -107863.74 | J36: =-'Fixed Assets & CAPEX'!J35 -> -63272.849 | K36: =-'Fixed Assets & CAPEX'!K35 -> -72311.827 | L36: =-'Fixed Assets & CAPEX'!L35 -> -82642.088 | M36: =-'Fixed Assets & CAPEX'!M35 -> -94448.101 | N36: =-'Fixed Assets & CAPEX'!N35 -> -107940.69 | O36: =-'Fixed Assets & CAPEX'!O35 -> -123360.79 | ... AB36: =-'Fixed Assets & CAPEX'!AB35 -> -126437.15
B37: Sale of Fixed Assets | H37: 0 | I37: 0 | J37: 0 | K37: 0 | L37: 0 | M37: 0 | N37: 0 | O37: 0 | P37: 0 | Q37: 0 | R37: 0 | S37: 0 | T37: 0 | U37: 0 | V37: 0 | W37: 0 | X37: 0 | Y37: 0 | Z37: 0 | AA37: 0 | AB37: 0
B38: Investments | J38: 0 | K38: 0 | L38: 0 | M38: 0 | N38: 0 | O38: 0 | P38: 0 | Q38: 0 | R38: 0 | S38: 0 | T38: 0 | U38: 0 | V38: 0 | W38: 0 | X38: 0 | Y38: 0 | Z38: 0 | AA38: 0 | AB38: 0
B39: Changes in Long Term Assets
B41: FREE CASH FLOW | H41: =H10+H34 -> -96915.49 | I41: =I10+I34 -> -44371.862 | J41: =J10+J34 -> 33111.552 | K41: =K10+K34 -> 26846.866 | L41: =L10+L34 -> -2608.1272 | M41: =M10+M34 -> -9084.4365 | N41: =N10+N34 -> -14415.765 | O41: =O10+O34 -> 46749.363 | ... AB41: =AB10+AB34 -> #DIV/0!
B43: CASH FLOW FROM FINANCING | H43: =SUM(H45:H54) -> 17873 | I43: =SUM(I45:I54) -> 60793.211 | J43: =SUM(J45:J54) -> -78382.043 | K43: =SUM(K45:K54) -> -129321.79 | L43: =SUM(L45:L54) -> -152160.24 | M43: =SUM(M45:M54) -> -253829.56 | N43: =SUM(N45:N54) -> -357942.41 | O43: =SUM(O45:O54) -> -372730.74 | ... AB43: =SUM(AB45:AB54) -> #VALUE!
B45: Cash Dividends Paid | H45: =-'Balance Sheet'!I53 -> 0 | I45: =-'Balance Sheet'!J53 -> 0 | J45: =-'Balance Sheet'!K53 -> 0 | K45: =-'Balance Sheet'!L53 -> 0 | L45: =-'Balance Sheet'!M53 -> 0 | M45: =-'Balance Sheet'!N53 -> 0 | N45: =-'Balance Sheet'!O53 -> 0 | O45: =-'Balance Sheet'!P53 -> 0 | ... AB45: =-'Balance Sheet'!AC53 -> #VALUE!
B46: Issuance / (Retirement) of Equity | N46: ='Goodwill, Taxes & Div.'!N53 -> 0 | O46: ='Goodwill, Taxes & Div.'!O53 -> 0 | P46: ='Goodwill, Taxes & Div.'!P53 -> 0 | Q46: ='Goodwill, Taxes & Div.'!Q53 -> 0 | R46: ='Goodwill, Taxes & Div.'!R53 -> 0 | S46: ='Goodwill, Taxes & Div.'!S53 -> 0 | T46: ='Goodwill, Taxes & Div.'!T53 -> 0 | U46: ='Goodwill, Taxes & Div.'!U53 -> 0 | ... AB46: ='Goodwill, Taxes & Div.'!AB53 -> 0
B47: Revolving Leverage
B48: Capex Lev
B49: Provisão Previdenciaria
B50: De-Leverage CapEx
B51: Debt Issuance | H51: ='ST Inv. & Debt'!H28-(IF('ST Inv. & Debt'!D128="N",'ST Inv. & Debt'!D125,0)) -> 95360 | I51: ='ST Inv. & Debt'!I28 -> 132359.12 | J51: ='ST Inv. & Debt'!J28 -> 31636.424 | K51: ='ST Inv. & Debt'!K28 -> 36155.914 | L51: ='ST Inv. & Debt'!L28 -> 41321.044 | M51: ='ST Inv. & Debt'!M28 -> 47224.051 | N51: ='ST Inv. & Debt'!N28 -> 53970.343 | O51: ='ST Inv. & Debt'!O28 -> 61680.393 | P51: ='ST Inv. & Debt'!P28 -> 60563.306 | ... AB51: ='ST Inv. & Debt'!AB28 -> 63218.573
B52: Debt Reduction | H52: ='ST Inv. & Debt'!H29 -> -53291 | I52: ='ST Inv. & Debt'!I29 -> -48163.912 | J52: ='ST Inv. & Debt'!J29 -> -87412.467 | K52: ='ST Inv. & Debt'!K29 -> -141041.7 | L52: ='ST Inv. & Debt'!L29 -> -176494.28 | M52: ='ST Inv. & Debt'!M29 -> -284066.61 | N52: ='ST Inv. & Debt'!N29 -> -394925.76 | O52: ='ST Inv. & Debt'!O29 -> -417424.13 | ... AB52: ='ST Inv. & Debt'!AB29 -> #VALUE!
B53: ='Balance Sheet'!C69 -> Tributos e contribuições a recolher - parcelamento | H53: =-'Balance Sheet'!I51 -> -24196 | I53: =-'Balance Sheet'!J51 -> -23402 | J53: =-'Balance Sheet'!K51 -> -22606 | K53: =-'Balance Sheet'!L51 -> -24436 | L53: =-'Balance Sheet'!M51 -> -16987 | M53: =-'Balance Sheet'!N51 -> -16987 | N53: =-'Balance Sheet'!O51 -> -16987 | O53: =-'Balance Sheet'!P51 -> -16987 | ... Z53: =-'Balance Sheet'!AA51 -> 0
B54: Redução Partes Relacionadas | H54: ='Balance Sheet'!J60-'Balance Sheet'!I60 -> 0 | I54: ='Balance Sheet'!K60-'Balance Sheet'!J60 -> 0 | J54: ='Balance Sheet'!L60-'Balance Sheet'!K60 -> 0 | K54: ='Balance Sheet'!M60-'Balance Sheet'!L60 -> 0 | L54: ='Balance Sheet'!N60-'Balance Sheet'!M60 -> 0 | M54: ='Balance Sheet'!O60-'Balance Sheet'!N60 -> 0 | N54: ='Balance Sheet'!P60-'Balance Sheet'!O60 -> 0 | O54: ='Balance Sheet'!Q60-'Balance Sheet'!P60 -> 0 | ... AB54: ='Balance Sheet'!AD60-'Balance Sheet'!AC60 -> 0
B56: NET CHANGE IN CASH | H56: =H41+H43 -> -79042.49 | I56: =I41+I43 -> 16421.349 | J56: =J41+J43 -> -45270.491 | K56: =K41+K43 -> -102474.92 | L56: =L41+L43 -> -154768.37 | M56: =M41+M43 -> -262913.99 | N56: =N41+N43 -> -372358.18 | O56: =O41+O43 -> -325981.38 | ... AB56: =AB41+AB43 -> #DIV/0!
B58: Beg. of the Period Cash | H58: ='Balance Sheet'!I13 -> 228486 | I58: ='Balance Sheet'!J13 -> 149443.51 | J58: ='Balance Sheet'!K13 -> 165864.86 | K58: ='Balance Sheet'!L13 -> 120594.37 | L58: ='Balance Sheet'!M13 -> 70000 | M58: ='Balance Sheet'!N13 -> 70000 | N58: ='Balance Sheet'!O13 -> 70000 | O58: ='Balance Sheet'!P13 -> 70000 | ... AB58: ='Balance Sheet'!AC13 -> #VALUE!
B59: END OF PERIOD CASH & ST INV. | H59: =IF(H56+H58<'ST Inv. & Debt'!$F$54,'ST Inv. & Debt'!$F$54,'Cash Flow'!H56+'Cash Flow'!H58) -> 149443.51 | I59: =IF(I56+I58<'ST Inv. & Debt'!$F$54,'ST Inv. & Debt'!$F$54,'Cash Flow'!I56+'Cash Flow'!I58) -> 165864.86 | J59: =IF(J56+J58<'ST Inv. & Debt'!$F$54,'ST Inv. & Debt'!$F$54,'Cash Flow'!J56+'Cash Flow'!J58) -> 120594.37 | K59: =IF(K56+K58<'ST Inv. & Debt'!$F$54,'ST Inv. & Debt'!$F$54,'Cash Flow'!K56+'Cash Flow'!K58) -> 70000 | L59: =IF(L56+L58<'ST Inv. & Debt'!$F$54,'ST Inv. & Debt'!$F$54,'Cash Flow'!L56+'Cash Flow'!L58) -> 70000 | M59: =IF(M56+M58<'ST Inv. & Debt'!$F$54,'ST Inv. & Debt'!$F$54,'Cash Flow'!M56+'Cash Flow'!M58) -> 70000 | N59: =IF(N56+N58<'ST Inv. & Debt'!$F$54,'ST Inv. & Debt'!$F$54,'Cash Flow'!N56+'Cash Flow'!N58) -> 70000 | O59: =IF(O56+O58<'ST Inv. & Debt'!$F$54,'ST Inv. & Debt'!$F$54,'Cash Flow'!O56+'Cash Flow'!O58) -> 70000 | ... AB59: =IF(AB56+AB58<'ST Inv. & Debt'!$F$54,'ST Inv. & Debt'!$F$54,'Cash Flow'!AB56+'Cash Flow'!AB58) -> #DIV/0!
B61: Required Cash
B62: Short Term Investments
B64: ADDITIONAL LEVERAGE Capex
B65: ADDITIONAL LEVERAGE

Sheet Goodwill, Taxes & Div.
B7: GOODWILL, TAXES & DIVIDENDS | D7: =#REF! -> #REF! | E7: =#REF! -> #REF! | F7: =#REF! -> #REF! | G7: =+'Revenues, COGS & SG&A'!C5 -> 40908 | H7: ='Revenues, COGS & SG&A'!I7 -> 41274 | I7: ='Revenues, COGS & SG&A'!J7 -> 41639 | J7: ='Revenues, COGS & SG&A'!K7 -> 42004 | K7: ='Revenues, COGS & SG&A'!L7 -> 42369 | L7: ='Revenues, COGS & SG&A'!M7 -> 42735 | M7: ='Revenues, COGS & SG&A'!N7 -> 43100 | N7: ='Revenues, COGS & SG&A'!O7 -> 43465 | O7: ='Revenues, COGS & SG&A'!P7 -> 43830 | ... AB7: ='Revenues, COGS & SG&A'!AC7 -> 48579
B8: R$ thousand
B10: BALANCE SHEET ACCOUNTS
B12: Deferred Taxes | H12: ='Balance Sheet'!J28 -> 8368 | I12: ='Balance Sheet'!K28 -> 8368 | J12: ='Balance Sheet'!L28 -> 8368 | K12: ='Balance Sheet'!M28 -> 8368 | L12: ='Balance Sheet'!N28 -> 8368 | M12: ='Balance Sheet'!O28 -> 8368 | N12: ='Balance Sheet'!P28 -> 8368 | O12: ='Balance Sheet'!Q28 -> 8368 | ... AB12: ='Balance Sheet'!AD28 -> 8368
B13: Acquisition Goodwill | H13: 0 | I13: 0 | J13: 0 | K13: 0 | L13: 0 | M13: 0 | N13: 0 | O13: 0 | P13: 0 | Q13: 0 | R13: 0 | S13: 0 | T13: 0 | U13: 0 | V13: 0 | W13: 0 | X13: 0 | Y13: 0 | Z13: 0 | AA13: 0 | AB13: 0
B14: Retained Earnings
B15: Dividends Payable | H15: =H55 -> 0 | I15: =I55 -> 0 | J15: =J55 -> 0 | K15: =K55 -> 0 | L15: =L55 -> 0 | M15: =M55 -> 0 | N15: =N55 -> 0 | O15: =O55 -> 0 | ... AB15: =AB55 -> #DIV/0!
B17: INCOME STATEMENT ACCOUNTS
B19: Current Taxes
B20: Deferred Taxes
B22: CASH FLOW ACCOUNTS
B24: Deferred Taxes
B25: Dividends Paid
B27: GOODWILL AMORTIZATION
B29: Goodwill Initial Balance | H29: 0 | I29: =H32 -> 0 | J29: =I32 -> 0 | K29: =J32 -> 0 | L29: =K32 -> 0 | M29: =L32 -> 0 | N29: =M32 -> 0 | O29: =N32 -> 0 | P29: =O32 -> 0 | ... AB29: =AA32 -> 0
B30: Goodwill Amortiz. (%) | H30: 0.075 | I30: 0.15 | J30: =I30 -> 0.15 | K30: =J30 -> 0.15 | L30: =K30 -> 0.15 | M30: =L30 -> 0.15 | N30: =M30 -> 0.15 | O30: =1-SUM(H30:N30) -> 0.025
B31: Goodwill Amortization | H31: =$H$29*(H30) -> 0 | I31: =$H$29*(I30) -> 0 | J31: =$H$29*(J30) -> 0 | K31: =$H$29*(K30) -> 0 | L31: =$H$29*(L30) -> 0 | M31: =$H$29*(M30) -> 0 | N31: =$H$29*(N30) -> 0 | O31: =$H$29*(O30) -> 0 | ... AB31: =$H$29*(AB30) -> 0
B32: Goodwill Final Balance | H32: =H29-H31 -> 0 | I32: =I29-I31 -> 0 | J32: =J29-J31 -> 0 | K32: =K29-K31 -> 0 | L32: =L29-L31 -> 0 | M32: =M29-M31 -> 0 | N32: =N29-N31 -> 0 | O32: =O29-O31 -> 0 | ... AB32: =AB29-AB31 -> 0
B34: DEFERRED TAX ASSETS
B36: Deferred Taxes Initial Balance | F36: ='Balance Sheet'!I28 -> 8368 | H36: =F36 -> 8368 | I36: =H40 -> #REF! | J36: =I40 -> #REF! | K36: =J40 -> #REF! | L36: =K40 -> #REF! | M36: =L40 -> #REF! | N36: =M40 -> #REF! | O36: =N40 -> #REF! | P36: =O40 -> #REF! | ... AB36: =AA40 -> #REF!
